Workbook
Name Pay: #REF!
Name Payments: #REF!
Name pick: #REF!
Name Status: #REF!
Name Type: #REF!
Name Pay: #REF!
Name Payments: #REF!
Name pick: #REF!
Name Status: #REF!
Name Type: #REF!
Name 切片器_月份: #N/A
Name may: #REF!
Name 结果: #REF!
Name 每日: #REF!
Name 我: #REF!
Name Pay: #REF!
Name Payments: #REF!
Name pick: #REF!
Name Status: #REF!
Name Type: #REF!
Name may: #REF!
Name 结果: #REF!
Name 每日: #REF!
Name 我: #REF!

Sheet Summary
B1: FY2026年6月度Payroll薪酬表
B2: HRO｜开弈集团 | P2: 15000 | Q2: 元/年
B3: 账期：202606 | D3: h=d+c+b+e+f1 | F3: d | G3: c | H3: b | I3: e | N3: f1 | P3: 1250 | Q3: 元/月
H4: 每月固定部分 | I4: 每月固定部分 | N4: 每月固定部分 | O4: 福利费
C6: 成本中心(BU) | D6: 企业人力成本总计 | F6: 实收工资 | G6: 个人所得税 | H6: 法定社会保险 （公司成本） | I6: 法定社会保险 （代扣个人） | K6: 绩效&佣金合计&津贴 | L6: 已包含 考勤调整 | N6: 商业保险（公司成本） | O6: 预提福利费
B7: 集团IIT | C7: G-集团管理层 | D7: 106908.76 | E7: 2 | F7: 94463.13 | G7: 2036.87 | H7: 6540 | I7: 3500 | K7: 0 | N7: 368.76 | O7: 1250
C8: G-Jenny-家庭 | D8: 16328.25 | E8: 2 | F8: 15295.46 | G8: 704.54 | H8: 0 | I8: 0 | K8: 0 | L8: 0 | N8: 328.25 | O8: 2500
C9: G-香港办 | D9: 64050 | E9: 3 | F9: 57950 | H9: 3050 | I9: 3050 | K9: 0 | L9: 0
C10: G-管培生 | D10: 36928.73 | E10: 5 | F10: 36774.62 | G10: 154.11 | H10: 0 | K10: 0 | L10: 4928.73 | O10: 5000
C11: G-时代人才 | D11: 35605.69 | E11: 2 | F11: 30348.71 | G11: 1728.66 | H11: 2253.22 | I11: 1119.3 | K11: 0 | L11: 0 | N11: 155.8 | O11: 1250
C12: F-大财务部 | D12: 98963.6 | E12: 5 | F12: 64661.44 | G12: 4791.96 | H12: 18175.44 | I12: 10119.6 | K12: 9403 | L12: 0 | N12: 1215.16 | O12: 6250
C13: F-账务部 | D13: 70615.57 | E13: 4 | F13: 44945.59 | G13: 1600.59 | H13: 15412.49 | I13: 7922.1 | K13: -1231.72 | L13: 0 | N13: 734.8 | O13: 5000
C14: 公司费用-待结算&法人&智名 | D14: 15890.32 | E14: 12 | F14: 11560 | G14: 440 | H14: 2434.22 | I14: 1300.3 | K14: 0 | N14: 155.8
B15: 靠普 | C15: Shaun-客服部 | D15: 118776.98 | E15: 8 | F15: 81373.35 | G15: 1573.67 | H15: 22030.9 | I15: 12495.5 | K15: -5116.48 | L15: 0 | N15: 1303.56 | O15: 8750
C16: Shaun-外地 | D16: 62095.51 | E16: 8 | F16: 44096 | G16: 727.19 | H16: 10282.71 | I16: 5831.61 | K16: 1002.8 | L16: 0 | N16: 1158 | O16: 3600
C17: Shaun-雇员服务部 | D17: 40595.3 | E17: 3 | F17: 25561.32 | G17: 936.04 | H17: 8668.34 | I17: 4850.6 | K17: 0 | L17: -331.04 | N17: 579 | O17: 3750
C18: HRO服务-公司销售部 | D18: 4519.83 | E18: 1 | F18: 0 | G18: 0 | H18: 2591.17 | I18: 1448.3 | K18: 0 | L18: 0 | N18: 480.36
C19: HRO服务-代收代付残疾人 | D19: 88006.32 | E19: 16 | F19: 43640 | G19: 0 | H19: 31485.81 | I19: 12880.51 | K19: 0
B20: 公寓 | C20: 园区-公寓&企业服务部 | D20: 124104.96 | E20: 9 | F20: 79312.01 | G20: 3356.47 | H20: 26050.32 | I20: 13926.8 | K20: 9724.59 | L20: 5020.69 | N20: 1459.36 | O20: 10000
B21: 办公 | C21: 园区-商办&企业服务 | D21: 146564.93 | E21: 6 | F21: 108093.04 | G21: 9255.89 | H21: 18440.54 | I21: 9895.1 | K21: 162.57 | L21: -23519.54 | N21: 880.36 | O21: 7500
B22: 大后台 | C22: C-大后台-行政 | D22: 19128.12 | E22: 3 | F22: 15065.35 | G22: 0 | H22: 2434.22 | I22: 1300.3 | K22: -241.15 | L22: 1890 | N22: 328.25 | O22: 3750
B23: 大后台 | C23: C-大后台-法务 | D23: 46980.32 | E23: 3 | F23: 35865.48 | G23: 43.77 | H23: 6559.17 | I23: 4200.3 | K23: -1484 | L23: 0 | N23: 311.6 | O23: 2500
B24: 大后台 | C24: C-大后台-人事 | D24: 14979.67 | E24: 1 | F24: 10892.3 | G24: 187.05 | H24: 2439.22 | I24: 1305.3 | K24: -315.35 | L24: 4200 | N24: 155.8 | O24: 1250
B25: 老龙 | C25: 老龙馄饨 | D25: 28067.36 | E25: 3 | F25: 26118.8 | G25: 1948.56 | H25: 0 | I25: 0 | K25: 0 | L25: 0
B26: 物业 | C26: 物业管理部 | D26: 75536.72 | E26: 4 | F26: 56568.44 | G26: 3013.92 | H26: 9918.66 | I26: 5300.9 | K26: 19166.57 | L26: -1193.31 | N26: 734.8 | O26: 5000
B27: 物业 | C27: 物业维修部 | D27: 42808.72 | E27: 3 | F27: 29255.92 | G27: 666.28 | H27: 8091.32 | I27: 4327.8 | K27: 5900 | L27: 0 | N27: 467.4 | O27: 3750
B28: 物业 | C28: 物业保安部 | D28: 70550.79 | E28: 7 | F28: 50626.91 | G28: 1659.36 | H28: 12300.32 | I28: 5496.8 | K28: 2590.67 | L28: 2892.4 | N28: 467.4 | O28: 8750
B29: 物业 | C29: 物业保洁部 | D29: 57999.44 | E29: 15 | F29: 53381.74 | G29: 571.58 | H29: 2434.22 | I29: 1300.3 | K29: 2115 | L29: -11815.38 | N29: 311.6 | O29: 16250
B30: 物业 | C30: 物业外包保安 | D30: 260500 | E30: 25 | F30: 260500 | G30: 0 | H30: 0 | I30: 0 | K30: 500 | O30: 27500
B31: 小计 | D31: =SUM(D7:D30) -> 1646505.9 | E31: =SUM(E7:E30) -> 150 | F31: =SUM(F7:F30) -> 1276349.6 | G31: =SUM(G7:G30) -> 35396.51 | H31: =SUM(H7:H30) -> 211592.29 | I31: =SUM(I7:I30) -> 111571.42 | J31: =SUM(J7:J30) -> 0 | K31: =SUM(K7:K30) -> 42176.5 | L31: =SUM(L7:L30) -> -17927.45 | N31: =SUM(N7:N30) -> 11596.06 | O31: =SUM(O7:O30) -> 123600
C37: 发薪公司 | D37: 企业人力成本总计 | F37: 实收工资 | G37: 个人所得税 | H37: 法定社会保险 （公司成本） | I37: 法定社会保险 （代扣个人） | K37: 绩效&佣金合计&津贴 | L37: 已包含 考勤调整 | N37: 商业保险（公司成本） | O37: 预提福利费
B38: 开弈人才系 | C38: 开弈信息 | D38: 164593.77 | E38: 8 | F38: 105320.53 | G38: 6056.12 | H38: 34497.66 | I38: 17415.9 | K38: -2407.45 | L38: 4200 | N38: 1303.56 | O38: 8750
C39: 开弈中国 | D39: 166656.05 | E39: 5 | F39: 157556.05 | H39: 4550 | I39: 4550 | K39: -742 | L39: 0
C40: 开弈中国-美元 | D40: 2200 | E40: 1 | F40: 2200 | H40: 0 | K40: 0 | L40: 2200
C41: 开弈人才 | D41: 21444.13 | E41: 3 | F41: 10233.62 | G41: 81.94 | H41: 6960.51 | I41: 3531.9 | K41: 0 | L41: -124.14 | N41: 636.16 | O41: 1250
C42: 开弈人力资源 | D42: 231081.36 | E42: 23 | F42: 147096.51 | G42: 5967.81 | H42: 50650.72 | I42: 25470.8 | K42: 6141.52 | L42: 0 | N42: 1895.52 | O42: 10000
C43: 开弈企业外包 | D43: 6449.47 | E43: 2 | F43: 3700 | G43: 40 | H43: 1926.17 | I43: 783.3 | K43: 0
C44: 靠普人力 | D44: 32309.51 | E44: 4 | F44: 20884.45 | G44: 179.05 | H44: 7181.51 | I44: 3752.9 | K44: 0 | L44: -206.9 | N44: 311.6 | O44: 2500
C45: 开博人才 | D45: 1000 | E45: 1 | F45: 960 | G45: 40 | H45: 0 | I45: 0 | K45: 0
C46: 弈享天津 | D46: 2000 | E46: 2 | F46: 1920 | G46: 80 | H46: 0 | I46: 0 | K46: 0 | L46: 0
C47: 北京点才 | D47: 19131.93 | E47: 4 | F47: 11504.99 | G47: 40 | H47: 4969.52 | I47: 2350.02 | K47: 0 | L47: 0 | N47: 267.4 | O47: 600
C48: 天津英才 | D48: 42221.19 | E48: 5 | F48: 31485.55 | G48: 727.19 | H48: 5943.19 | I48: 3442.06 | K48: 1002.8 | L48: 0 | N48: 623.2 | O48: 2400
C49: 智名信息 | D49: 4890.32 | E49: 1 | F49: 1000 | G49: 0 | H49: 2434.22 | I49: 1300.3 | K49: 0 | N49: 155.8
C50: 深圳和弈 | D50: 8254.66 | E50: 2 | F50: 5565.46 | G50: 40 | H50: 1587.26 | I50: 794.54 | K50: 0 | L50: 0 | N50: 267.4 | O50: 600
B51: 开弈投资系 | C51: 开弈投资 | D51: 173588.35 | E51: 13 | F51: 123035.97 | G51: 6715.85 | H51: 26745.42 | I51: 14880.3 | K51: 1260.86 | L51: -21629.54 | N51: 2210.81 | O51: 16250
C52: 弈工分信息 | D52: 325465.93 | E52: 26 | F52: 244214.05 | G52: 10110.64 | H52: 44478.18 | I52: 23845.7 | K52: 33470.97 | L52: 448.42 | N52: 2817.36 | O52: 31250
C53: 弈工分健康 | D53: 92884.43 | E53: 19 | F53: 73649.76 | G53: 496.15 | H53: 12537.32 | I53: 5733.8 | K53: 3895 | L53: -2815.29 | N53: 467.4 | O53: 17500
C54: 弈工分健康（外包保安） | D54: 260000 | E54: 22 | F54: 260000 | H54: 0 | K54: 0 | O54: 27500
C55: 人力资源研究院 | D55: 3899.27 | E55: 1 | F55: 0 | G55: 0 | H55: 2443.17 | I55: 1300.3 | K55: -445.2 | L55: 0 | N55: 155.8 | O55: 1250
C56: 弈工分文化 | D56: 15172.45 | E56: 2 | F56: 13855.46 | G56: 1144.54 | H56: 0 | I56: 0 | K56: 0 | L56: 0 | N56: 172.45 | O56: 1250
C57: 微芮洺 | D57: 9590.02 | E57: 1 | F57: 5699.7 | G57: 0 | H57: 2434.22 | I57: 1300.3 | K57: 0 | L57: 0 | N57: 155.8 | O57: 1250
C58: 时代人才 | D58: 35605.69 | E58: 2 | F58: 30348.71 | G58: 1728.66 | H58: 2253.22 | I58: 1119.3 | K58: 0 | L58: 0 | N58: 155.8 | O58: 1250
C59: 老龙馄饨-灵工 | D59: 28067.36 | E59: 3 | F59: 26118.8 | G59: 1948.56 | H59: 0 | I59: 0 | K59: 0 | L59: 0
C60: 总计 | D60: =SUM(D38:D59) -> 1646505.9 | E60: =SUM(E38:E59) -> 150 | F60: =SUM(F38:F59) -> 1276349.6 | G60: =SUM(G38:G59) -> 35396.51 | H60: =SUM(H38:H59) -> 211592.29 | I60: =SUM(I38:I59) -> 111571.42 | K60: =SUM(K38:K59) -> 42176.5 | L60: =SUM(L38:L59) -> -17927.45 | N60: =SUM(N38:N59) -> 11596.06 | O60: =SUM(O38:O59) -> 123600
D61: =D31-D60 -> 0 | E61: =E31-E60 -> 0 | F61: =F31-F60 -> 0 | G61: =G31-G60 -> 0 | H61: =H31-H60 -> 0 | I61: =I31-I60 -> 0 | J61: =J31-J60 -> 0 | K61: =K31-K60 -> 0 | L61: =L31-L60 -> 0 | N61: =N31-N60 -> 0 | O61: =O31-O60 -> 0
D62: =D60-薪酬明细!K163 -> 0 | F62: =F60-薪酬明细!L163 -> 0 | G62: =G60-薪酬明细!AY163 -> 0 | H62: =H60-薪酬明细!BL161 -> 0 | I62: =I60-薪酬明细!AM163 -> 0 | K62: =K60-薪酬明细!BS161 -> 0 | L62: =L60-薪酬明细!Q161 -> 0 | N62: =N60-薪酬明细!S163 -> 0 | O62: =O60-薪酬明细!BT161 -> 0

Sheet 薪酬明细
B1: 薪资汇总表 | F1: 审核时间 | K1: 考勤统计表 | N1: a1 | O1: 基本薪资: | P1: 求职申请表（劳动劳务合同）、员工流动表；a1'待完成手续； | AB1: 本月工资： | AC1: 计税部分合计 | AE1: 组织管理 | AI1: 人事档案&人事信息统计表 | AN1: 执行责任人 | BN1: 员工福利
B2: -时期 | C2: 2026/6/1-2026/6/30 | K2: -考勤周期 | L2: 2026/6/1-2026/6/30 | N2: a2 | O2: 考勤调整： | P2: 调整天数来自考勤统计表； | AB2: KPI： | AC2: KPI | AE2: -人事任命书 | AI2: -人事信息统计表 | AN2: ✅ | AO2: 发薪 | AP2: 黄欢欢 | BN2: 行业保险补充医疗
B3: -考勤责任人 | C3: 黄燕婷 | F3: 2日发出 | K3: -考勤制表 | L3: 黄燕婷 | N3: a3 | O3: 高温费： | P3: 根据当地政策；含天津历史遗留问题； | AB3: 离职补偿金/年终奖金： | AC3: 根据离职解除协议约定/年终奖公司核算审批额 | AE3: -部门架构发起 | AI3: -薪酬工资表 | AN3: ✅ | AO3: 报税 | AP3: 黄欢欢 | AY3: =AY4-AY5 -> 0 | BN3: 高管健康管理保险
B4: -HR责任人 | C4: 黄一萧 | F4: 3日发出 | K4: -HR审核人 | L4: 黄一萧 | N4: a4 | O4: 补差补扣： | P4: HR与员工签订申请合约所约定委托代扣部分； | AB4: 特殊员工发： | AC4: 开弈人才报销通道发放 | AE4: -组织架构图 | AI4: -人事档案管理 | AN4: ✅ | AO4: 工资单 | AP4: 黄欢欢 | AY4: 35396.51 | BN4: 节日津贴（端午/中秋/春节年会/三八/六一）
B5: -公司终审批人 | C5: 张毅 | F5: 收到文件+2工作日 | N5: a61 | O5: KPI预提： | P5: KPI部分预提，KPI结算时减除； | AB5: 薪资小计： | AC5: 本月薪资汇总 | AE5: -相关内部合规审批权限表统筹管理 | AI5: -人事档案薪酬数据文档抄送 | AN5: ✅ | AO5: 社保/公积金 | AP5: 黄欢欢 | AY5: =AY161 -> 35396.51 | BN5: 生日/婚丧孕
B6: -发放工资单 | C6: 黄欢欢验证工资数据源文件代发工资单 | F6: 3个工作日 | AE6: -相关信息通知到各个部门 | AN6: ✅ | AO6: 福利费申请 | AP6: 黄燕婷 | BN6: 特殊帮助福利
K8: a+e+f | L8: d=a-b-c-c1+sum(g) | O8: a1 | P8: a1' | Q8: a2 | R8: a5 | S8: a6 | T8: a61 | U8: a0=sum(a1..a61) | V8: a75 | AC8: a=sum（a71..a8) | AH8: b1 | AI8: b2 | AJ8: b3 | AK8: b4 | AL8: b5 | AM8: b=sum(b1..b5) | AS8: a0-b | AX8: c1 | AY8: c | AZ8: g1 | BA8: g2 | BB8: h=a0-b-c-c1+sum(g)+f2 | BC8: a8 | BD8: d=a-b-c-c1+sum(g)+f2 | BE8: e1 | BF8: e2 | BG8: e3 | BH8: e4 | BI8: e5 | BJ8: e6 | BK8: e7 | BL8: e=sum(e1..e7) | BN8: f1 | BO8: f2 | BP8: f3 | BQ8: f4 | BR8: f=sum(f1:f4)
A9: 发薪公司验证数据 | B9: 成本中心（P&L核算标准） | C9: 发薪公司 | D9: 人员性质 | E9: 部门 | F9: 汇报人 | G9: 职位 | H9: 所属人 | I9: 姓名 | J9: 考勤制 | K9: 企业人力成本总计 | L9: 实收 | M9: 1 | N9: 计税月份 | O9: 基本工资 | P9: 补贴/补充公积金 | Q9: 考勤调整 | R9: 其他补贴/调整 | S9: 商保金额 | T9: KPI预提 | U9: 本月工资 | V9: 商办佣金 | W9: 绩效 | X9: 公寓佣金 | Y9: 防暑降温费 | Z9: 津贴 | AA9: 保安奖金 | AB9: 保洁奖金 | AC9: 薪资小计 | AD9: 0 | AE9: 社保公积金 缴纳月份 | AF9: 社保基数 | AG9: 公积金基数 | AH9: 养老 | AI9: 医疗 | AJ9: 失业 | AK9: 公积金 | AL9: 补充公积金 | AM9: 个人福利合计 | AN9: 累计子女教育 | AO9: 累计住房贷款利息 | AP9: 累计住房租金 | AQ9: 累计赡养老人 | AR9: 累计继续教育 | AS9: 本期纳税工资 | AT9: 1 | AU9: 累计收入 | AV9: 应纳税所得额 | AW9: 累计已扣税额 | AX9: 上月个税调整 | AY9: 当月个人所得税 | AZ9: 商保调整 | BA9: 个税调整 | BB9: 银行实发 | BC9: 账外实发 | BD9: 实收工资 | BE9: 养老 | BF9: 医疗 | BG9: 失业 | BH9: 工伤 | BI9: 生育 | BJ9: 公积金 | BK9: 补充公积金 | BL9: 公司法定福利合计 | BM9: 2 | BN9: 商业保险 | BO9: 生日/婚丧孕 | BP9: 健康管理服务费 | BQ9: 住房津贴 | BR9: 福利合计 | BS9: 绩效&佣金合计 | BT9: 预提福利费 | BU9: 富平99号项目福利费 | BV9: 备注 | BW9: 发薪公司&姓名 | BX9: 备注 | BY9: 商保 | BZ9: 比例 | CA9: 累积验证 | CB9: 发薪公司验证数据 | CC9: 商保筛选 | CD9: 所属人-姓名
A10: =C10&I10 -> 北京点才孟庆芳 | B10: Shaun-外地 | C10: 北京点才 | D10: 正常计税 | E10: 北京事业部 | F10: 杨崴 | G10: 客服专员 | H10: 孟庆芳 | I10: 孟庆芳 | J10: 全日制 | K10: =AC10+BL10 -> 1600 | L10: =AC10-AM10-AX10-AY10+SUM(AZ10:BA10) -> 1600 | N10: 6 | O10: 1600 | Q10: =VLOOKUP(I10,考勤调整记录!I:W,15,0) -> 0 | U10: =SUM(O10:T10) -> 1600 | AC10: =SUM(O10:T10)+SUM(V10:AB10) -> 1600 | AE10: 202606 | AF10: =VLOOKUP(BW10,'HR|社保明细'!C:F,4,0) -> 0 | AG10: =VLOOKUP($BW10,'HR|社保明细'!$C:G,5,0) -> 0 | AH10: =VLOOKUP($BW10,'HR|社保明细'!$C:H,6,0) -> 0 | AI10: =VLOOKUP($BW10,'HR|社保明细'!$C:I,7,0) -> 0 | AJ10: =VLOOKUP($BW10,'HR|社保明细'!$C:J,8,0) -> 0 | AK10: =VLOOKUP($BW10,'HR|社保明细'!$C:K,9,0) -> 0 | AL10: =VLOOKUP($BW10,'HR|社保明细'!$C:L,10,0) -> 0 | AM10: =SUM(AH10:AL10) -> 0 | AS10: =AC10-AM10-SUM(AN10:AR10) -> 1600 | AU10: =VLOOKUP(BW10,hr.个税累计数据!C:DS,121,0) -> 9600 | AV10: =IF(AU10-5000*N10-VLOOKUP(A10,hr.个税累计数据!C:DT,122,0)-VLOOKUP(A10,hr.个税累计数据!C:DU,123,0)>0,AU10-5000*N10-VLOOKUP(A10,hr.个税累计数据!C:DT,122,0)-VLOOKUP(A10,hr.个税累计数据!C:DU,123,0),0) -> 0 | AW10: =VLOOKUP(BW10,hr.个税累计数据!C:DV,124,0) -> 0 | AY10: =IF(ROUND(MAX(AV10*{0.03,0.1,0.2,0.25,0.3,0.35,0.45}-{0,210,1410,2660,4410,7160,15160}*12)-AW10,2)<=0,0,ROUND(MAX(AV10*{0.03,0.1,0.2,0.25,0.3,0.35,0.45}-{0,210,1410,2660,4410,7160,15160}*12)-AW10,2)) -> 0 | AZ10: =-S10 -> 0 | BB10: =AC10-AM10-AY10-AX10+SUM(AZ10:BA10) -> 1600 | BD10: =AC10-AM10-AX10-AY10+SUM(AZ10:BA10) -> 1600 | BE10: =VLOOKUP($BW10,'HR|社保明细'!C:T,11,0) -> 0 | BF10: =VLOOKUP($BW10,'HR|社保明细'!$C:U,12,0) -> 0 | BG10: =VLOOKUP($BW10,'HR|社保明细'!$C:V,13,0) -> 0 | BH10: =VLOOKUP($BW10,'HR|社保明细'!$C:W,14,0) -> 0 | BI10: =VLOOKUP($BW10,'HR|社保明细'!$C:X,15,0) -> 0 | BJ10: =VLOOKUP($BW10,'HR|社保明细'!$C:Y,16,0) -> 0 | BK10: =VLOOKUP($BW10,'HR|社保明细'!$C:Z,17,0) -> 0 | BL10: =SUM(BE10:BK10) -> 0 | BR10: =SUM(BN10:BQ10) -> 0 | BS10: =SUM(V10:AB10) -> 0 | BW10: =C10&I10 -> 北京点才孟庆芳 | BX10: 无社公 | BY10: 无 | CA10: =VLOOKUP(A10,hr.个税累计数据!C:C,1,0) -> 北京点才孟庆芳 | CB10: 北京点才孟庆芳 | CD10: =H10=I10 -> TRUE
A11: =C11&I11 -> 北京点才尚庆军 | B11: HRO服务-代收代付残疾人 | C11: 北京点才 | D11: 正常计税 | E11: 客户残疾人 | F11: 葛豪平 | G11: 残疾人 | H11: 尚庆军 | I11: 尚庆军 | J11: 代收代付残疾人 | K11: =AC11+BL11 -> 5512.27 | L11: =AC11-AM11-AX11-AY11+SUM(AZ11:BA11) -> 2540 | N11: 6 | O11: =3199.21+167.4-71.6 -> 3295.01 | U11: =SUM(O11:T11) -> 3295.01 | AC11: =SUM(O11:T11)+SUM(V11:AB11) -> 3295.01 | AE11: 202606 | AF11: =VLOOKUP(BW11,'HR|社保明细'!C:F,4,0) -> 7162 | AG11: =VLOOKUP($BW11,'HR|社保明细'!$C:G,5,0) -> 2540 | AH11: =VLOOKUP($BW11,'HR|社保明细'!$C:H,6,0) -> 572.96 | AI11: =VLOOKUP($BW11,'HR|社保明细'!$C:I,7,0) -> 146.24 | AJ11: =VLOOKUP($BW11,'HR|社保明细'!$C:J,8,0) -> 35.81 | AK11: =VLOOKUP($BW11,'HR|社保明细'!$C:K,9,0) -> 0 | AL11: =VLOOKUP($BW11,'HR|社保明细'!$C:L,10,0) -> 0 | AM11: =SUM(AH11:AL11) -> 755.01 | AS11: =AC11-AM11-SUM(AN11:AR11) -> 2540 | AU11: =VLOOKUP(BW11,hr.个税累计数据!C:DS,121,0) -> 19770.06 | AV11: =IF(AU11-5000*N11-VLOOKUP(A11,hr.个税累计数据!C:DT,122,0)-VLOOKUP(A11,hr.个税累计数据!C:DU,123,0)>0,AU11-5000*N11-VLOOKUP(A11,hr.个税累计数据!C:DT,122,0)-VLOOKUP(A11,hr.个税累计数据!C:DU,123,0),0) -> 0 | AW11: =VLOOKUP(BW11,hr.个税累计数据!C:DV,124,0) -> 0 | AY11: =IF(ROUND(MAX(AV11*{0.03,0.1,0.2,0.25,0.3,0.35,0.45}-{0,210,1410,2660,4410,7160,15160}*12)-AW11,2)<=0,0,ROUND(MAX(AV11*{0.03,0.1,0.2,0.25,0.3,0.35,0.45}-{0,210,1410,2660,4410,7160,15160}*12)-AW11,2)) -> 0 | AZ11: =-S11 -> 0 | BB11: =AC11-AM11-AY11-AX11+SUM(AZ11:BA11) -> 2540 | BD11: =AC11-AM11-AX11-AY11+SUM(AZ11:BA11) -> 2540 | BE11: =VLOOKUP($BW11,'HR|社保明细'!C:T,11,0) -> 1145.92 | BF11: =VLOOKUP($BW11,'HR|社保明细'!$C:U,12,0) -> 644.58 | BG11: =VLOOKUP($BW11,'HR|社保明细'!$C:V,13,0) -> 35.81 | BH11: =VLOOKUP($BW11,'HR|社保明细'!$C:W,14,0) -> 28.65 | BI11: =VLOOKUP($BW11,'HR|社保明细'!$C:X,15,0) -> 57.3 | BJ11: =VLOOKUP($BW11,'HR|社保明细'!$C:Y,16,0) -> 305 | BK11: =VLOOKUP($BW11,'HR|社保明细'!$C:Z,17,0) -> 0 | BL11: =SUM(BE11:BK11) -> 2217.26 | BR11: =SUM(BN11:BQ11) -> 0 | BS11: =SUM(V11:AB11) -> 0 | BW11: =C11&I11 -> 北京点才尚庆军 | BY11: 无 | CA11: =VLOOKUP(A11,hr.个税累计数据!C:C,1,0) -> 北京点才尚庆军 | CB11: 北京点才尚庆军 | CD11: =H11=I11 -> TRUE
A12: =C12&I12 -> 北京点才王倩 | B12: 公司费用-待结算&法人&智名 | C12: 北京点才 | D12: 劳务计税 | E12: 公司费用-法人 | F12: 张毅 | G12: 法人 | H12: 王倩 | I12: 王倩 | J12: 非全日制 | K12: =AC12+BL12 -> 1000 | L12: =AC12-AM12-AX12-AY12+SUM(AZ12:BA12) -> 960 | N12: 6 | O12: 1000 | U12: =SUM(O12:T12) -> 1000 | AC12: =SUM(O12:T12)+SUM(V12:AB12) -> 1000 | AE12: 202606 | AF12: =VLOOKUP(BW12,'HR|社保明细'!C:F,4,0) -> 0 | AG12: =VLOOKUP($BW12,'HR|社保明细'!$C:G,5,0) -> 0 | AH12: =VLOOKUP($BW12,'HR|社保明细'!$C:H,6,0) -> 0 | AI12: =VLOOKUP($BW12,'HR|社保明细'!$C:I,7,0) -> 0 | AJ12: =VLOOKUP($BW12,'HR|社保明细'!$C:J,8,0) -> 0 | AK12: =VLOOKUP($BW12,'HR|社保明细'!$C:K,9,0) -> 0 | AL12: =VLOOKUP($BW12,'HR|社保明细'!$C:L,10,0) -> 0 | AM12: =SUM(AH12:AL12) -> 0 | AS12: 1000 | AU12: =VLOOKUP(BW12,hr.个税累计数据!C:DS,121,0) -> 6000 | AV12: =IF(AU12-5000*N12-VLOOKUP(A12,hr.个税累计数据!C:DT,122,0)-VLOOKUP(A12,hr.个税累计数据!C:DU,123,0)>0,AU12-5000*N12-VLOOKUP(A12,hr.个税累计数据!C:DT,122,0)-VLOOKUP(A12,hr.个税累计数据!C:DU,123,0),0) -> 0 | AW12: =VLOOKUP(BW12,hr.个税累计数据!C:DV,124,0) -> 200 | AY12: =IF(D12="国内不计税",0,IF(D12="正常计税",ROUND(MAX(AS12*{0.03,0.1,0.2,0.25,0.3,0.35,0.45}-{0,210,1410,2660,4410,7160,15160},0),2),IF(D12="外籍人",ROUND(MAX(AS12*{0.03,0.1,0.2,0.25,0.3,0.35,0.45}-{0,210,1410,2660,4410,7160,15160},0),2),ROUND(MAX((AS12-IF(AS12<4000,800,AS12*0.2))*10%*{2,3,4}-1000*{0,2,7},0),2)))) -> 40 | AZ12: =-S12 -> 0 | BB12: =AC12-AM12-AY12-AX12+SUM(AZ12:BA12) -> 960 | BD12: =AC12-AM12-AX12-AY12+SUM(AZ12:BA12) -> 960 | BE12: =VLOOKUP($BW12,'HR|社保明细'!C:T,11,0) -> 0 | BF12: =VLOOKUP($BW12,'HR|社保明细'!$C:U,12,0) -> 0 | BG12: =VLOOKUP($BW12,'HR|社保明细'!$C:V,13,0) -> 0 | BH12: =VLOOKUP($BW12,'HR|社保明细'!$C:W,14,0) -> 0 | BI12: =VLOOKUP($BW12,'HR|社保明细'!$C:X,15,0) -> 0 | BJ12: =VLOOKUP($BW12,'HR|社保明细'!$C:Y,16,0) -> 0 | BK12: =VLOOKUP($BW12,'HR|社保明细'!$C:Z,17,0) -> 0 | BL12: =SUM(BE12:BK12) -> 0 | BR12: =SUM(BN12:BQ12) -> 0 | BS12: =SUM(V12:AB12) -> 0 | BW12: =C12&I12 -> 北京点才王倩 | BX12: 无社公 | BY12: 无 | CA12: =VLOOKUP(A12,hr.个税累计数据!C:C,1,0) -> 北京点才王倩 | CB12: 北京点才王倩 | CD12: =H12=I12 -> TRUE
A13: =C13&I13 -> 北京点才杨崴 | B13: Shaun-外地 | C13: 北京点才 | D13: 正常计税 | E13: 北京事业部 | F13: 黄一萧 | G13: 客服专员 | H13: 杨崴 | I13: 杨崴 | J13: 全日制 | K13: =AC13+BL13 -> 11019.66 | L13: =AC13-AM13-AX13-AY13+SUM(AZ13:BA13) -> 6404.99 | N13: 6 | O13: 8000 | Q13: =VLOOKUP(I13,考勤调整记录!I:W,15,0) -> 0 | S13: 267.4 | U13: =SUM(O13:T13) -> 8267.4 | AC13: =SUM(O13:T13)+SUM(V13:AB13) -> 8267.4 | AE13: 202606 | AF13: =VLOOKUP(BW13,'HR|社保明细'!C:F,4,0) -> 7162 | AG13: =VLOOKUP($BW13,'HR|社保明细'!$C:G,5,0) -> 7000 | AH13: =VLOOKUP($BW13,'HR|社保明细'!$C:H,6,0) -> 572.96 | AI13: =VLOOKUP($BW13,'HR|社保明细'!$C:I,7,0) -> 146.24 | AJ13: =VLOOKUP($BW13,'HR|社保明细'!$C:J,8,0) -> 35.81 | AK13: =VLOOKUP($BW13,'HR|社保明细'!$C:K,9,0) -> 840 | AL13: =VLOOKUP($BW13,'HR|社保明细'!$C:L,10,0) -> 0 | AM13: =SUM(AH13:AL13) -> 1595.01 | AS13: =AC13-AM13-SUM(AN13:AR13) -> 6672.39 | AU13: =VLOOKUP(BW13,hr.个税累计数据!C:DS,121,0) -> 48849.15 | AV13: =IF(AU13-5000*N13-VLOOKUP(A13,hr.个税累计数据!C:DT,122,0)-VLOOKUP(A13,hr.个税累计数据!C:DU,123,0)>0,AU13-5000*N13-VLOOKUP(A13,hr.个税累计数据!C:DT,122,0)-VLOOKUP(A13,hr.个税累计数据!C:DU,123,0),0) -> 0 | AW13: =VLOOKUP(BW13,hr.个税累计数据!C:DV,124,0) -> 0 | AY13: =IF(ROUND(MAX(AV13*{0.03,0.1,0.2,0.25,0.3,0.35,0.45}-{0,210,1410,2660,4410,7160,15160}*12)-AW13,2)<=0,0,ROUND(MAX(AV13*{0.03,0.1,0.2,0.25,0.3,0.35,0.45}-{0,210,1410,2660,4410,7160,15160}*12)-AW13,2)) -> 0 | AZ13: =-S13 -> -267.4 | BB13: =AC13-AM13-AY13-AX13+SUM(AZ13:BA13) -> 6404.99 | BD13: =AC13-AM13-AX13-AY13+SUM(AZ13:BA13) -> 6404.99 | BE13: =VLOOKUP($BW13,'HR|社保明细'!C:T,11,0) -> 1145.92 | BF13: =VLOOKUP($BW13,'HR|社保明细'!$C:U,12,0) -> 644.58 | BG13: =VLOOKUP($BW13,'HR|社保明细'!$C:V,13,0) -> 35.81 | BH13: =VLOOKUP($BW13,'HR|社保明细'!$C:W,14,0) -> 28.65 | BI13: =VLOOKUP($BW13,'HR|社保明细'!$C:X,15,0) -> 57.3 | BJ13: =VLOOKUP($BW13,'HR|社保明细'!$C:Y,16,0) -> 840 | BK13: =VLOOKUP($BW13,'HR|社保明细'!$C:Z,17,0) -> 0 | BL13: =SUM(BE13:BK13) -> 2752.26 | BR13: =SUM(BN13:BQ13) -> 0 | BS13: =SUM(V13:AB13) -> 0 | BT13: 600 | BW13: =C13&I13 -> 北京点才杨崴 | BY13: 有 | BZ13: 人才 | CA13: =VLOOKUP(A13,hr.个税累计数据!C:C,1,0) -> 北京点才杨崴 | CB13: 北京点才杨崴 | CC13: 有 | CD13: =H13=I13 -> TRUE
A14: =C14&I14 -> 开博人才王倩 | B14: 公司费用-待结算&法人&智名 | C14: 开博人才 | D14: 劳务计税 | E14: 公司费用-法人 | F14: 张毅 | G14: 法人 | H14: 王倩 | I14: 王倩 | J14: 非全日制 | K14: =AC14+BL14 -> 1000 | L14: =AC14-AM14-AX14-AY14+SUM(AZ14:BA14) -> 960 | N14: 6 | O14: 1000 | U14: =SUM(O14:T14) -> 1000 | AC14: =SUM(O14:T14)+SUM(V14:AB14) -> 1000 | AE14: 202606 | AF14: =VLOOKUP(BW14,'HR|社保明细'!C:F,4,0) -> 0 | AG14: =VLOOKUP($BW14,'HR|社保明细'!$C:G,5,0) -> 0 | AH14: =VLOOKUP($BW14,'HR|社保明细'!$C:H,6,0) -> 0 | AI14: =VLOOKUP($BW14,'HR|社保明细'!$C:I,7,0) -> 0 | AJ14: =VLOOKUP($BW14,'HR|社保明细'!$C:J,8,0) -> 0 | AK14: =VLOOKUP($BW14,'HR|社保明细'!$C:K,9,0) -> 0 | AL14: =VLOOKUP($BW14,'HR|社保明细'!$C:L,10,0) -> 0 | AM14: =SUM(AH14:AL14) -> 0 | AS14: 1000 | AU14: =VLOOKUP(BW14,hr.个税累计数据!C:DS,121,0) -> 6000 | AV14: =IF(AU14-5000*N14-VLOOKUP(A14,hr.个税累计数据!C:DT,122,0)-VLOOKUP(A14,hr.个税累计数据!C:DU,123,0)>0,AU14-5000*N14-VLOOKUP(A14,hr.个税累计数据!C:DT,122,0)-VLOOKUP(A14,hr.个税累计数据!C:DU,123,0),0) -> 0 | AW14: =VLOOKUP(BW14,hr.个税累计数据!C:DV,124,0) -> 200 | AY14: =IF(D14="国内不计税",0,IF(D14="正常计税",ROUND(MAX(AS14*{0.03,0.1,0.2,0.25,0.3,0.35,0.45}-{0,210,1410,2660,4410,7160,15160},0),2),IF(D14="外籍人",ROUND(MAX(AS14*{0.03,0.1,0.2,0.25,0.3,0.35,0.45}-{0,210,1410,2660,4410,7160,15160},0),2),ROUND(MAX((AS14-IF(AS14<4000,800,AS14*0.2))*10%*{2,3,4}-1000*{0,2,7},0),2)))) -> 40 | AZ14: =-S14 -> 0 | BB14: =AC14-AM14-AY14-AX14+SUM(AZ14:BA14) -> 960 | BD14: =AC14-AM14-AX14-AY14+SUM(AZ14:BA14) -> 960 | BE14: =VLOOKUP($BW14,'HR|社保明细'!C:T,11,0) -> 0 | BF14: =VLOOKUP($BW14,'HR|社保明细'!$C:U,12,0) -> 0 | BG14: =VLOOKUP($BW14,'HR|社保明细'!$C:V,13,0) -> 0 | BH14: =VLOOKUP($BW14,'HR|社保明细'!$C:W,14,0) -> 0 | BI14: =VLOOKUP($BW14,'HR|社保明细'!$C:X,15,0) -> 0 | BJ14: =VLOOKUP($BW14,'HR|社保明细'!$C:Y,16,0) -> 0 | BK14: =VLOOKUP($BW14,'HR|社保明细'!$C:Z,17,0) -> 0 | BL14: =SUM(BE14:BK14) -> 0 | BR14: =SUM(BN14:BQ14) -> 0 | BS14: =SUM(V14:AB14) -> 0 | BW14: =C14&I14 -> 开博人才王倩 | BX14: 无社公 | BY14: 无 | CA14: =VLOOKUP(A14,hr.个税累计数据!C:C,1,0) -> 开博人才王倩 | CB14: 开博人才王倩 | CD14: =H14=I14 -> TRUE
A15: =C15&I15 -> 开弈企业外包吴玉斌 | B15: HRO服务-代收代付残疾人 | C15: 开弈企业外包 | D15: 正常计税 | E15: 客户残疾人 | F15: 葛豪平 | G15: 残疾人 | H15: 吴玉斌 | I15: 吴玉斌 | J15: 代收代付残疾人 | K15: =AC15+BL15 -> 5449.47 | L15: =AC15-AM15-AX15-AY15+SUM(AZ15:BA15) -> 2740 | N15: 6 | O15: =3457.55+15.54-7.77+50+23.94-15.96 -> 3523.3 | U15: =SUM(O15:T15) -> 3523.3 | AC15: =SUM(O15:T15)+SUM(V15:AB15) -> 3523.3 | AE15: 202606 | AF15: =VLOOKUP(BW15,'HR|社保明细'!C:F,4,0) -> 7460 | AG15: =VLOOKUP($BW15,'HR|社保明细'!$C:G,5,0) -> 0 | AH15: =VLOOKUP($BW15,'HR|社保明细'!$C:H,6,0) -> 596.8 | AI15: =VLOOKUP($BW15,'HR|社保明细'!$C:I,7,0) -> 149.2 | AJ15: =VLOOKUP($BW15,'HR|社保明细'!$C:J,8,0) -> 37.3 | AK15: =VLOOKUP($BW15,'HR|社保明细'!$C:K,9,0) -> 0 | AL15: =VLOOKUP($BW15,'HR|社保明细'!$C:L,10,0) -> 0 | AM15: =SUM(AH15:AL15) -> 783.3 | AS15: =AC15-AM15-SUM(AN15:AR15) -> 2740 | AU15: =VLOOKUP(BW15,hr.个税累计数据!C:DS,121,0) -> 21139.8 | AV15: =IF(AU15-5000*N15-VLOOKUP(A15,hr.个税累计数据!C:DT,122,0)-VLOOKUP(A15,hr.个税累计数据!C:DU,123,0)>0,AU15-5000*N15-VLOOKUP(A15,hr.个税累计数据!C:DT,122,0)-VLOOKUP(A15,hr.个税累计数据!C:DU,123,0),0) -> 0 | AW15: =VLOOKUP(BW15,hr.个税累计数据!C:DV,124,0) -> 0 | AY15: =IF(ROUND(MAX(AV15*{0.03,0.1,0.2,0.25,0.3,0.35,0.45}-{0,210,1410,2660,4410,7160,15160}*12)-AW15,2)<=0,0,ROUND(MAX(AV15*{0.03,0.1,0.2,0.25,0.3,0.35,0.45}-{0,210,1410,2660,4410,7160,15160}*12)-AW15,2)) -> 0 | AZ15: =-S15 -> 0 | BB15: =AC15-AM15-AY15-AX15+SUM(AZ15:BA15) -> 2740 | BD15: =AC15-AM15-AX15-AY15+SUM(AZ15:BA15) -> 2740 | BE15: =VLOOKUP($BW15,'HR|社保明细'!C:T,11,0) -> 1193.6 | BF15: =VLOOKUP($BW15,'HR|社保明细'!$C:U,12,0) -> 596.8 | BG15: =VLOOKUP($BW15,'HR|社保明细'!$C:V,13,0) -> 37.3 | BH15: =VLOOKUP($BW15,'HR|社保明细'!$C:W,14,0) -> 23.87 | BI15: =VLOOKUP($BW15,'HR|社保明细'!$C:X,15,0) -> 74.6 | BJ15: =VLOOKUP($BW15,'HR|社保明细'!$C:Y,16,0) -> 0 | BK15: =VLOOKUP($BW15,'HR|社保明细'!$C:Z,17,0) -> 0 | BL15: =SUM(BE15:BK15) -> 1926.17 | BR15: =SUM(BN15:BQ15) -> 0 | BS15: =SUM(V15:AB15) -> 0 | BW15: =C15&I15 -> 开弈企业外包吴玉斌 | BY15: 无 | CA15: =VLOOKUP(A15,hr.个税累计数据!C:C,1,0) -> 开弈企业外包吴玉斌 | CB15: 开弈人力资源吴玉斌 | CD15: =H15=I15 -> TRUE
A16: =C16&I16 -> 开弈企业外包王倩 | B16: 公司费用-待结算&法人&智名 | C16: 开弈企业外包 | D16: 劳务计税 | E16: 公司费用-法人 | F16: 张毅 | G16: 法人 | H16: 王倩 | I16: 王倩 | J16: 非全日制 | K16: =AC16+BL16 -> 1000 | L16: =AC16-AM16-AX16-AY16+SUM(AZ16:BA16) -> 960 | N16: 6 | O16: 1000 | U16: =SUM(O16:T16) -> 1000 | AC16: =SUM(O16:T16)+SUM(V16:AB16) -> 1000 | AE16: 202606 | AF16: =VLOOKUP(BW16,'HR|社保明细'!C:F,4,0) -> 0 | AG16: =VLOOKUP($BW16,'HR|社保明细'!$C:G,5,0) -> 0 | AH16: =VLOOKUP($BW16,'HR|社保明细'!$C:H,6,0) -> 0 | AI16: =VLOOKUP($BW16,'HR|社保明细'!$C:I,7,0) -> 0 | AJ16: =VLOOKUP($BW16,'HR|社保明细'!$C:J,8,0) -> 0 | AK16: =VLOOKUP($BW16,'HR|社保明细'!$C:K,9,0) -> 0 | AL16: =VLOOKUP($BW16,'HR|社保明细'!$C:L,10,0) -> 0 | AM16: =SUM(AH16:AL16) -> 0 | AS16: 1000 | AU16: =VLOOKUP(BW16,hr.个税累计数据!C:DS,121,0) -> 6000 | AV16: =IF(AU16-5000*N16-VLOOKUP(A16,hr.个税累计数据!C:DT,122,0)-VLOOKUP(A16,hr.个税累计数据!C:DU,123,0)>0,AU16-5000*N16-VLOOKUP(A16,hr.个税累计数据!C:DT,122,0)-VLOOKUP(A16,hr.个税累计数据!C:DU,123,0),0) -> 0 | AW16: =VLOOKUP(BW16,hr.个税累计数据!C:DV,124,0) -> 200 | AY16: =IF(D16="国内不计税",0,IF(D16="正常计税",ROUND(MAX(AS16*{0.03,0.1,0.2,0.25,0.3,0.35,0.45}-{0,210,1410,2660,4410,7160,15160},0),2),IF(D16="外籍人",ROUND(MAX(AS16*{0.03,0.1,0.2,0.25,0.3,0.35,0.45}-{0,210,1410,2660,4410,7160,15160},0),2),ROUND(MAX((AS16-IF(AS16<4000,800,AS16*0.2))*10%*{2,3,4}-1000*{0,2,7},0),2)))) -> 40 | AZ16: =-S16 -> 0 | BB16: =AC16-AM16-AY16-AX16+SUM(AZ16:BA16) -> 960 | BD16: =AC16-AM16-AX16-AY16+SUM(AZ16:BA16) -> 960 | BE16: =VLOOKUP($BW16,'HR|社保明细'!C:T,11,0) -> 0 | BF16: =VLOOKUP($BW16,'HR|社保明细'!$C:U,12,0) -> 0 | BG16: =VLOOKUP($BW16,'HR|社保明细'!$C:V,13,0) -> 0 | BH16: =VLOOKUP($BW16,'HR|社保明细'!$C:W,14,0) -> 0 | BI16: =VLOOKUP($BW16,'HR|社保明细'!$C:X,15,0) -> 0 | BJ16: =VLOOKUP($BW16,'HR|社保明细'!$C:Y,16,0) -> 0 | BK16: =VLOOKUP($BW16,'HR|社保明细'!$C:Z,17,0) -> 0 | BL16: =SUM(BE16:BK16) -> 0 | BR16: =SUM(BN16:BQ16) -> 0 | BS16: =SUM(V16:AB16) -> 0 | BW16: =C16&I16 -> 开弈企业外包王倩 | BX16: 无社公 | BY16: 无 | CA16: =VLOOKUP(A16,hr.个税累计数据!C:C,1,0) -> 开弈企业外包王倩 | CB16: 开弈企业外包王倩 | CD16: =H16=I16 -> TRUE
A17: =C17&I17 -> 靠普人力英成盛 | B17: HRO服务-代收代付残疾人 | C17: 靠普人力 | D17: 正常计税 | E17: 客户残疾人 | F17: 葛豪平 | G17: 残疾人 | H17: 英成盛 | I17: 英成盛 | J17: 代收代付残疾人 | K17: =AC17+BL17 -> 5449.47 | L17: =AC17-AM17-AX17-AY17+SUM(AZ17:BA17) -> 2740 | N17: 6 | O17: =3457.55+15.54-7.77+50+23.94-15.96 -> 3523.3 | U17: =SUM(O17:T17) -> 3523.3 | AC17: =SUM(O17:T17)+SUM(V17:AB17) -> 3523.3 | AE17: 202606 | AF17: =VLOOKUP(BW17,'HR|社保明细'!C:F,4,0) -> 7460 | AG17: =VLOOKUP($BW17,'HR|社保明细'!$C:G,5,0) -> 0 | AH17: =VLOOKUP($BW17,'HR|社保明细'!$C:H,6,0) -> 596.8 | AI17: =VLOOKUP($BW17,'HR|社保明细'!$C:I,7,0) -> 149.2 | AJ17: =VLOOKUP($BW17,'HR|社保明细'!$C:J,8,0) -> 37.3 | AK17: =VLOOKUP($BW17,'HR|社保明细'!$C:K,9,0) -> 0 | AL17: =VLOOKUP($BW17,'HR|社保明细'!$C:L,10,0) -> 0 | AM17: =SUM(AH17:AL17) -> 783.3 | AS17: =AC17-AM17-SUM(AN17:AR17) -> 2740 | AU17: =VLOOKUP(BW17,hr.个税累计数据!C:DS,121,0) -> 21139.8 | AV17: =IF(AU17-5000*N17-VLOOKUP(A17,hr.个税累计数据!C:DT,122,0)-VLOOKUP(A17,hr.个税累计数据!C:DU,123,0)>0,AU17-5000*N17-VLOOKUP(A17,hr.个税累计数据!C:DT,122,0)-VLOOKUP(A17,hr.个税累计数据!C:DU,123,0),0) -> 0 | AW17: =VLOOKUP(BW17,hr.个税累计数据!C:DV,124,0) -> 0 | AY17: =IF(ROUND(MAX(AV17*{0.03,0.1,0.2,0.25,0.3,0.35,0.45}-{0,210,1410,2660,4410,7160,15160}*12)-AW17,2)<=0,0,ROUND(MAX(AV17*{0.03,0.1,0.2,0.25,0.3,0.35,0.45}-{0,210,1410,2660,4410,7160,15160}*12)-AW17,2)) -> 0 | AZ17: =-S17 -> 0 | BB17: =AC17-AM17-AY17-AX17+SUM(AZ17:BA17) -> 2740 | BD17: =AC17-AM17-AX17-AY17+SUM(AZ17:BA17) -> 2740 | BE17: =VLOOKUP($BW17,'HR|社保明细'!C:T,11,0) -> 1193.6 | BF17: =VLOOKUP($BW17,'HR|社保明细'!$C:U,12,0) -> 596.8 | BG17: =VLOOKUP($BW17,'HR|社保明细'!$C:V,13,0) -> 37.3 | BH17: =VLOOKUP($BW17,'HR|社保明细'!$C:W,14,0) -> 23.87 | BI17: =VLOOKUP($BW17,'HR|社保明细'!$C:X,15,0) -> 74.6 | BJ17: =VLOOKUP($BW17,'HR|社保明细'!$C:Y,16,0) -> 0 | BK17: =VLOOKUP($BW17,'HR|社保明细'!$C:Z,17,0) -> 0 | BL17: =SUM(BE17:BK17) -> 1926.17 | BR17: =SUM(BN17:BQ17) -> 0 | BS17: =SUM(V17:AB17) -> 0 | BW17: =C17&I17 -> 靠普人力英成盛 | BY17: 无 | CA17: =VLOOKUP(A17,hr.个税累计数据!C:C,1,0) -> 靠普人力英成盛 | CB17: 开弈人力资源英成盛 | CD17: =H17=I17 -> TRUE
A18: =C18&I18 -> 开弈人力资源曹保兵 | B18: HRO服务-代收代付残疾人 | C18: 开弈人力资源 | D18: 正常计税 | E18: 客户残疾人 | F18: 葛豪平 | G18: 残疾人 | H18: 曹保兵 | I18: 曹保兵 | J18: 代收代付残疾人 | K18: =AC18+BL18 -> 5449.47 | L18: =AC18-AM18-AX18-AY18+SUM(AZ18:BA18) -> 2740 | N18: 6 | O18: =3457.55+15.54-7.77+50+23.94-15.96 -> 3523.3 | U18: =SUM(O18:T18) -> 3523.3 | AC18: =SUM(O18:T18)+SUM(V18:AB18) -> 3523.3 | AE18: 202606 | AF18: =VLOOKUP(BW18,'HR|社保明细'!C:F,4,0) -> 7460 | AG18: =VLOOKUP($BW18,'HR|社保明细'!$C:G,5,0) -> 0 | AH18: =VLOOKUP($BW18,'HR|社保明细'!$C:H,6,0) -> 596.8 | AI18: =VLOOKUP($BW18,'HR|社保明细'!$C:I,7,0) -> 149.2 | AJ18: =VLOOKUP($BW18,'HR|社保明细'!$C:J,8,0) -> 37.3 | AK18: =VLOOKUP($BW18,'HR|社保明细'!$C:K,9,0) -> 0 | AL18: =VLOOKUP($BW18,'HR|社保明细'!$C:L,10,0) -> 0 | AM18: =SUM(AH18:AL18) -> 783.3 | AS18: =AC18-AM18-SUM(AN18:AR18) -> 2740 | AU18: =VLOOKUP(BW18,hr.个税累计数据!C:DS,121,0) -> 21139.8 | AV18: =IF(AU18-5000*N18-VLOOKUP(A18,hr.个税累计数据!C:DT,122,0)-VLOOKUP(A18,hr.个税累计数据!C:DU,123,0)>0,AU18-5000*N18-VLOOKUP(A18,hr.个税累计数据!C:DT,122,0)-VLOOKUP(A18,hr.个税累计数据!C:DU,123,0),0) -> 0 | AW18: =VLOOKUP(BW18,hr.个税累计数据!C:DV,124,0) -> 0 | AY18: =IF(ROUND(MAX(AV18*{0.03,0.1,0.2,0.25,0.3,0.35,0.45}-{0,210,1410,2660,4410,7160,15160}*12)-AW18,2)<=0,0,ROUND(MAX(AV18*{0.03,0.1,0.2,0.25,0.3,0.35,0.45}-{0,210,1410,2660,4410,7160,15160}*12)-AW18,2)) -> 0 | AZ18: =-S18 -> 0 | BB18: =AC18-AM18-AY18-AX18+SUM(AZ18:BA18) -> 2740 | BD18: =AC18-AM18-AX18-AY18+SUM(AZ18:BA18) -> 2740 | BE18: =VLOOKUP($BW18,'HR|社保明细'!C:T,11,0) -> 1193.6 | BF18: =VLOOKUP($BW18,'HR|社保明细'!$C:U,12,0) -> 596.8 | BG18: =VLOOKUP($BW18,'HR|社保明细'!$C:V,13,0) -> 37.3 | BH18: =VLOOKUP($BW18,'HR|社保明细'!$C:W,14,0) -> 23.87 | BI18: =VLOOKUP($BW18,'HR|社保明细'!$C:X,15,0) -> 74.6 | BJ18: =VLOOKUP($BW18,'HR|社保明细'!$C:Y,16,0) -> 0 | BK18: =VLOOKUP($BW18,'HR|社保明细'!$C:Z,17,0) -> 0 | BL18: =SUM(BE18:BK18) -> 1926.17 | BR18: =SUM(BN18:BQ18) -> 0 | BS18: =SUM(V18:AB18) -> 0 | BW18: =C18&I18 -> 开弈人力资源曹保兵 | BY18: 无 | CA18: =VLOOKUP(A18,hr.个税累计数据!C:C,1,0) -> 开弈人力资源曹保兵 | CB18: 开弈人力资源曹保兵 | CD18: =H18=I18 -> TRUE
A19: =C19&I19 -> 开弈人力资源陶桔林 | B19: HRO服务-代收代付残疾人 | C19: 开弈人力资源 | D19: 正常计税 | E19: 客户残疾人 | F19: 葛豪平 | G19: 残疾人 | H19: 陶桔林 | I19: 陶桔林 | J19: 代收代付残疾人 | K19: =AC19+BL19 -> 5825.47 | L19: =AC19-AM19-AX19-AY19+SUM(AZ19:BA19) -> 2740 | N19: 6 | O19: =3638.55+22.54-7.77+50+23.94-15.96 -> 3711.3 | U19: =SUM(O19:T19) -> 3711.3 | AC19: =SUM(O19:T19)+SUM(V19:AB19) -> 3711.3 | AE19: 202606 | AF19: =VLOOKUP(BW19,'HR|社保明细'!C:F,4,0) -> 7460 | AG19: =VLOOKUP($BW19,'HR|社保明细'!$C:G,5,0) -> 2690 | AH19: =VLOOKUP($BW19,'HR|社保明细'!$C:H,6,0) -> 596.8 | AI19: =VLOOKUP($BW19,'HR|社保明细'!$C:I,7,0) -> 149.2 | AJ19: =VLOOKUP($BW19,'HR|社保明细'!$C:J,8,0) -> 37.3 | AK19: =VLOOKUP($BW19,'HR|社保明细'!$C:K,9,0) -> 188 | AL19: =VLOOKUP($BW19,'HR|社保明细'!$C:L,10,0) -> 0 | AM19: =SUM(AH19:AL19) -> 971.3 | AS19: =AC19-AM19-SUM(AN19:AR19) -> 2740 | AU19: =VLOOKUP(BW19,hr.个税累计数据!C:DS,121,0) -> 22267.8 | AV19: =IF(AU19-5000*N19-VLOOKUP(A19,hr.个税累计数据!C:DT,122,0)-VLOOKUP(A19,hr.个税累计数据!C:DU,123,0)>0,AU19-5000*N19-VLOOKUP(A19,hr.个税累计数据!C:DT,122,0)-VLOOKUP(A19,hr.个税累计数据!C:DU,123,0),0) -> 0 | AW19: =VLOOKUP(BW19,hr.个税累计数据!C:DV,124,0) -> 0 | AY19: =IF(ROUND(MAX(AV19*{0.03,0.1,0.2,0.25,0.3,0.35,0.45}-{0,210,1410,2660,4410,7160,15160}*12)-AW19,2)<=0,0,ROUND(MAX(AV19*{0.03,0.1,0.2,0.25,0.3,0.35,0.45}-{0,210,1410,2660,4410,7160,15160}*12)-AW19,2)) -> 0 | AZ19: =-S19 -> 0 | BB19: =AC19-AM19-AY19-AX19+SUM(AZ19:BA19) -> 2740 | BD19: =AC19-AM19-AX19-AY19+SUM(AZ19:BA19) -> 2740 | BE19: =VLOOKUP($BW19,'HR|社保明细'!C:T,11,0) -> 1193.6 | BF19: =VLOOKUP($BW19,'HR|社保明细'!$C:U,12,0) -> 596.8 | BG19: =VLOOKUP($BW19,'HR|社保明细'!$C:V,13,0) -> 37.3 | BH19: =VLOOKUP($BW19,'HR|社保明细'!$C:W,14,0) -> 23.87 | BI19: =VLOOKUP($BW19,'HR|社保明细'!$C:X,15,0) -> 74.6 | BJ19: =VLOOKUP($BW19,'HR|社保明细'!$C:Y,16,0) -> 188 | BK19: =VLOOKUP($BW19,'HR|社保明细'!$C:Z,17,0) -> 0 | BL19: =SUM(BE19:BK19) -> 2114.17 | BR19: =SUM(BN19:BQ19) -> 0 | BS19: =SUM(V19:AB19) -> 0 | BW19: =C19&I19 -> 开弈人力资源陶桔林 | BY19: 无 | CA19: =VLOOKUP(A19,hr.个税累计数据!C:C,1,0) -> 开弈人力资源陶桔林 | CB19: 开弈人力资源陶桔林 | CD19: =H19=I19 -> TRUE
A20: =C20&I20 -> 开弈人力资源李晓晓 | B20: HRO服务-代收代付残疾人 | C20: 开弈人力资源 | D20: 正常计税 | E20: 客户残疾人 | F20: 葛豪平 | G20: 残疾人 | H20: 李晓晓 | I20: 李晓晓 | J20: 代收代付残疾人 | K20: =AC20+BL20 -> 5449.47 | L20: =AC20-AM20-AX20-AY20+SUM(AZ20:BA20) -> 2740 | N20: 6 | O20: =3457.55+15.54-7.77+50+23.94-15.96 -> 3523.3 | U20: =SUM(O20:T20) -> 3523.3 | AC20: =SUM(O20:T20)+SUM(V20:AB20) -> 3523.3 | AE20: 202606 | AF20: =VLOOKUP(BW20,'HR|社保明细'!C:F,4,0) -> 7460 | AG20: =VLOOKUP($BW20,'HR|社保明细'!$C:G,5,0) -> 0 | AH20: =VLOOKUP($BW20,'HR|社保明细'!$C:H,6,0) -> 596.8 | AI20: =VLOOKUP($BW20,'HR|社保明细'!$C:I,7,0) -> 149.2 | AJ20: =VLOOKUP($BW20,'HR|社保明细'!$C:J,8,0) -> 37.3 | AK20: =VLOOKUP($BW20,'HR|社保明细'!$C:K,9,0) -> 0 | AL20: =VLOOKUP($BW20,'HR|社保明细'!$C:L,10,0) -> 0 | AM20: =SUM(AH20:AL20) -> 783.3 | AS20: =AC20-AM20-SUM(AN20:AR20) -> 2740 | AU20: =VLOOKUP(BW20,hr.个税累计数据!C:DS,121,0) -> 21139.8 | AV20: =IF(AU20-5000*N20-VLOOKUP(A20,hr.个税累计数据!C:DT,122,0)-VLOOKUP(A20,hr.个税累计数据!C:DU,123,0)>0,AU20-5000*N20-VLOOKUP(A20,hr.个税累计数据!C:DT,122,0)-VLOOKUP(A20,hr.个税累计数据!C:DU,123,0),0) -> 0 | AW20: =VLOOKUP(BW20,hr.个税累计数据!C:DV,124,0) -> 0 | AY20: =IF(ROUND(MAX(AV20*{0.03,0.1,0.2,0.25,0.3,0.35,0.45}-{0,210,1410,2660,4410,7160,15160}*12)-AW20,2)<=0,0,ROUND(MAX(AV20*{0.03,0.1,0.2,0.25,0.3,0.35,0.45}-{0,210,1410,2660,4410,7160,15160}*12)-AW20,2)) -> 0 | AZ20: =-S20 -> 0 | BB20: =AC20-AM20-AY20-AX20+SUM(AZ20:BA20) -> 2740 | BD20: =AC20-AM20-AX20-AY20+SUM(AZ20:BA20) -> 2740 | BE20: =VLOOKUP($BW20,'HR|社保明细'!C:T,11,0) -> 1193.6 | BF20: =VLOOKUP($BW20,'HR|社保明细'!$C:U,12,0) -> 596.8 | BG20: =VLOOKUP($BW20,'HR|社保明细'!$C:V,13,0) -> 37.3 | BH20: =VLOOKUP($BW20,'HR|社保明细'!$C:W,14,0) -> 23.87 | BI20: =VLOOKUP($BW20,'HR|社保明细'!$C:X,15,0) -> 74.6 | BJ20: =VLOOKUP($BW20,'HR|社保明细'!$C:Y,16,0) -> 0 | BK20: =VLOOKUP($BW20,'HR|社保明细'!$C:Z,17,0) -> 0 | BL20: =SUM(BE20:BK20) -> 1926.17 | BR20: =SUM(BN20:BQ20) -> 0 | BS20: =SUM(V20:AB20) -> 0 | BW20: =C20&I20 -> 开弈人力资源李晓晓 | BY20: 无 | CA20: =VLOOKUP(A20,hr.个税累计数据!C:C,1,0) -> 开弈人力资源李晓晓 | CB20: 开弈人力资源李晓晓 | CD20: =H20=I20 -> TRUE
A21: =C21&I21 -> 开弈人力资源闫秀文 | B21: HRO服务-代收代付残疾人 | C21: 开弈人力资源 | D21: 正常计税 | E21: 客户残疾人 | F21: 葛豪平 | G21: 残疾人 | H21: 闫秀文 | I21: 闫秀文 | J21: 代收代付残疾人 | K21: =AC21+BL21 -> 5449.47 | L21: =AC21-AM21-AX21-AY21+SUM(AZ21:BA21) -> 2740 | N21: 6 | O21: =3457.55+15.54-7.77+50+23.94-15.96 -> 3523.3 | U21: =SUM(O21:T21) -> 3523.3 | AC21: =SUM(O21:T21)+SUM(V21:AB21) -> 3523.3 | AE21: 202606 | AF21: =VLOOKUP(BW21,'HR|社保明细'!C:F,4,0) -> 7460 | AG21: =VLOOKUP($BW21,'HR|社保明细'!$C:G,5,0) -> 0 | AH21: =VLOOKUP($BW21,'HR|社保明细'!$C:H,6,0) -> 596.8 | AI21: =VLOOKUP($BW21,'HR|社保明细'!$C:I,7,0) -> 149.2 | AJ21: =VLOOKUP($BW21,'HR|社保明细'!$C:J,8,0) -> 37.3 | AK21: =VLOOKUP($BW21,'HR|社保明细'!$C:K,9,0) -> 0 | AL21: =VLOOKUP($BW21,'HR|社保明细'!$C:L,10,0) -> 0 | AM21: =SUM(AH21:AL21) -> 783.3 | AS21: =AC21-AM21-SUM(AN21:AR21) -> 2740 | AU21: =VLOOKUP(BW21,hr.个税累计数据!C:DS,121,0) -> 21139.8 | AV21: =IF(AU21-5000*N21-VLOOKUP(A21,hr.个税累计数据!C:DT,122,0)-VLOOKUP(A21,hr.个税累计数据!C:DU,123,0)>0,AU21-5000*N21-VLOOKUP(A21,hr.个税累计数据!C:DT,122,0)-VLOOKUP(A21,hr.个税累计数据!C:DU,123,0),0) -> 0 | AW21: =VLOOKUP(BW21,hr.个税累计数据!C:DV,124,0) -> 0 | AY21: =IF(ROUND(MAX(AV21*{0.03,0.1,0.2,0.25,0.3,0.35,0.45}-{0,210,1410,2660,4410,7160,15160}*12)-AW21,2)<=0,0,ROUND(MAX(AV21*{0.03,0.1,0.2,0.25,0.3,0.35,0.45}-{0,210,1410,2660,4410,7160,15160}*12)-AW21,2)) -> 0 | AZ21: =-S21 -> 0 | BB21: =AC21-AM21-AY21-AX21+SUM(AZ21:BA21) -> 2740 | BD21: =AC21-AM21-AX21-AY21+SUM(AZ21:BA21) -> 2740 | BE21: =VLOOKUP($BW21,'HR|社保明细'!C:T,11,0) -> 1193.6 | BF21: =VLOOKUP($BW21,'HR|社保明细'!$C:U,12,0) -> 596.8 | BG21: =VLOOKUP($BW21,'HR|社保明细'!$C:V,13,0) -> 37.3 | BH21: =VLOOKUP($BW21,'HR|社保明细'!$C:W,14,0) -> 23.87 | BI21: =VLOOKUP($BW21,'HR|社保明细'!$C:X,15,0) -> 74.6 | BJ21: =VLOOKUP($BW21,'HR|社保明细'!$C:Y,16,0) -> 0 | BK21: =VLOOKUP($BW21,'HR|社保明细'!$C:Z,17,0) -> 0 | BL21: =SUM(BE21:BK21) -> 1926.17 | BR21: =SUM(BN21:BQ21) -> 0 | BS21: =SUM(V21:AB21) -> 0 | BW21: =C21&I21 -> 开弈人力资源闫秀文 | BY21: 无 | CA21: =VLOOKUP(A21,hr.个税累计数据!C:C,1,0) -> 开弈人力资源闫秀文 | CB21: 开弈人力资源闫秀文 | CD21: =H21=I21 -> TRUE
A22: =C22&I22 -> 开弈人力资源施宏宇 | B22: HRO服务-代收代付残疾人 | C22: 开弈人力资源 | D22: 正常计税 | E22: 客户残疾人 | F22: 葛豪平 | G22: 残疾人 | H22: 施宏宇 | I22: 施宏宇 | J22: 代收代付残疾人 | K22: =AC22+BL22 -> 5825.47 | L22: =AC22-AM22-AX22-AY22+SUM(AZ22:BA22) -> 2740 | N22: 6 | O22: =3638.55+22.54-7.77+50+23.94-15.96 -> 3711.3 | U22: =SUM(O22:T22) -> 3711.3 | AC22: =SUM(O22:T22)+SUM(V22:AB22) -> 3711.3 | AE22: 202606 | AF22: =VLOOKUP(BW22,'HR|社保明细'!C:F,4,0) -> 7460 | AG22: =VLOOKUP($BW22,'HR|社保明细'!$C:G,5,0) -> 2690 | AH22: =VLOOKUP($BW22,'HR|社保明细'!$C:H,6,0) -> 596.8 | AI22: =VLOOKUP($BW22,'HR|社保明细'!$C:I,7,0) -> 149.2 | AJ22: =VLOOKUP($BW22,'HR|社保明细'!$C:J,8,0) -> 37.3 | AK22: =VLOOKUP($BW22,'HR|社保明细'!$C:K,9,0) -> 188 | AL22: =VLOOKUP($BW22,'HR|社保明细'!$C:L,10,0) -> 0 | AM22: =SUM(AH22:AL22) -> 971.3 | AS22: =AC22-AM22-SUM(AN22:AR22) -> 2740 | AU22: =VLOOKUP(BW22,hr.个税累计数据!C:DS,121,0) -> 22267.8 | AV22: =IF(AU22-5000*N22-VLOOKUP(A22,hr.个税累计数据!C:DT,122,0)-VLOOKUP(A22,hr.个税累计数据!C:DU,123,0)>0,AU22-5000*N22-VLOOKUP(A22,hr.个税累计数据!C:DT,122,0)-VLOOKUP(A22,hr.个税累计数据!C:DU,123,0),0) -> 0 | AW22: =VLOOKUP(BW22,hr.个税累计数据!C:DV,124,0) -> 0 | AY22: =IF(ROUND(MAX(AV22*{0.03,0.1,0.2,0.25,0.3,0.35,0.45}-{0,210,1410,2660,4410,7160,15160}*12)-AW22,2)<=0,0,ROUND(MAX(AV22*{0.03,0.1,0.2,0.25,0.3,0.35,0.45}-{0,210,1410,2660,4410,7160,15160}*12)-AW22,2)) -> 0 | AZ22: =-S22 -> 0 | BB22: =AC22-AM22-AY22-AX22+SUM(AZ22:BA22) -> 2740 | BD22: =AC22-AM22-AX22-AY22+SUM(AZ22:BA22) -> 2740 | BE22: =VLOOKUP($BW22,'HR|社保明细'!C:T,11,0) -> 1193.6 | BF22: =VLOOKUP($BW22,'HR|社保明细'!$C:U,12,0) -> 596.8 | BG22: =VLOOKUP($BW22,'HR|社保明细'!$C:V,13,0) -> 37.3 | BH22: =VLOOKUP($BW22,'HR|社保明细'!$C:W,14,0) -> 23.87 | BI22: =VLOOKUP($BW22,'HR|社保明细'!$C:X,15,0) -> 74.6 | BJ22: =VLOOKUP($BW22,'HR|社保明细'!$C:Y,16,0) -> 188 | BK22: =VLOOKUP($BW22,'HR|社保明细'!$C:Z,17,0) -> 0 | BL22: =SUM(BE22:BK22) -> 2114.17 | BR22: =SUM(BN22:BQ22) -> 0 | BS22: =SUM(V22:AB22) -> 0 | BW22: =C22&I22 -> 开弈人力资源施宏宇 | BY22: 无 | CA22: =VLOOKUP(A22,hr.个税累计数据!C:C,1,0) -> 开弈人力资源施宏宇 | CB22: 开弈人力资源施宏宇 | CD22: =H22=I22 -> TRUE
A23: =C23&I23 -> 开弈人力资源孙文丽 | B23: HRO服务-代收代付残疾人 | C23: 开弈人力资源 | D23: 正常计税 | E23: 客户残疾人 | F23: 葛豪平 | G23: 残疾人 | H23: 孙文丽 | I23: 孙文丽 | J23: 代收代付残疾人 | K23: =AC23+BL23 -> 5449.47 | L23: =AC23-AM23-AX23-AY23+SUM(AZ23:BA23) -> 2740 | N23: 6 | O23: =3457.55+15.54-7.77+50+23.94-15.96 -> 3523.3 | U23: =SUM(O23:T23) -> 3523.3 | AC23: =SUM(O23:T23)+SUM(V23:AB23) -> 3523.3 | AE23: 202606 | AF23: =VLOOKUP(BW23,'HR|社保明细'!C:F,4,0) -> 7460 | AG23: =VLOOKUP($BW23,'HR|社保明细'!$C:G,5,0) -> 0 | AH23: =VLOOKUP($BW23,'HR|社保明细'!$C:H,6,0) -> 596.8 | AI23: =VLOOKUP($BW23,'HR|社保明细'!$C:I,7,0) -> 149.2 | AJ23: =VLOOKUP($BW23,'HR|社保明细'!$C:J,8,0) -> 37.3 | AK23: =VLOOKUP($BW23,'HR|社保明细'!$C:K,9,0) -> 0 | AL23: =VLOOKUP($BW23,'HR|社保明细'!$C:L,10,0) -> 0 | AM23: =SUM(AH23:AL23) -> 783.3 | AS23: =AC23-AM23-SUM(AN23:AR23) -> 2740 | AU23: =VLOOKUP(BW23,hr.个税累计数据!C:DS,121,0) -> 21139.8 | AV23: =IF(AU23-5000*N23-VLOOKUP(A23,hr.个税累计数据!C:DT,122,0)-VLOOKUP(A23,hr.个税累计数据!C:DU,123,0)>0,AU23-5000*N23-VLOOKUP(A23,hr.个税累计数据!C:DT,122,0)-VLOOKUP(A23,hr.个税累计数据!C:DU,123,0),0) -> 0 | AW23: =VLOOKUP(BW23,hr.个税累计数据!C:DV,124,0) -> 0 | AY23: =IF(ROUND(MAX(AV23*{0.03,0.1,0.2,0.25,0.3,0.35,0.45}-{0,210,1410,2660,4410,7160,15160}*12)-AW23,2)<=0,0,ROUND(MAX(AV23*{0.03,0.1,0.2,0.25,0.3,0.35,0.45}-{0,210,1410,2660,4410,7160,15160}*12)-AW23,2)) -> 0 | AZ23: =-S23 -> 0 | BB23: =AC23-AM23-AY23-AX23+SUM(AZ23:BA23) -> 2740 | BD23: =AC23-AM23-AX23-AY23+SUM(AZ23:BA23) -> 2740 | BE23: =VLOOKUP($BW23,'HR|社保明细'!C:T,11,0) -> 1193.6 | BF23: =VLOOKUP($BW23,'HR|社保明细'!$C:U,12,0) -> 596.8 | BG23: =VLOOKUP($BW23,'HR|社保明细'!$C:V,13,0) -> 37.3 | BH23: =VLOOKUP($BW23,'HR|社保明细'!$C:W,14,0) -> 23.87 | BI23: =VLOOKUP($BW23,'HR|社保明细'!$C:X,15,0) -> 74.6 | BJ23: =VLOOKUP($BW23,'HR|社保明细'!$C:Y,16,0) -> 0 | BK23: =VLOOKUP($BW23,'HR|社保明细'!$C:Z,17,0) -> 0 | BL23: =SUM(BE23:BK23) -> 1926.17 | BR23: =SUM(BN23:BQ23) -> 0 | BS23: =SUM(V23:AB23) -> 0 | BW23: =C23&I23 -> 开弈人力资源孙文丽 | BY23: 无 | CA23: =VLOOKUP(A23,hr.个税累计数据!C:C,1,0) -> 开弈人力资源孙文丽 | CB23: 开弈人力资源孙文丽 | CD23: =H23=I23 -> TRUE
A24: =C24&I24 -> 开弈人才谢宁 | B24: HRO服务-代收代付残疾人 | C24: 开弈人才 | D24: 正常计税 | E24: 客户残疾人 | F24: 葛豪平 | G24: 残疾人 | H24: 谢宁 | I24: 谢宁 | J24: 代收代付残疾人 | K24: =AC24+BL24 -> 5449.47 | L24: =AC24-AM24-AX24-AY24+SUM(AZ24:BA24) -> 2740 | N24: 6 | O24: =3457.55+15.54-7.77+50+23.94-15.96 -> 3523.3 | U24: =SUM(O24:T24) -> 3523.3 | AC24: =SUM(O24:T24)+SUM(V24:AB24) -> 3523.3 | AE24: 202606 | AF24: =VLOOKUP(BW24,'HR|社保明细'!C:F,4,0) -> 7460 | AG24: =VLOOKUP($BW24,'HR|社保明细'!$C:G,5,0) -> 0 | AH24: =VLOOKUP($BW24,'HR|社保明细'!$C:H,6,0) -> 596.8 | AI24: =VLOOKUP($BW24,'HR|社保明细'!$C:I,7,0) -> 149.2 | AJ24: =VLOOKUP($BW24,'HR|社保明细'!$C:J,8,0) -> 37.3 | AK24: =VLOOKUP($BW24,'HR|社保明细'!$C:K,9,0) -> 0 | AL24: =VLOOKUP($BW24,'HR|社保明细'!$C:L,10,0) -> 0 | AM24: =SUM(AH24:AL24) -> 783.3 | AS24: =AC24-AM24-SUM(AN24:AR24) -> 2740 | AU24: =VLOOKUP(BW24,hr.个税累计数据!C:DS,121,0) -> 21139.8 | AV24: =IF(AU24-5000*N24-VLOOKUP(A24,hr.个税累计数据!C:DT,122,0)-VLOOKUP(A24,hr.个税累计数据!C:DU,123,0)>0,AU24-5000*N24-VLOOKUP(A24,hr.个税累计数据!C:DT,122,0)-VLOOKUP(A24,hr.个税累计数据!C:DU,123,0),0) -> 0 | AW24: =VLOOKUP(BW24,hr.个税累计数据!C:DV,124,0) -> 0 | AY24: =IF(ROUND(MAX(AV24*{0.03,0.1,0.2,0.25,0.3,0.35,0.45}-{0,210,1410,2660,4410,7160,15160}*12)-AW24,2)<=0,0,ROUND(MAX(AV24*{0.03,0.1,0.2,0.25,0.3,0.35,0.45}-{0,210,1410,2660,4410,7160,15160}*12)-AW24,2)) -> 0 | AZ24: =-S24 -> 0 | BB24: =AC24-AM24-AY24-AX24+SUM(AZ24:BA24) -> 2740 | BD24: =AC24-AM24-AX24-AY24+SUM(AZ24:BA24) -> 2740 | BE24: =VLOOKUP($BW24,'HR|社保明细'!C:T,11,0) -> 1193.6 | BF24: =VLOOKUP($BW24,'HR|社保明细'!$C:U,12,0) -> 596.8 | BG24: =VLOOKUP($BW24,'HR|社保明细'!$C:V,13,0) -> 37.3 | BH24: =VLOOKUP($BW24,'HR|社保明细'!$C:W,14,0) -> 23.87 | BI24: =VLOOKUP($BW24,'HR|社保明细'!$C:X,15,0) -> 74.6 | BJ24: =VLOOKUP($BW24,'HR|社保明细'!$C:Y,16,0) -> 0 | BK24: =VLOOKUP($BW24,'HR|社保明细'!$C:Z,17,0) -> 0 | BL24: =SUM(BE24:BK24) -> 1926.17 | BR24: =SUM(BN24:BQ24) -> 0 | BS24: =SUM(V24:AB24) -> 0 | BW24: =C24&I24 -> 开弈人才谢宁 | BY24: 有 | CA24: =VLOOKUP(A24,hr.个税累计数据!C:C,1,0) -> 开弈人才谢宁 | CB24: 开弈人力资源谢宁 | CD24: =H24=I24 -> TRUE
A25: =C25&I25 -> 开弈人才徐峰 | B25: HRO服务-公司销售部 | C25: 开弈人才 | D25: 正常计税 | E25: 销售部 | F25: 黄一萧 | G25: 销售 | H25: 徐峰 | I25: 徐峰 | J25: 非全日制 | K25: =AC25+BL25 -> 4519.83 | L25: =AC25-AM25-AX25-AY25+SUM(AZ25:BA25) -> 0 | N25: 6 | O25: =1425.55+29.54-14.77+23.94-15.96 -> 1448.3 | Q25: =VLOOKUP(I25,考勤调整记录!I:W,15,0) -> 0 | S25: 480.36 | U25: =SUM(O25:T25) -> 1928.66 | AC25: =SUM(O25:T25)+SUM(V25:AB25) -> 1928.66 | AE25: 202606 | AF25: =VLOOKUP(BW25,'HR|社保明细'!C:F,4,0) -> 7460 | AG25: =VLOOKUP($BW25,'HR|社保明细'!$C:G,5,0) -> 7384 | AH25: =VLOOKUP($BW25,'HR|社保明细'!$C:H,6,0) -> 596.8 | AI25: =VLOOKUP($BW25,'HR|社保明细'!$C:I,7,0) -> 149.2 | AJ25: =VLOOKUP($BW25,'HR|社保明细'!$C:J,8,0) -> 37.3 | AK25: =VLOOKUP($BW25,'HR|社保明细'!$C:K,9,0) -> 517 | AL25: =VLOOKUP($BW25,'HR|社保明细'!$C:L,10,0) -> 148 | AM25: =SUM(AH25:AL25) -> 1448.3 | AQ25: 3000 | AS25: =AC25-AM25-SUM(AN25:AR25) -> -2519.64 | AU25: =VLOOKUP(BW25,hr.个税累计数据!C:DS,121,0) -> 11336.52 | AV25: =IF(AU25-5000*N25-VLOOKUP(A25,hr.个税累计数据!C:DT,122,0)-VLOOKUP(A25,hr.个税累计数据!C:DU,123,0)>0,AU25-5000*N25-VLOOKUP(A25,hr.个税累计数据!C:DT,122,0)-VLOOKUP(A25,hr.个税累计数据!C:DU,123,0),0) -> 0 | AW25: =VLOOKUP(BW25,hr.个税累计数据!C:DV,124,0) -> 0 | AY25: =IF(ROUND(MAX(AV25*{0.03,0.1,0.2,0.25,0.3,0.35,0.45}-{0,210,1410,2660,4410,7160,15160}*12)-AW25,2)<=0,0,ROUND(MAX(AV25*{0.03,0.1,0.2,0.25,0.3,0.35,0.45}-{0,210,1410,2660,4410,7160,15160}*12)-AW25,2)) -> 0 | AZ25: =-S25 -> -480.36 | BB25: =AC25-AM25-AY25-AX25+SUM(AZ25:BA25) -> 0 | BD25: =AC25-AM25-AX25-AY25+SUM(AZ25:BA25) -> 0 | BE25: =VLOOKUP($BW25,'HR|社保明细'!C:T,11,0) -> 1193.6 | BF25: =VLOOKUP($BW25,'HR|社保明细'!$C:U,12,0) -> 596.8 | BG25: =VLOOKUP($BW25,'HR|社保明细'!$C:V,13,0) -> 37.3 | BH25: =VLOOKUP($BW25,'HR|社保明细'!$C:W,14,0) -> 23.87 | BI25: =VLOOKUP($BW25,'HR|社保明细'!$C:X,15,0) -> 74.6 | BJ25: =VLOOKUP($BW25,'HR|社保明细'!$C:Y,16,0) -> 517 | BK25: =VLOOKUP($BW25,'HR|社保明细'!$C:Z,17,0) -> 148 | BL25: =SUM(BE25:BK25) -> 2591.17 | BR25: =SUM(BN25:BQ25) -> 0 | BS25: =SUM(V25:AB25) -> 0 | BW25: =C25&I25 -> 开弈人才徐峰 | BY25: 有 | CA25: =VLOOKUP(A25,hr.个税累计数据!C:C,1,0) -> 开弈人才徐峰 | CB25: 开弈人才徐峰 | CC25: 有 | CD25: =H25=I25 -> TRUE
A26: =C26&I26 -> 开弈人力资源樊涛 | B26: HRO服务-代收代付残疾人 | C26: 开弈人力资源 | D26: 正常计税 | E26: 客户残疾人 | F26: 葛豪平 | G26: 残疾人 | H26: 樊涛 | I26: 樊涛 | J26: 代收代付残疾人 | K26: =AC26+BL26 -> 5449.47 | L26: =AC26-AM26-AX26-AY26+SUM(AZ26:BA26) -> 2740 | N26: 6 | O26: =3457.55+15.54-7.77+50+23.94-15.96 -> 3523.3 | U26: =SUM(O26:T26) -> 3523.3 | AC26: =SUM(O26:T26)+SUM(V26:AB26) -> 3523.3 | AE26: 202606 | AF26: =VLOOKUP(BW26,'HR|社保明细'!C:F,4,0) -> 7460 | AG26: =VLOOKUP($BW26,'HR|社保明细'!$C:G,5,0) -> 0 | AH26: =VLOOKUP($BW26,'HR|社保明细'!$C:H,6,0) -> 596.8 | AI26: =VLOOKUP($BW26,'HR|社保明细'!$C:I,7,0) -> 149.2 | AJ26: =VLOOKUP($BW26,'HR|社保明细'!$C:J,8,0) -> 37.3 | AK26: =VLOOKUP($BW26,'HR|社保明细'!$C:K,9,0) -> 0 | AL26: =VLOOKUP($BW26,'HR|社保明细'!$C:L,10,0) -> 0 | AM26: =SUM(AH26:AL26) -> 783.3 | AS26: =AC26-AM26-SUM(AN26:AR26) -> 2740 | AU26: =VLOOKUP(BW26,hr.个税累计数据!C:DS,121,0) -> 21139.8 | AV26: =IF(AU26-5000*N26-VLOOKUP(A26,hr.个税累计数据!C:DT,122,0)-VLOOKUP(A26,hr.个税累计数据!C:DU,123,0)>0,AU26-5000*N26-VLOOKUP(A26,hr.个税累计数据!C:DT,122,0)-VLOOKUP(A26,hr.个税累计数据!C:DU,123,0),0) -> 0 | AW26: =VLOOKUP(BW26,hr.个税累计数据!C:DV,124,0) -> 0 | AY26: =IF(ROUND(MAX(AV26*{0.03,0.1,0.2,0.25,0.3,0.35,0.45}-{0,210,1410,2660,4410,7160,15160}*12)-AW26,2)<=0,0,ROUND(MAX(AV26*{0.03,0.1,0.2,0.25,0.3,0.35,0.45}-{0,210,1410,2660,4410,7160,15160}*12)-AW26,2)) -> 0 | AZ26: =-S26 -> 0 | BB26: =AC26-AM26-AY26-AX26+SUM(AZ26:BA26) -> 2740 | BD26: =AC26-AM26-AX26-AY26+SUM(AZ26:BA26) -> 2740 | BE26: =VLOOKUP($BW26,'HR|社保明细'!C:T,11,0) -> 1193.6 | BF26: =VLOOKUP($BW26,'HR|社保明细'!$C:U,12,0) -> 596.8 | BG26: =VLOOKUP($BW26,'HR|社保明细'!$C:V,13,0) -> 37.3 | BH26: =VLOOKUP($BW26,'HR|社保明细'!$C:W,14,0) -> 23.87 | BI26: =VLOOKUP($BW26,'HR|社保明细'!$C:X,15,0) -> 74.6 | BJ26: =VLOOKUP($BW26,'HR|社保明细'!$C:Y,16,0) -> 0 | BK26: =VLOOKUP($BW26,'HR|社保明细'!$C:Z,17,0) -> 0 | BL26: =SUM(BE26:BK26) -> 1926.17 | BR26: =SUM(BN26:BQ26) -> 0 | BS26: =SUM(V26:AB26) -> 0 | BW26: =C26&I26 -> 开弈人力资源樊涛 | BY26: 无 | CA26: =VLOOKUP(A26,hr.个税累计数据!C:C,1,0) -> 开弈人力资源樊涛 | CB26: 开弈人力资源樊涛 | CD26: =H26=I26 -> TRUE
A27: =C27&I27 -> 开弈人力资源葛豪平 | B27: Shaun-雇员服务部 | C27: 开弈人力资源 | D27: 正常计税 | E27: 社保部 | F27: 黄一萧 | G27: 社保经理 | H27: 葛豪平 | I27: 葛豪平 | J27: 全日制 | K27: =AC27+BL27 -> 19228.4 | L27: =AC27-AM27-AX27-AY27+SUM(AZ27:BA27) -> 12109.36 | N27: 6 | O27: 15000 | P27: 179 | Q27: =VLOOKUP(I27,考勤调整记录!I:W,15,0) -> 0 | S27: 267.4 | U27: =SUM(O27:T27) -> 15446.4 | AC27: =SUM(O27:T27)+SUM(V27:AB27) -> 15446.4 | AE27: 202606 | AF27: =VLOOKUP(BW27,'HR|社保明细'!C:F,4,0) -> 10000 | AG27: =VLOOKUP($BW27,'HR|社保明细'!$C:G,5,0) -> 10000 | AH27: =VLOOKUP($BW27,'HR|社保明细'!$C:H,6,0) -> 800 | AI27: =VLOOKUP($BW27,'HR|社保明细'!$C:I,7,0) -> 200 | AJ27: =VLOOKUP($BW27,'HR|社保明细'!$C:J,8,0) -> 50 | AK27: =VLOOKUP($BW27,'HR|社保明细'!$C:K,9,0) -> 700 | AL27: =VLOOKUP($BW27,'HR|社保明细'!$C:L,10,0) -> 500 | AM27: =SUM(AH27:AL27) -> 2250 | AS27: =AC27-AM27-SUM(AN27:AR27) -> 13196.4 | AU27: =VLOOKUP(BW27,hr.个税累计数据!C:DS,121,0) -> 106148.35 | AV27: =IF(AU27-5000*N27-VLOOKUP(A27,hr.个税累计数据!C:DT,122,0)-VLOOKUP(A27,hr.个税累计数据!C:DU,123,0)>0,AU27-5000*N27-VLOOKUP(A27,hr.个税累计数据!C:DT,122,0)-VLOOKUP(A27,hr.个税累计数据!C:DU,123,0),0) -> 62648.35 | AW27: =VLOOKUP(BW27,hr.个税累计数据!C:DV,124,0) -> 2925.2 | AY27: =IF(ROUND(MAX(AV27*{0.03,0.1,0.2,0.25,0.3,0.35,0.45}-{0,210,1410,2660,4410,7160,15160}*12)-AW27,2)<=0,0,ROUND(MAX(AV27*{0.03,0.1,0.2,0.25,0.3,0.35,0.45}-{0,210,1410,2660,4410,7160,15160}*12)-AW27,2)) -> 819.64 | AZ27: =-S27 -> -267.4 | BB27: =AC27-AM27-AY27-AX27+SUM(AZ27:BA27) -> 12109.36 | BD27: =AC27-AM27-AX27-AY27+SUM(AZ27:BA27) -> 12109.36 | BE27: =VLOOKUP($BW27,'HR|社保明细'!C:T,11,0) -> 1600 | BF27: =VLOOKUP($BW27,'HR|社保明细'!$C:U,12,0) -> 800 | BG27: =VLOOKUP($BW27,'HR|社保明细'!$C:V,13,0) -> 50 | BH27: =VLOOKUP($BW27,'HR|社保明细'!$C:W,14,0) -> 32 | BI27: =VLOOKUP($BW27,'HR|社保明细'!$C:X,15,0) -> 100 | BJ27: =VLOOKUP($BW27,'HR|社保明细'!$C:Y,16,0) -> 700 | BK27: =VLOOKUP($BW27,'HR|社保明细'!$C:Z,17,0) -> 500 | BL27: =SUM(BE27:BK27) -> 3782 | BR27: =SUM(BN27:BQ27) -> 0 | BS27: =SUM(V27:AB27) -> 0 | BT27: 1250 | BW27: =C27&I27 -> 开弈人力资源葛豪平 | BY27: 有 | BZ27: 人才 | CA27: =VLOOKUP(A27,hr.个税累计数据!C:C,1,0) -> 开弈人力资源葛豪平 | CB27: 开弈人力资源葛豪平 | CC27: 有 | CD27: =H27=I27 -> TRUE
A28: =C28&I28 -> 开弈人力资源侯心怡 | B28: Shaun-客服部 | C28: 开弈人力资源 | D28: 正常计税 | E28: 客服部（S） | F28: 杨漾 | G28: 客服专员 | H28: 侯心怡 | I28: 侯心怡 | J28: 全日制 | K28: =AC28+BL28 -> 12598.97 | L28: =AC28-AM28-AX28-AY28+SUM(AZ28:BA28) -> 8584.03 | N28: 6 | O28: 10000 | Q28: =VLOOKUP(I28,考勤调整记录!I:W,15,0) -> 0 | S28: 155.8 | U28: =SUM(O28:T28) -> 10155.8 | AC28: =SUM(O28:T28)+SUM(V28:AB28) -> 10155.8 | AE28: 202606 | AF28: =VLOOKUP(BW28,'HR|社保明细'!C:F,4,0) -> 7460 | AG28: =VLOOKUP($BW28,'HR|社保明细'!$C:G,5,0) -> 7384 | AH28: =VLOOKUP($BW28,'HR|社保明细'!$C:H,6,0) -> 596.8 | AI28: =VLOOKUP($BW28,'HR|社保明细'!$C:I,7,0) -> 149.2 | AJ28: =VLOOKUP($BW28,'HR|社保明细'!$C:J,8,0) -> 37.3 | AK28: =VLOOKUP($BW28,'HR|社保明细'!$C:K,9,0) -> 517 | AL28: =VLOOKUP($BW28,'HR|社保明细'!$C:L,10,0) -> 0 | AM28: =SUM(AH28:AL28) -> 1300.3 | AS28: =AC28-AM28-SUM(AN28:AR28) -> 8855.5 | AU28: =VLOOKUP(BW28,hr.个税累计数据!C:DS,121,0) -> 63319.98 | AV28: =IF(AU28-5000*N28-VLOOKUP(A28,hr.个税累计数据!C:DT,122,0)-VLOOKUP(A28,hr.个税累计数据!C:DU,123,0)>0,AU28-5000*N28-VLOOKUP(A28,hr.个税累计数据!C:DT,122,0)-VLOOKUP(A28,hr.个税累计数据!C:DU,123,0),0) -> 25518.18 | AW28: =VLOOKUP(BW28,hr.个税累计数据!C:DV,124,0) -> 649.88 | AX28: 0 | AY28: =IF(ROUND(MAX(AV28*{0.03,0.1,0.2,0.25,0.3,0.35,0.45}-{0,210,1410,2660,4410,7160,15160}*12)-AW28,2)<=0,0,ROUND(MAX(AV28*{0.03,0.1,0.2,0.25,0.3,0.35,0.45}-{0,210,1410,2660,4410,7160,15160}*12)-AW28,2)) -> 115.67 | AZ28: =-S28 -> -155.8 | BB28: =AC28-AM28-AY28-AX28+SUM(AZ28:BA28) -> 8584.03 | BD28: =AC28-AM28-AX28-AY28+SUM(AZ28:BA28) -> 8584.03 | BE28: =VLOOKUP($BW28,'HR|社保明细'!C:T,11,0) -> 1193.6 | BF28: =VLOOKUP($BW28,'HR|社保明细'!$C:U,12,0) -> 596.8 | BG28: =VLOOKUP($BW28,'HR|社保明细'!$C:V,13,0) -> 37.3 | BH28: =VLOOKUP($BW28,'HR|社保明细'!$C:W,14,0) -> 23.87 | BI28: =VLOOKUP($BW28,'HR|社保明细'!$C:X,15,0) -> 74.6 | BJ28: =VLOOKUP($BW28,'HR|社保明细'!$C:Y,16,0) -> 517 | BK28: =VLOOKUP($BW28,'HR|社保明细'!$C:Z,17,0) -> 0 | BL28: =SUM(BE28:BK28) -> 2443.17 | BR28: =SUM(BN28:BQ28) -> 0 | BS28: =SUM(V28:AB28) -> 0 | BT28: 1250 | BW28: =C28&I28 -> 开弈人力资源侯心怡 | BY28: 有 | BZ28: 人才 | CA28: =VLOOKUP(A28,hr.个税累计数据!C:C,1,0) -> 开弈人力资源侯心怡 | CB28: 开弈人力资源侯心怡 | CC28: 有 | CD28: =H28=I28 -> TRUE
A29: =C29&I29 -> 开弈人力资源黄一萧 | B29: Shaun-客服部 | C29: 开弈人力资源 | D29: 正常计税 | E29: 客服部（S） | F29: 张毅 | G29: 客服总监 | H29: 黄一萧 | I29: 黄一萧 | J29: 全日制 | K29: =AC29+BL29 -> 23272.68 | L29: =AC29-AM29-AX29-AY29+SUM(AZ29:BA29) -> 13745.05 | N29: 6 | O29: 17100 | P29: 359 | Q29: =VLOOKUP(I29,考勤调整记录!I:W,15,0) -> 0 | S29: 257.16 | T29: 5000 | U29: =SUM(O29:T29) -> 22716.16 | W29: -5116.48 | AC29: =SUM(O29:T29)+SUM(V29:AB29) -> 17599.68 | AE29: 202606 | AF29: =VLOOKUP(BW29,'HR|社保明细'!C:F,4,0) -> 15000 | AG29: =VLOOKUP($BW29,'HR|社保明细'!$C:G,5,0) -> 15000 | AH29: =VLOOKUP($BW29,'HR|社保明细'!$C:H,6,0) -> 1200 | AI29: =VLOOKUP($BW29,'HR|社保明细'!$C:I,7,0) -> 300 | AJ29: =VLOOKUP($BW29,'HR|社保明细'!$C:J,8,0) -> 75 | AK29: =VLOOKUP($BW29,'HR|社保明细'!$C:K,9,0) -> 1050 | AL29: =VLOOKUP($BW29,'HR|社保明细'!$C:L,10,0) -> 750 | AM29: =SUM(AH29:AL29) -> 3375 | AQ29: 3000 | AS29: =AC29-AM29-SUM(AN29:AR29) -> 11224.68 | AU29: =VLOOKUP(BW29,hr.个税累计数据!C:DS,121,0) -> 174340.29 | AV29: =IF(AU29-5000*N29-VLOOKUP(A29,hr.个税累计数据!C:DT,122,0)-VLOOKUP(A29,hr.个税累计数据!C:DU,123,0)>0,AU29-5000*N29-VLOOKUP(A29,hr.个税累计数据!C:DT,122,0)-VLOOKUP(A29,hr.个税累计数据!C:DU,123,0),0) -> 82090.29 | AW29: =VLOOKUP(BW29,hr.个税累计数据!C:DV,124,0) -> 5466.56 | AY29: =IF(ROUND(MAX(AV29*{0.03,0.1,0.2,0.25,0.3,0.35,0.45}-{0,210,1410,2660,4410,7160,15160}*12)-AW29,2)<=0,0,ROUND(MAX(AV29*{0.03,0.1,0.2,0.25,0.3,0.35,0.45}-{0,210,1410,2660,4410,7160,15160}*12)-AW29,2)) -> 222.47 | AZ29: =-S29 -> -257.16 | BB29: =AC29-AM29-AY29-AX29+SUM(AZ29:BA29) -> 13745.05 | BD29: =AC29-AM29-AX29-AY29+SUM(AZ29:BA29) -> 13745.05 | BE29: =VLOOKUP($BW29,'HR|社保明细'!C:T,11,0) -> 2400 | BF29: =VLOOKUP($BW29,'HR|社保明细'!$C:U,12,0) -> 1200 | BG29: =VLOOKUP($BW29,'HR|社保明细'!$C:V,13,0) -> 75 | BH29: =VLOOKUP($BW29,'HR|社保明细'!$C:W,14,0) -> 48 | BI29: =VLOOKUP($BW29,'HR|社保明细'!$C:X,15,0) -> 150 | BJ29: =VLOOKUP($BW29,'HR|社保明细'!$C:Y,16,0) -> 1050 | BK29: =VLOOKUP($BW29,'HR|社保明细'!$C:Z,17,0) -> 750 | BL29: =SUM(BE29:BK29) -> 5673 | BR29: =SUM(BN29:BQ29) -> 0 | BS29: =SUM(V29:AB29) -> -5116.48 | BT29: 1250 | BW29: =C29&I29 -> 开弈人力资源黄一萧 | BY29: 有 | BZ29: 人才 | CA29: =VLOOKUP(A29,hr.个税累计数据!C:C,1,0) -> 开弈人力资源黄一萧 | CB29: 开弈人力资源黄一萧 | CC29: 有 | CD29: =H29=I29 -> TRUE
A30: =C30&I30 -> 开弈人力资源肖宝仙 | B30: Shaun-客服部 | C30: 开弈人力资源 | D30: 正常计税 | E30: 客服部（S） | F30: 黄一萧 | G30: 顾问 | H30: 黄一萧 | I30: 肖宝仙 | J30: 非全日制 | K30: =AC30+BL30 -> 10000 | L30: =AC30-AM30-AX30-AY30+SUM(AZ30:BA30) -> 9850 | N30: 6 | O30: 10000 | Q30: =VLOOKUP(I30,考勤调整记录!I:W,15,0) -> 0 | U30: =SUM(O30:T30) -> 10000 | AC30: =SUM(O30:T30)+SUM(V30:AB30) -> 10000 | AE30: 202606 | AF30: =VLOOKUP(BW30,'HR|社保明细'!C:F,4,0) -> 0 | AG30: =VLOOKUP($BW30,'HR|社保明细'!$C:G,5,0) -> 0 | AH30: =VLOOKUP($BW30,'HR|社保明细'!$C:H,6,0) -> 0 | AI30: =VLOOKUP($BW30,'HR|社保明细'!$C:I,7,0) -> 0 | AJ30: =VLOOKUP($BW30,'HR|社保明细'!$C:J,8,0) -> 0 | AK30: =VLOOKUP($BW30,'HR|社保明细'!$C:K,9,0) -> 0 | AL30: =VLOOKUP($BW30,'HR|社保明细'!$C:L,10,0) -> 0 | AM30: =SUM(AH30:AL30) -> 0 | AS30: =AC30-AM30-SUM(AN30:AR30) -> 10000 | AU30: =VLOOKUP(BW30,hr.个税累计数据!C:DS,121,0) -> 58329 | AV30: =IF(AU30-5000*N30-VLOOKUP(A30,hr.个税累计数据!C:DT,122,0)-VLOOKUP(A30,hr.个税累计数据!C:DU,123,0)>0,AU30-5000*N30-VLOOKUP(A30,hr.个税累计数据!C:DT,122,0)-VLOOKUP(A30,hr.个税累计数据!C:DU,123,0),0) -> 28329 | AW30: =VLOOKUP(BW30,hr.个税累计数据!C:DV,124,0) -> 699.87 | AY30: =IF(ROUND(MAX(AV30*{0.03,0.1,0.2,0.25,0.3,0.35,0.45}-{0,210,1410,2660,4410,7160,15160}*12)-AW30,2)<=0,0,ROUND(MAX(AV30*{0.03,0.1,0.2,0.25,0.3,0.35,0.45}-{0,210,1410,2660,4410,7160,15160}*12)-AW30,2)) -> 150 | AZ30: =-S30 -> 0 | BB30: =AC30-AM30-AY30-AX30+SUM(AZ30:BA30) -> 9850 | BD30: =AC30-AM30-AX30-AY30+SUM(AZ30:BA30) -> 9850 | BE30: =VLOOKUP($BW30,'HR|社保明细'!C:T,11,0) -> 0 | BF30: =VLOOKUP($BW30,'HR|社保明细'!$C:U,12,0) -> 0 | BG30: =VLOOKUP($BW30,'HR|社保明细'!$C:V,13,0) -> 0 | BH30: =VLOOKUP($BW30,'HR|社保明细'!$C:W,14,0) -> 0 | BI30: =VLOOKUP($BW30,'HR|社保明细'!$C:X,15,0) -> 0 | BJ30: =VLOOKUP($BW30,'HR|社保明细'!$C:Y,16,0) -> 0 | BK30: =VLOOKUP($BW30,'HR|社保明细'!$C:Z,17,0) -> 0 | BL30: =SUM(BE30:BK30) -> 0 | BR30: =SUM(BN30:BQ30) -> 0 | BS30: =SUM(V30:AB30) -> 0 | BW30: =C30&I30 -> 开弈人力资源肖宝仙 | BX30: 无社公 | BY30: 无 | BZ30: 人才 | CA30: =VLOOKUP(A30,hr.个税累计数据!C:C,1,0) -> 开弈人力资源肖宝仙 | CB30: 开弈人力资源肖宝仙 | CD30: =H30=I30 -> FALSE
A31: =C31&I31 -> 开弈人力资源李家东 | B31: HRO服务-代收代付残疾人 | C31: 开弈人力资源 | D31: 正常计税 | E31: 客户残疾人 | F31: 葛豪平 | G31: 残疾人 | H31: 李家东 | I31: 李家东 | J31: 代收代付残疾人 | K31: =AC31+BL31 -> 5449.47 | L31: =AC31-AM31-AX31-AY31+SUM(AZ31:BA31) -> 2740 | N31: 6 | O31: =3457.55+15.54-7.77+50+23.94-15.96 -> 3523.3 | U31: =SUM(O31:T31) -> 3523.3 | AC31: =SUM(O31:T31)+SUM(V31:AB31) -> 3523.3 | AE31: 202606 | AF31: =VLOOKUP(BW31,'HR|社保明细'!C:F,4,0) -> 7460 | AG31: =VLOOKUP($BW31,'HR|社保明细'!$C:G,5,0) -> 0 | AH31: =VLOOKUP($BW31,'HR|社保明细'!$C:H,6,0) -> 596.8 | AI31: =VLOOKUP($BW31,'HR|社保明细'!$C:I,7,0) -> 149.2 | AJ31: =VLOOKUP($BW31,'HR|社保明细'!$C:J,8,0) -> 37.3 | AK31: =VLOOKUP($BW31,'HR|社保明细'!$C:K,9,0) -> 0 | AL31: =VLOOKUP($BW31,'HR|社保明细'!$C:L,10,0) -> 0 | AM31: =SUM(AH31:AL31) -> 783.3 | AS31: =AC31-AM31-SUM(AN31:AR31) -> 2740 | AU31: =VLOOKUP(BW31,hr.个税累计数据!C:DS,121,0) -> 21139.8 | AV31: =IF(AU31-5000*N31-VLOOKUP(A31,hr.个税累计数据!C:DT,122,0)-VLOOKUP(A31,hr.个税累计数据!C:DU,123,0)>0,AU31-5000*N31-VLOOKUP(A31,hr.个税累计数据!C:DT,122,0)-VLOOKUP(A31,hr.个税累计数据!C:DU,123,0),0) -> 0 | AW31: =VLOOKUP(BW31,hr.个税累计数据!C:DV,124,0) -> 0 | AY31: =IF(ROUND(MAX(AV31*{0.03,0.1,0.2,0.25,0.3,0.35,0.45}-{0,210,1410,2660,4410,7160,15160}*12)-AW31,2)<=0,0,ROUND(MAX(AV31*{0.03,0.1,0.2,0.25,0.3,0.35,0.45}-{0,210,1410,2660,4410,7160,15160}*12)-AW31,2)) -> 0 | AZ31: =-S31 -> 0 | BB31: =AC31-AM31-AY31-AX31+SUM(AZ31:BA31) -> 2740 | BD31: =AC31-AM31-AX31-AY31+SUM(AZ31:BA31) -> 2740 | BE31: =VLOOKUP($BW31,'HR|社保明细'!C:T,11,0) -> 1193.6 | BF31: =VLOOKUP($BW31,'HR|社保明细'!$C:U,12,0) -> 596.8 | BG31: =VLOOKUP($BW31,'HR|社保明细'!$C:V,13,0) -> 37.3 | BH31: =VLOOKUP($BW31,'HR|社保明细'!$C:W,14,0) -> 23.87 | BI31: =VLOOKUP($BW31,'HR|社保明细'!$C:X,15,0) -> 74.6 | BJ31: =VLOOKUP($BW31,'HR|社保明细'!$C:Y,16,0) -> 0 | BK31: =VLOOKUP($BW31,'HR|社保明细'!$C:Z,17,0) -> 0 | BL31: =SUM(BE31:BK31) -> 1926.17 | BR31: =SUM(BN31:BQ31) -> 0 | BS31: =SUM(V31:AB31) -> 0 | BW31: =C31&I31 -> 开弈人力资源李家东 | BY31: 无 | CA31: =VLOOKUP(A31,hr.个税累计数据!C:C,1,0) -> 开弈人力资源李家东 | CB31: 开弈人力资源李家东 | CD31: =H31=I31 -> TRUE
A32: =C32&I32 -> 开弈人力资源卢素丹 | B32: Shaun-客服部 | C32: 开弈人力资源 | D32: 正常计税 | E32: 客服部（S） | F32: 杨漾 | G32: 客服专员 | H32: 卢素丹 | I32: 卢素丹 | J32: 全日制 | K32: =AC32+BL32 -> 10598.97 | L32: =AC32-AM32-AX32-AY32+SUM(AZ32:BA32) -> 6644.03 | N32: 6 | O32: 8000 | Q32: =VLOOKUP(I32,考勤调整记录!I:W,15,0) -> 0 | S32: 155.8 | U32: =SUM(O32:T32) -> 8155.8 | AC32: =SUM(O32:T32)+SUM(V32:AB32) -> 8155.8 | AE32: 202606 | AF32: =VLOOKUP(BW32,'HR|社保明细'!C:F,4,0) -> 7460 | AG32: =VLOOKUP($BW32,'HR|社保明细'!$C:G,5,0) -> 7384 | AH32: =VLOOKUP($BW32,'HR|社保明细'!$C:H,6,0) -> 596.8 | AI32: =VLOOKUP($BW32,'HR|社保明细'!$C:I,7,0) -> 149.2 | AJ32: =VLOOKUP($BW32,'HR|社保明细'!$C:J,8,0) -> 37.3 | AK32: =VLOOKUP($BW32,'HR|社保明细'!$C:K,9,0) -> 517 | AL32: =VLOOKUP($BW32,'HR|社保明细'!$C:L,10,0) -> 0 | AM32: =SUM(AH32:AL32) -> 1300.3 | AS32: =AC32-AM32-SUM(AN32:AR32) -> 6855.5 | AU32: =VLOOKUP(BW32,hr.个税累计数据!C:DS,121,0) -> 51052 | AV32: =IF(AU32-5000*N32-VLOOKUP(A32,hr.个税累计数据!C:DT,122,0)-VLOOKUP(A32,hr.个税累计数据!C:DU,123,0)>0,AU32-5000*N32-VLOOKUP(A32,hr.个税累计数据!C:DT,122,0)-VLOOKUP(A32,hr.个税累计数据!C:DU,123,0),0) -> 13250.2 | AW32: =VLOOKUP(BW32,hr.个税累计数据!C:DV,124,0) -> 341.84 | AY32: =IF(ROUND(MAX(AV32*{0.03,0.1,0.2,0.25,0.3,0.35,0.45}-{0,210,1410,2660,4410,7160,15160}*12)-AW32,2)<=0,0,ROUND(MAX(AV32*{0.03,0.1,0.2,0.25,0.3,0.35,0.45}-{0,210,1410,2660,4410,7160,15160}*12)-AW32,2)) -> 55.67 | AZ32: =-S32 -> -155.8 | BB32: =AC32-AM32-AY32-AX32+SUM(AZ32:BA32) -> 6644.03 | BD32: =AC32-AM32-AX32-AY32+SUM(AZ32:BA32) -> 6644.03 | BE32: =VLOOKUP($BW32,'HR|社保明细'!C:T,11,0) -> 1193.6 | BF32: =VLOOKUP($BW32,'HR|社保明细'!$C:U,12,0) -> 596.8 | BG32: =VLOOKUP($BW32,'HR|社保明细'!$C:V,13,0) -> 37.3 | BH32: =VLOOKUP($BW32,'HR|社保明细'!$C:W,14,0) -> 23.87 | BI32: =VLOOKUP($BW32,'HR|社保明细'!$C:X,15,0) -> 74.6 | BJ32: =VLOOKUP($BW32,'HR|社保明细'!$C:Y,16,0) -> 517 | BK32: =VLOOKUP($BW32,'HR|社保明细'!$C:Z,17,0) -> 0 | BL32: =SUM(BE32:BK32) -> 2443.17 | BR32: =SUM(BN32:BQ32) -> 0 | BS32: =SUM(V32:AB32) -> 0 | BT32: 1250 | BW32: =C32&I32 -> 开弈人力资源卢素丹 | BY32: 有 | BZ32: 人才 | CA32: =VLOOKUP(A32,hr.个税累计数据!C:C,1,0) -> 开弈人力资源卢素丹 | CB32: 开弈人力资源卢素丹 | CC32: 有 | CD32: =H32=I32 -> TRUE
A33: =C33&I33 -> 开弈人力资源芦智蔚 | B33: F-大财务部 | C33: 开弈人力资源 | D33: 正常计税 | E33: 财务部 | F33: 张毅 | G33: 财务经理 | H33: 芦智蔚 | I33: 芦智蔚 | J33: 全日制 | K33: =AC33+BL33 -> 35520.36 | L33: =AC33-AM33-AX33-AY33+SUM(AZ33:BA33) -> 25513.5 | N33: 6 | O33: 20000 | Q33: =VLOOKUP(I33,考勤调整记录!I:W,15,0) -> 0 | S33: 480.36 | U33: =SUM(O33:T33) -> 20480.36 | W33: =ROUND((O33)*(0.9629-1),2) -> -742 | Z33: 12000 | AC33: =SUM(O33:T33)+SUM(V33:AB33) -> 31738.36 | AE33: 202606 | AF33: =VLOOKUP(BW33,'HR|社保明细'!C:F,4,0) -> 10000 | AG33: =VLOOKUP($BW33,'HR|社保明细'!$C:G,5,0) -> 10000 | AH33: =VLOOKUP($BW33,'HR|社保明细'!$C:H,6,0) -> 800 | AI33: =VLOOKUP($BW33,'HR|社保明细'!$C:I,7,0) -> 200 | AJ33: =VLOOKUP($BW33,'HR|社保明细'!$C:J,8,0) -> 50 | AK33: =VLOOKUP($BW33,'HR|社保明细'!$C:K,9,0) -> 700 | AL33: =VLOOKUP($BW33,'HR|社保明细'!$C:L,10,0) -> 500 | AM33: =SUM(AH33:AL33) -> 2250 | AQ33: 1500 | AS33: =AC33-AM33-SUM(AN33:AR33) -> 27988.36 | AU33: =VLOOKUP(BW33,hr.个税累计数据!C:DS,121,0) -> 208456.72 | AV33: =IF(AU33-5000*N33-VLOOKUP(A33,hr.个税累计数据!C:DT,122,0)-VLOOKUP(A33,hr.个税累计数据!C:DU,123,0)>0,AU33-5000*N33-VLOOKUP(A33,hr.个税累计数据!C:DT,122,0)-VLOOKUP(A33,hr.个税累计数据!C:DU,123,0),0) -> 155956.72 | AW33: =VLOOKUP(BW33,hr.个税累计数据!C:DV,124,0) -> 10776.84 | AY33: =IF(ROUND(MAX(AV33*{0.03,0.1,0.2,0.25,0.3,0.35,0.45}-{0,210,1410,2660,4410,7160,15160}*12)-AW33,2)<=0,0,ROUND(MAX(AV33*{0.03,0.1,0.2,0.25,0.3,0.35,0.45}-{0,210,1410,2660,4410,7160,15160}*12)-AW33,2)) -> 3494.5 | AZ33: =-S33 -> -480.36 | BB33: =AC33-AM33-AY33-AX33+SUM(AZ33:BA33) -> 25513.5 | BD33: =AC33-AM33-AX33-AY33+SUM(AZ33:BA33) -> 25513.5 | BE33: =VLOOKUP($BW33,'HR|社保明细'!C:T,11,0) -> 1600 | BF33: =VLOOKUP($BW33,'HR|社保明细'!$C:U,12,0) -> 800 | BG33: =VLOOKUP($BW33,'HR|社保明细'!$C:V,13,0) -> 50 | BH33: =VLOOKUP($BW33,'HR|社保明细'!$C:W,14,0) -> 32 | BI33: =VLOOKUP($BW33,'HR|社保明细'!$C:X,15,0) -> 100 | BJ33: =VLOOKUP($BW33,'HR|社保明细'!$C:Y,16,0) -> 700 | BK33: =VLOOKUP($BW33,'HR|社保明细'!$C:Z,17,0) -> 500 | BL33: =SUM(BE33:BK33) -> 3782 | BR33: =SUM(BN33:BQ33) -> 0 | BS33: =SUM(V33:AB33) -> 11258 | BT33: 1250 | BW33: =C33&I33 -> 开弈人力资源芦智蔚 | BY33: 有 | BZ33: 后台 | CA33: =VLOOKUP(A33,hr.个税累计数据!C:C,1,0) -> 开弈人力资源芦智蔚 | CB33: 开弈人力资源芦智蔚 | CC33: 有 | CD33: =H33=I33 -> TRUE
A34: =C34&I34 -> 靠普人力毛华英 | B34: Shaun-雇员服务部 | C34: 靠普人力 | D34: 正常计税 | E34: 社保部 | F34: 葛豪平 | G34: 社保专员 | H34: 毛华英 | I34: 毛华英 | J34: 全日制 | K34: =AC34+BL34 -> 9892.07 | L34: =AC34-AM34-AX34-AY34+SUM(AZ34:BA34) -> 5958.34 | N34: 6 | O34: 7500 | Q34: =VLOOKUP(I34,考勤调整记录!I:W,15,0) -> -206.9 | S34: 155.8 | U34: =SUM(O34:T34) -> 7448.9 | AC34: =SUM(O34:T34)+SUM(V34:AB34) -> 7448.9 | AE34: 202606 | AF34: =VLOOKUP(BW34,'HR|社保明细'!C:F,4,0) -> 7460 | AG34: =VLOOKUP($BW34,'HR|社保明细'!$C:G,5,0) -> 7384 | AH34: =VLOOKUP($BW34,'HR|社保明细'!$C:H,6,0) -> 596.8 | AI34: =VLOOKUP($BW34,'HR|社保明细'!$C:I,7,0) -> 149.2 | AJ34: =VLOOKUP($BW34,'HR|社保明细'!$C:J,8,0) -> 37.3 | AK34: =VLOOKUP($BW34,'HR|社保明细'!$C:K,9,0) -> 517 | AL34: =VLOOKUP($BW34,'HR|社保明细'!$C:L,10,0) -> 0 | AM34: =SUM(AH34:AL34) -> 1300.3 | AS34: =AC34-AM34-SUM(AN34:AR34) -> 6148.6 | AU34: =VLOOKUP(BW34,hr.个税累计数据!C:DS,121,0) -> 51139.43 | AV34: =IF(AU34-5000*N34-VLOOKUP(A34,hr.个税累计数据!C:DT,122,0)-VLOOKUP(A34,hr.个税累计数据!C:DU,123,0)>0,AU34-5000*N34-VLOOKUP(A34,hr.个税累计数据!C:DT,122,0)-VLOOKUP(A34,hr.个税累计数据!C:DU,123,0),0) -> 13337.63 | AW34: =VLOOKUP(BW34,hr.个税累计数据!C:DV,124,0) -> 365.67 | AY34: =IF(ROUND(MAX(AV34*{0.03,0.1,0.2,0.25,0.3,0.35,0.45}-{0,210,1410,2660,4410,7160,15160}*12)-AW34,2)<=0,0,ROUND(MAX(AV34*{0.03,0.1,0.2,0.25,0.3,0.35,0.45}-{0,210,1410,2660,4410,7160,15160}*12)-AW34,2)) -> 34.46 | AZ34: =-S34 -> -155.8 | BB34: =AC34-AM34-AY34-AX34+SUM(AZ34:BA34) -> 5958.34 | BD34: =AC34-AM34-AX34-AY34+SUM(AZ34:BA34) -> 5958.34 | BE34: =VLOOKUP($BW34,'HR|社保明细'!C:T,11,0) -> 1193.6 | BF34: =VLOOKUP($BW34,'HR|社保明细'!$C:U,12,0) -> 596.8 | BG34: =VLOOKUP($BW34,'HR|社保明细'!$C:V,13,0) -> 37.3 | BH34: =VLOOKUP($BW34,'HR|社保明细'!$C:W,14,0) -> 23.87 | BI34: =VLOOKUP($BW34,'HR|社保明细'!$C:X,15,0) -> 74.6 | BJ34: =VLOOKUP($BW34,'HR|社保明细'!$C:Y,16,0) -> 517 | BK34: =VLOOKUP($BW34,'HR|社保明细'!$C:Z,17,0) -> 0 | BL34: =SUM(BE34:BK34) -> 2443.17 | BR34: =SUM(BN34:BQ34) -> 0 | BS34: =SUM(V34:AB34) -> 0 | BT34: 1250 | BW34: =C34&I34 -> 靠普人力毛华英 | BY34: 有 | BZ34: 人才 | CA34: =VLOOKUP(A34,hr.个税累计数据!C:C,1,0) -> 靠普人力毛华英 | CB34: 靠普人力毛华英 | CC34: 有 | CD34: =H34=I34 -> TRUE
A35: =C35&I35 -> 开弈人力资源裘碧钰 | B35: Shaun-客服部 | C35: 开弈人力资源 | D35: 正常计税 | E35: 客服部（S） | F35: 杨漾 | G35: 客服专员 | H35: 裘碧钰 | I35: 裘碧钰 | J35: 全日制 | K35: =AC35+BL35 -> 12598.97 | L35: =AC35-AM35-AX35-AY35+SUM(AZ35:BA35) -> 8699.7 | N35: 6 | O35: 10000 | Q35: =VLOOKUP(I35,考勤调整记录!I:W,15,0) -> 0 | S35: 155.8 | U35: =SUM(O35:T35) -> 10155.8 | AC35: =SUM(O35:T35)+SUM(V35:AB35) -> 10155.8 | AE35: 202606 | AF35: =VLOOKUP(BW35,'HR|社保明细'!C:F,4,0) -> 7460 | AG35: =VLOOKUP($BW35,'HR|社保明细'!$C:G,5,0) -> 7384 | AH35: =VLOOKUP($BW35,'HR|社保明细'!$C:H,6,0) -> 596.8 | AI35: =VLOOKUP($BW35,'HR|社保明细'!$C:I,7,0) -> 149.2 | AJ35: =VLOOKUP($BW35,'HR|社保明细'!$C:J,8,0) -> 37.3 | AK35: =VLOOKUP($BW35,'HR|社保明细'!$C:K,9,0) -> 517 | AL35: =VLOOKUP($BW35,'HR|社保明细'!$C:L,10,0) -> 0 | AM35: =SUM(AH35:AL35) -> 1300.3 | AP35: 1500 | AS35: =AC35-AM35-SUM(AN35:AR35) -> 7355.5 | AU35: =VLOOKUP(BW35,hr.个税累计数据!C:DS,121,0) -> 60789 | AV35: =IF(AU35-5000*N35-VLOOKUP(A35,hr.个税累计数据!C:DT,122,0)-VLOOKUP(A35,hr.个税累计数据!C:DU,123,0)>0,AU35-5000*N35-VLOOKUP(A35,hr.个税累计数据!C:DT,122,0)-VLOOKUP(A35,hr.个税累计数据!C:DU,123,0),0) -> 0 | AW35: =VLOOKUP(BW35,hr.个税累计数据!C:DV,124,0) -> 70.34 | AY35: =IF(ROUND(MAX(AV35*{0.03,0.1,0.2,0.25,0.3,0.35,0.45}-{0,210,1410,2660,4410,7160,15160}*12)-AW35,2)<=0,0,ROUND(MAX(AV35*{0.03,0.1,0.2,0.25,0.3,0.35,0.45}-{0,210,1410,2660,4410,7160,15160}*12)-AW35,2)) -> 0 | AZ35: =-S35 -> -155.8 | BB35: =AC35-AM35-AY35-AX35+SUM(AZ35:BA35) -> 8699.7 | BD35: =AC35-AM35-AX35-AY35+SUM(AZ35:BA35) -> 8699.7 | BE35: =VLOOKUP($BW35,'HR|社保明细'!C:T,11,0) -> 1193.6 | BF35: =VLOOKUP($BW35,'HR|社保明细'!$C:U,12,0) -> 596.8 | BG35: =VLOOKUP($BW35,'HR|社保明细'!$C:V,13,0) -> 37.3 | BH35: =VLOOKUP($BW35,'HR|社保明细'!$C:W,14,0) -> 23.87 | BI35: =VLOOKUP($BW35,'HR|社保明细'!$C:X,15,0) -> 74.6 | BJ35: =VLOOKUP($BW35,'HR|社保明细'!$C:Y,16,0) -> 517 | BK35: =VLOOKUP($BW35,'HR|社保明细'!$C:Z,17,0) -> 0 | BL35: =SUM(BE35:BK35) -> 2443.17 | BR35: =SUM(BN35:BQ35) -> 0 | BS35: =SUM(V35:AB35) -> 0 | BT35: 1250 | BW35: =C35&I35 -> 开弈人力资源裘碧钰 | BY35: 有 | BZ35: 人才 | CA35: =VLOOKUP(A35,hr.个税累计数据!C:C,1,0) -> 开弈人力资源裘碧钰 | CB35: 开弈人力资源裘碧钰 | CC35: 有 | CD35: =H35=I35 -> TRUE
A36: =C36&I36 -> 开弈人力资源姜启志 | B36: HRO服务-代收代付残疾人 | C36: 开弈人力资源 | D36: 正常计税 | E36: 客户残疾人 | F36: 葛豪平 | G36: 残疾人 | H36: 姜启志 | I36: 姜启志 | J36: 代收代付残疾人 | K36: =AC36+BL36 -> 5449.47 | L36: =AC36-AM36-AX36-AY36+SUM(AZ36:BA36) -> 2740 | N36: 6 | O36: =3457.55+15.54-7.77+50+23.94-15.96 -> 3523.3 | U36: =SUM(O36:T36) -> 3523.3 | AC36: =SUM(O36:T36)+SUM(V36:AB36) -> 3523.3 | AE36: 202606 | AF36: =VLOOKUP(BW36,'HR|社保明细'!C:F,4,0) -> 7460 | AG36: =VLOOKUP($BW36,'HR|社保明细'!$C:G,5,0) -> 0 | AH36: =VLOOKUP($BW36,'HR|社保明细'!$C:H,6,0) -> 596.8 | AI36: =VLOOKUP($BW36,'HR|社保明细'!$C:I,7,0) -> 149.2 | AJ36: =VLOOKUP($BW36,'HR|社保明细'!$C:J,8,0) -> 37.3 | AK36: =VLOOKUP($BW36,'HR|社保明细'!$C:K,9,0) -> 0 | AL36: =VLOOKUP($BW36,'HR|社保明细'!$C:L,10,0) -> 0 | AM36: =SUM(AH36:AL36) -> 783.3 | AS36: =AC36-AM36-SUM(AN36:AR36) -> 2740 | AU36: =VLOOKUP(BW36,hr.个税累计数据!C:DS,121,0) -> 21139.8 | AV36: =IF(AU36-5000*N36-VLOOKUP(A36,hr.个税累计数据!C:DT,122,0)-VLOOKUP(A36,hr.个税累计数据!C:DU,123,0)>0,AU36-5000*N36-VLOOKUP(A36,hr.个税累计数据!C:DT,122,0)-VLOOKUP(A36,hr.个税累计数据!C:DU,123,0),0) -> 0 | AW36: =VLOOKUP(BW36,hr.个税累计数据!C:DV,124,0) -> 0 | AY36: =IF(ROUND(MAX(AV36*{0.03,0.1,0.2,0.25,0.3,0.35,0.45}-{0,210,1410,2660,4410,7160,15160}*12)-AW36,2)<=0,0,ROUND(MAX(AV36*{0.03,0.1,0.2,0.25,0.3,0.35,0.45}-{0,210,1410,2660,4410,7160,15160}*12)-AW36,2)) -> 0 | AZ36: =-S36 -> 0 | BB36: =AC36-AM36-AY36-AX36+SUM(AZ36:BA36) -> 2740 | BD36: =AC36-AM36-AX36-AY36+SUM(AZ36:BA36) -> 2740 | BE36: =VLOOKUP($BW36,'HR|社保明细'!C:T,11,0) -> 1193.6 | BF36: =VLOOKUP($BW36,'HR|社保明细'!$C:U,12,0) -> 596.8 | BG36: =VLOOKUP($BW36,'HR|社保明细'!$C:V,13,0) -> 37.3 | BH36: =VLOOKUP($BW36,'HR|社保明细'!$C:W,14,0) -> 23.87 | BI36: =VLOOKUP($BW36,'HR|社保明细'!$C:X,15,0) -> 74.6 | BJ36: =VLOOKUP($BW36,'HR|社保明细'!$C:Y,16,0) -> 0 | BK36: =VLOOKUP($BW36,'HR|社保明细'!$C:Z,17,0) -> 0 | BL36: =SUM(BE36:BK36) -> 1926.17 | BR36: =SUM(BN36:BQ36) -> 0 | BS36: =SUM(V36:AB36) -> 0 | BW36: =C36&I36 -> 开弈人力资源姜启志 | BY36: 无 | CA36: =VLOOKUP(A36,hr.个税累计数据!C:C,1,0) -> 开弈人力资源姜启志 | CB36: 开弈人力资源姜启志 | CD36: =H36=I36 -> TRUE
A37: =C37&I37 -> 开弈人力资源沈丽霞 | B37: Shaun-客服部 | C37: 开弈人力资源 | D37: 正常计税 | E37: 客服部（S） | F37: 杨漾 | G37: 客服专员 | H37: 沈丽霞 | I37: 沈丽霞 | J37: 全日制 | K37: =AC37+BL37 -> 14917.57 | L37: =AC37-AM37-AX37-AY37+SUM(AZ37:BA37) -> 10155.62 | N37: 6 | O37: 11000 | P37: 838 | Q37: =VLOOKUP(I37,考勤调整记录!I:W,15,0) -> 0 | S37: 267.4 | U37: =SUM(O37:T37) -> 12105.4 | AC37: =SUM(O37:T37)+SUM(V37:AB37) -> 12105.4 | AE37: 202606 | AF37: =VLOOKUP(BW37,'HR|社保明细'!C:F,4,0) -> 7460 | AG37: =VLOOKUP($BW37,'HR|社保明细'!$C:G,5,0) -> 7384 | AH37: =VLOOKUP($BW37,'HR|社保明细'!$C:H,6,0) -> 596.8 | AI37: =VLOOKUP($BW37,'HR|社保明细'!$C:I,7,0) -> 149.2 | AJ37: =VLOOKUP($BW37,'HR|社保明细'!$C:J,8,0) -> 37.3 | AK37: =VLOOKUP($BW37,'HR|社保明细'!$C:K,9,0) -> 517 | AL37: =VLOOKUP($BW37,'HR|社保明细'!$C:L,10,0) -> 369 | AM37: =SUM(AH37:AL37) -> 1669.3 | AN37: 2000 | AQ37: 3000 | AS37: =AC37-AM37-SUM(AN37:AR37) -> 5436.1 | AU37: =VLOOKUP(BW37,hr.个税累计数据!C:DS,121,0) -> 81175.09 | AV37: =IF(AU37-5000*N37-VLOOKUP(A37,hr.个税累计数据!C:DT,122,0)-VLOOKUP(A37,hr.个税累计数据!C:DU,123,0)>0,AU37-5000*N37-VLOOKUP(A37,hr.个税累计数据!C:DT,122,0)-VLOOKUP(A37,hr.个税累计数据!C:DU,123,0),0) -> 11159.29 | AW37: =VLOOKUP(BW37,hr.个税累计数据!C:DV,124,0) -> 321.7 | AX37: 0 | AY37: =IF(ROUND(MAX(AV37*{0.03,0.1,0.2,0.25,0.3,0.35,0.45}-{0,210,1410,2660,4410,7160,15160}*12)-AW37,2)<=0,0,ROUND(MAX(AV37*{0.03,0.1,0.2,0.25,0.3,0.35,0.45}-{0,210,1410,2660,4410,7160,15160}*12)-AW37,2)) -> 13.08 | AZ37: =-S37 -> -267.4 | BB37: =AC37-AM37-AY37-AX37+SUM(AZ37:BA37) -> 10155.62 | BD37: =AC37-AM37-AX37-AY37+SUM(AZ37:BA37) -> 10155.62 | BE37: =VLOOKUP($BW37,'HR|社保明细'!C:T,11,0) -> 1193.6 | BF37: =VLOOKUP($BW37,'HR|社保明细'!$C:U,12,0) -> 596.8 | BG37: =VLOOKUP($BW37,'HR|社保明细'!$C:V,13,0) -> 37.3 | BH37: =VLOOKUP($BW37,'HR|社保明细'!$C:W,14,0) -> 23.87 | BI37: =VLOOKUP($BW37,'HR|社保明细'!$C:X,15,0) -> 74.6 | BJ37: =VLOOKUP($BW37,'HR|社保明细'!$C:Y,16,0) -> 517 | BK37: =VLOOKUP($BW37,'HR|社保明细'!$C:Z,17,0) -> 369 | BL37: =SUM(BE37:BK37) -> 2812.17 | BR37: =SUM(BN37:BQ37) -> 0 | BS37: =SUM(V37:AB37) -> 0 | BT37: 1250 | BW37: =C37&I37 -> 开弈人力资源沈丽霞 | BY37: 有 | BZ37: 人才 | CA37: =VLOOKUP(A37,hr.个税累计数据!C:C,1,0) -> 开弈人力资源沈丽霞 | CB37: 开弈人力资源沈丽霞 | CC37: 有 | CD37: =H37=I37 -> TRUE
A38: =C38&I38 -> 开弈人力资源宋广忠 | B38: HRO服务-代收代付残疾人 | C38: 开弈人力资源 | D38: 正常计税 | E38: 客户残疾人 | F38: 葛豪平 | G38: 残疾人 | H38: 宋广忠 | I38: 宋广忠 | J38: 代收代付残疾人 | K38: =AC38+BL38 -> 5449.47 | L38: =AC38-AM38-AX38-AY38+SUM(AZ38:BA38) -> 2740 | N38: 6 | O38: =3457.55+15.54-7.77+50+23.94-15.96 -> 3523.3 | U38: =SUM(O38:T38) -> 3523.3 | AC38: =SUM(O38:T38)+SUM(V38:AB38) -> 3523.3 | AE38: 202606 | AF38: =VLOOKUP(BW38,'HR|社保明细'!C:F,4,0) -> 7460 | AG38: =VLOOKUP($BW38,'HR|社保明细'!$C:G,5,0) -> 0 | AH38: =VLOOKUP($BW38,'HR|社保明细'!$C:H,6,0) -> 596.8 | AI38: =VLOOKUP($BW38,'HR|社保明细'!$C:I,7,0) -> 149.2 | AJ38: =VLOOKUP($BW38,'HR|社保明细'!$C:J,8,0) -> 37.3 | AK38: =VLOOKUP($BW38,'HR|社保明细'!$C:K,9,0) -> 0 | AL38: =VLOOKUP($BW38,'HR|社保明细'!$C:L,10,0) -> 0 | AM38: =SUM(AH38:AL38) -> 783.3 | AS38: =AC38-AM38-SUM(AN38:AR38) -> 2740 | AU38: =VLOOKUP(BW38,hr.个税累计数据!C:DS,121,0) -> 21139.8 | AV38: =IF(AU38-5000*N38-VLOOKUP(A38,hr.个税累计数据!C:DT,122,0)-VLOOKUP(A38,hr.个税累计数据!C:DU,123,0)>0,AU38-5000*N38-VLOOKUP(A38,hr.个税累计数据!C:DT,122,0)-VLOOKUP(A38,hr.个税累计数据!C:DU,123,0),0) -> 0 | AW38: =VLOOKUP(BW38,hr.个税累计数据!C:DV,124,0) -> 0 | AY38: =IF(ROUND(MAX(AV38*{0.03,0.1,0.2,0.25,0.3,0.35,0.45}-{0,210,1410,2660,4410,7160,15160}*12)-AW38,2)<=0,0,ROUND(MAX(AV38*{0.03,0.1,0.2,0.25,0.3,0.35,0.45}-{0,210,1410,2660,4410,7160,15160}*12)-AW38,2)) -> 0 | AZ38: =-S38 -> 0 | BB38: =AC38-AM38-AY38-AX38+SUM(AZ38:BA38) -> 2740 | BD38: =AC38-AM38-AX38-AY38+SUM(AZ38:BA38) -> 2740 | BE38: =VLOOKUP($BW38,'HR|社保明细'!C:T,11,0) -> 1193.6 | BF38: =VLOOKUP($BW38,'HR|社保明细'!$C:U,12,0) -> 596.8 | BG38: =VLOOKUP($BW38,'HR|社保明细'!$C:V,13,0) -> 37.3 | BH38: =VLOOKUP($BW38,'HR|社保明细'!$C:W,14,0) -> 23.87 | BI38: =VLOOKUP($BW38,'HR|社保明细'!$C:X,15,0) -> 74.6 | BJ38: =VLOOKUP($BW38,'HR|社保明细'!$C:Y,16,0) -> 0 | BK38: =VLOOKUP($BW38,'HR|社保明细'!$C:Z,17,0) -> 0 | BL38: =SUM(BE38:BK38) -> 1926.17 | BR38: =SUM(BN38:BQ38) -> 0 | BS38: =SUM(V38:AB38) -> 0 | BW38: =C38&I38 -> 开弈人力资源宋广忠 | BY38: 无 | CA38: =VLOOKUP(A38,hr.个税累计数据!C:C,1,0) -> 开弈人力资源宋广忠 | CB38: 开弈人力资源宋广忠 | CD38: =H38=I38 -> TRUE
A39: =C39&I39 -> 开弈人力资源王倩 | B39: 公司费用-待结算&法人&智名 | C39: 开弈人力资源 | D39: 劳务计税 | E39: 公司费用-法人 | F39: 张毅 | G39: 法人 | H39: 王倩 | I39: 王倩 | J39: 非全日制 | K39: =AC39+BL39 -> 1000 | L39: =AC39-AM39-AX39-AY39+SUM(AZ39:BA39) -> 960 | N39: 6 | O39: 1000 | U39: =SUM(O39:T39) -> 1000 | AC39: =SUM(O39:T39)+SUM(V39:AB39) -> 1000 | AE39: 202606 | AF39: =VLOOKUP(BW39,'HR|社保明细'!C:F,4,0) -> 0 | AG39: =VLOOKUP($BW39,'HR|社保明细'!$C:G,5,0) -> 0 | AH39: =VLOOKUP($BW39,'HR|社保明细'!$C:H,6,0) -> 0 | AI39: =VLOOKUP($BW39,'HR|社保明细'!$C:I,7,0) -> 0 | AJ39: =VLOOKUP($BW39,'HR|社保明细'!$C:J,8,0) -> 0 | AK39: =VLOOKUP($BW39,'HR|社保明细'!$C:K,9,0) -> 0 | AL39: =VLOOKUP($BW39,'HR|社保明细'!$C:L,10,0) -> 0 | AM39: =SUM(AH39:AL39) -> 0 | AS39: 1000 | AU39: =VLOOKUP(BW39,hr.个税累计数据!C:DS,121,0) -> 6000 | AV39: =IF(AU39-5000*N39-VLOOKUP(A39,hr.个税累计数据!C:DT,122,0)-VLOOKUP(A39,hr.个税累计数据!C:DU,123,0)>0,AU39-5000*N39-VLOOKUP(A39,hr.个税累计数据!C:DT,122,0)-VLOOKUP(A39,hr.个税累计数据!C:DU,123,0),0) -> 0 | AW39: =VLOOKUP(BW39,hr.个税累计数据!C:DV,124,0) -> 200 | AY39: =IF(D39="国内不计税",0,IF(D39="正常计税",ROUND(MAX(AS39*{0.03,0.1,0.2,0.25,0.3,0.35,0.45}-{0,210,1410,2660,4410,7160,15160},0),2),IF(D39="外籍人",ROUND(MAX(AS39*{0.03,0.1,0.2,0.25,0.3,0.35,0.45}-{0,210,1410,2660,4410,7160,15160},0),2),ROUND(MAX((AS39-IF(AS39<4000,800,AS39*0.2))*10%*{2,3,4}-1000*{0,2,7},0),2)))) -> 40 | AZ39: =-S39 -> 0 | BB39: =AC39-AM39-AY39-AX39+SUM(AZ39:BA39) -> 960 | BD39: =AC39-AM39-AX39-AY39+SUM(AZ39:BA39) -> 960 | BE39: =VLOOKUP($BW39,'HR|社保明细'!C:T,11,0) -> 0 | BF39: =VLOOKUP($BW39,'HR|社保明细'!$C:U,12,0) -> 0 | BG39: =VLOOKUP($BW39,'HR|社保明细'!$C:V,13,0) -> 0 | BH39: =VLOOKUP($BW39,'HR|社保明细'!$C:W,14,0) -> 0 | BI39: =VLOOKUP($BW39,'HR|社保明细'!$C:X,15,0) -> 0 | BJ39: =VLOOKUP($BW39,'HR|社保明细'!$C:Y,16,0) -> 0 | BK39: =VLOOKUP($BW39,'HR|社保明细'!$C:Z,17,0) -> 0 | BL39: =SUM(BE39:BK39) -> 0 | BR39: =SUM(BN39:BQ39) -> 0 | BS39: =SUM(V39:AB39) -> 0 | BW39: =C39&I39 -> 开弈人力资源王倩 | BX39: 无社公 | BY39: 无 | CA39: =VLOOKUP(A39,hr.个税累计数据!C:C,1,0) -> 开弈人力资源王倩 | CB39: 开弈人力资源王倩 | CD39: =H39=I39 -> TRUE
A40: =C40&I40 -> 开弈人力资源徐丽红 | B40: HRO服务-代收代付残疾人 | C40: 开弈人力资源 | D40: 正常计税 | E40: 客户残疾人 | F40: 葛豪平 | G40: 残疾人 | H40: 徐丽红 | I40: 徐丽红 | J40: 代收代付残疾人 | K40: =AC40+BL40 -> 5449.47 | L40: =AC40-AM40-AX40-AY40+SUM(AZ40:BA40) -> 2740 | N40: 6 | O40: =3457.55+15.54-7.77+50+23.94-15.96 -> 3523.3 | U40: =SUM(O40:T40) -> 3523.3 | AC40: =SUM(O40:T40)+SUM(V40:AB40) -> 3523.3 | AE40: 202606 | AF40: =VLOOKUP(BW40,'HR|社保明细'!C:F,4,0) -> 7460 | AG40: =VLOOKUP($BW40,'HR|社保明细'!$C:G,5,0) -> 0 | AH40: =VLOOKUP($BW40,'HR|社保明细'!$C:H,6,0) -> 596.8 | AI40: =VLOOKUP($BW40,'HR|社保明细'!$C:I,7,0) -> 149.2 | AJ40: =VLOOKUP($BW40,'HR|社保明细'!$C:J,8,0) -> 37.3 | AK40: =VLOOKUP($BW40,'HR|社保明细'!$C:K,9,0) -> 0 | AL40: =VLOOKUP($BW40,'HR|社保明细'!$C:L,10,0) -> 0 | AM40: =SUM(AH40:AL40) -> 783.3 | AS40: =AC40-AM40-SUM(AN40:AR40) -> 2740 | AU40: =VLOOKUP(BW40,hr.个税累计数据!C:DS,121,0) -> 21139.8 | AV40: =IF(AU40-5000*N40-VLOOKUP(A40,hr.个税累计数据!C:DT,122,0)-VLOOKUP(A40,hr.个税累计数据!C:DU,123,0)>0,AU40-5000*N40-VLOOKUP(A40,hr.个税累计数据!C:DT,122,0)-VLOOKUP(A40,hr.个税累计数据!C:DU,123,0),0) -> 0 | AW40: =VLOOKUP(BW40,hr.个税累计数据!C:DV,124,0) -> 0 | AY40: =IF(ROUND(MAX(AV40*{0.03,0.1,0.2,0.25,0.3,0.35,0.45}-{0,210,1410,2660,4410,7160,15160}*12)-AW40,2)<=0,0,ROUND(MAX(AV40*{0.03,0.1,0.2,0.25,0.3,0.35,0.45}-{0,210,1410,2660,4410,7160,15160}*12)-AW40,2)) -> 0 | AZ40: =-S40 -> 0 | BB40: =AC40-AM40-AY40-AX40+SUM(AZ40:BA40) -> 2740 | BD40: =AC40-AM40-AX40-AY40+SUM(AZ40:BA40) -> 2740 | BE40: =VLOOKUP($BW40,'HR|社保明细'!C:T,11,0) -> 1193.6 | BF40: =VLOOKUP($BW40,'HR|社保明细'!$C:U,12,0) -> 596.8 | BG40: =VLOOKUP($BW40,'HR|社保明细'!$C:V,13,0) -> 37.3 | BH40: =VLOOKUP($BW40,'HR|社保明细'!$C:W,14,0) -> 23.87 | BI40: =VLOOKUP($BW40,'HR|社保明细'!$C:X,15,0) -> 74.6 | BJ40: =VLOOKUP($BW40,'HR|社保明细'!$C:Y,16,0) -> 0 | BK40: =VLOOKUP($BW40,'HR|社保明细'!$C:Z,17,0) -> 0 | BL40: =SUM(BE40:BK40) -> 1926.17 | BR40: =SUM(BN40:BQ40) -> 0 | BS40: =SUM(V40:AB40) -> 0 | BW40: =C40&I40 -> 开弈人力资源徐丽红 | BY40: 无 | CA40: =VLOOKUP(A40,hr.个税累计数据!C:C,1,0) -> 开弈人力资源徐丽红 | CB40: 开弈人力资源徐丽红 | CD40: =H40=I40 -> TRUE
A41: =C41&I41 -> 开弈人力资源杨漾 | B41: Shaun-客服部 | C41: 开弈人力资源 | D41: 正常计税 | E41: 客服部（S） | F41: 黄一萧 | G41: 客服主管 | H41: 杨漾 | I41: 杨漾 | J41: 全日制 | K41: =AC41+BL41 -> 24199.8 | L41: =AC41-AM41-AX41-AY41+SUM(AZ41:BA41) -> 16995.22 | N41: 6 | O41: 20000 | P41: 262 | Q41: =VLOOKUP(I41,考勤调整记录!I:W,15,0) -> 0 | S41: 155.8 | U41: =SUM(O41:T41) -> 20417.8 | AC41: =SUM(O41:T41)+SUM(V41:AB41) -> 20417.8 | AE41: 202606 | AF41: =VLOOKUP(BW41,'HR|社保明细'!C:F,4,0) -> 10000 | AG41: =VLOOKUP($BW41,'HR|社保明细'!$C:G,5,0) -> 10000 | AH41: =VLOOKUP($BW41,'HR|社保明细'!$C:H,6,0) -> 800 | AI41: =VLOOKUP($BW41,'HR|社保明细'!$C:I,7,0) -> 200 | AJ41: =VLOOKUP($BW41,'HR|社保明细'!$C:J,8,0) -> 50 | AK41: =VLOOKUP($BW41,'HR|社保明细'!$C:K,9,0) -> 700 | AL41: =VLOOKUP($BW41,'HR|社保明细'!$C:L,10,0) -> 500 | AM41: =SUM(AH41:AL41) -> 2250 | AQ41: 3000 | AS41: =AC41-AM41-SUM(AN41:AR41) -> 15167.8 | AU41: =VLOOKUP(BW41,hr.个税累计数据!C:DS,121,0) -> 143768.79 | AV41: =IF(AU41-5000*N41-VLOOKUP(A41,hr.个税累计数据!C:DT,122,0)-VLOOKUP(A41,hr.个税累计数据!C:DU,123,0)>0,AU41-5000*N41-VLOOKUP(A41,hr.个税累计数据!C:DT,122,0)-VLOOKUP(A41,hr.个税累计数据!C:DU,123,0),0) -> 82268.79 | AW41: =VLOOKUP(BW41,hr.个税累计数据!C:DV,124,0) -> 4690.1 | AY41: =IF(ROUND(MAX(AV41*{0.03,0.1,0.2,0.25,0.3,0.35,0.45}-{0,210,1410,2660,4410,7160,15160}*12)-AW41,2)<=0,0,ROUND(MAX(AV41*{0.03,0.1,0.2,0.25,0.3,0.35,0.45}-{0,210,1410,2660,4410,7160,15160}*12)-AW41,2)) -> 1016.78 | AZ41: =-S41 -> -155.8 | BB41: =AC41-AM41-AY41-AX41+SUM(AZ41:BA41) -> 16995.22 | BD41: =AC41-AM41-AX41-AY41+SUM(AZ41:BA41) -> 16995.22 | BE41: =VLOOKUP($BW41,'HR|社保明细'!C:T,11,0) -> 1600 | BF41: =VLOOKUP($BW41,'HR|社保明细'!$C:U,12,0) -> 800 | BG41: =VLOOKUP($BW41,'HR|社保明细'!$C:V,13,0) -> 50 | BH41: =VLOOKUP($BW41,'HR|社保明细'!$C:W,14,0) -> 32 | BI41: =VLOOKUP($BW41,'HR|社保明细'!$C:X,15,0) -> 100 | BJ41: =VLOOKUP($BW41,'HR|社保明细'!$C:Y,16,0) -> 700 | BK41: =VLOOKUP($BW41,'HR|社保明细'!$C:Z,17,0) -> 500 | BL41: =SUM(BE41:BK41) -> 3782 | BR41: =SUM(BN41:BQ41) -> 0 | BS41: =SUM(V41:AB41) -> 0 | BT41: 1250 | BW41: =C41&I41 -> 开弈人力资源杨漾 | BY41: 有 | BZ41: 人才 | CA41: =VLOOKUP(A41,hr.个税累计数据!C:C,1,0) -> 开弈人力资源杨漾 | CB41: 开弈人力资源杨漾 | CC41: 有 | CD41: =H41=I41 -> TRUE
A42: =C42&I42 -> 开弈人才张祥 | B42: Shaun-雇员服务部 | C42: 开弈人才 | D42: 正常计税 | E42: 社保部 | F42: 葛豪平 | G42: 社保专员 | H42: 张祥 | I42: 张祥 | J42: 全日制 | K42: =AC42+BL42 -> 11474.83 | L42: =AC42-AM42-AX42-AY42+SUM(AZ42:BA42) -> 7493.62 | N42: 6 | O42: 9000 | Q42: =VLOOKUP(I42,考勤调整记录!I:W,15,0) -> -124.14 | S42: 155.8 | U42: =SUM(O42:T42) -> 9031.66 | AC42: =SUM(O42:T42)+SUM(V42:AB42) -> 9031.66 | AE42: 202606 | AF42: =VLOOKUP(BW42,'HR|社保明细'!C:F,4,0) -> 7460 | AG42: =VLOOKUP($BW42,'HR|社保明细'!$C:G,5,0) -> 7384 | AH42: =VLOOKUP($BW42,'HR|社保明细'!$C:H,6,0) -> 596.8 | AI42: =VLOOKUP($BW42,'HR|社保明细'!$C:I,7,0) -> 149.2 | AJ42: =VLOOKUP($BW42,'HR|社保明细'!$C:J,8,0) -> 37.3 | AK42: =VLOOKUP($BW42,'HR|社保明细'!$C:K,9,0) -> 517 | AL42: =VLOOKUP($BW42,'HR|社保明细'!$C:L,10,0) -> 0 | AM42: =SUM(AH42:AL42) -> 1300.3 | AS42: =AC42-AM42-SUM(AN42:AR42) -> 7731.36 | AU42: =VLOOKUP(BW42,hr.个税累计数据!C:DS,121,0) -> 59074.01 | AV42: =IF(AU42-5000*N42-VLOOKUP(A42,hr.个税累计数据!C:DT,122,0)-VLOOKUP(A42,hr.个税累计数据!C:DU,123,0)>0,AU42-5000*N42-VLOOKUP(A42,hr.个税累计数据!C:DT,122,0)-VLOOKUP(A42,hr.个税累计数据!C:DU,123,0),0) -> 21272.21 | AW42: =VLOOKUP(BW42,hr.个税累计数据!C:DV,124,0) -> 556.23 | AY42: =IF(ROUND(MAX(AV42*{0.03,0.1,0.2,0.25,0.3,0.35,0.45}-{0,210,1410,2660,4410,7160,15160}*12)-AW42,2)<=0,0,ROUND(MAX(AV42*{0.03,0.1,0.2,0.25,0.3,0.35,0.45}-{0,210,1410,2660,4410,7160,15160}*12)-AW42,2)) -> 81.94 | AZ42: =-S42 -> -155.8 | BB42: =AC42-AM42-AY42-AX42+SUM(AZ42:BA42) -> 7493.62 | BD42: =AC42-AM42-AX42-AY42+SUM(AZ42:BA42) -> 7493.62 | BE42: =VLOOKUP($BW42,'HR|社保明细'!C:T,11,0) -> 1193.6 | BF42: =VLOOKUP($BW42,'HR|社保明细'!$C:U,12,0) -> 596.8 | BG42: =VLOOKUP($BW42,'HR|社保明细'!$C:V,13,0) -> 37.3 | BH42: =VLOOKUP($BW42,'HR|社保明细'!$C:W,14,0) -> 23.87 | BI42: =VLOOKUP($BW42,'HR|社保明细'!$C:X,15,0) -> 74.6 | BJ42: =VLOOKUP($BW42,'HR|社保明细'!$C:Y,16,0) -> 517 | BK42: =VLOOKUP($BW42,'HR|社保明细'!$C:Z,17,0) -> 0 | BL42: =SUM(BE42:BK42) -> 2443.17 | BR42: =SUM(BN42:BQ42) -> 0 | BS42: =SUM(V42:AB42) -> 0 | BT42: 1250 | BW42: =C42&I42 -> 开弈人才张祥 | BY42: 有 | BZ42: 人才 | CA42: =VLOOKUP(A42,hr.个税累计数据!C:C,1,0) -> 开弈人才张祥 | CB42: 开弈人才张祥 | CC42: 有 | CD42: =H42=I42 -> TRUE
A43: =C43&I43 -> 开弈投资韩燕 | B43: F-大财务部 | C43: 开弈投资 | D43: 正常计税 | E43: 财务部 | F43: 蔡心宇 | G43: 会计 | H43: 韩燕 | I43: 韩燕 | J43: 全日制 | K43: =AC43+BL43 -> 12869.62 | L43: =AC43-AM43-AX43-AY43+SUM(AZ43:BA43) -> 8129.7 | N43: 6 | O43: 10000 | P43: 170 | Q43: =VLOOKUP(I43,考勤调整记录!I:W,15,0) -> 0 | S43: 267.4 | U43: =SUM(O43:T43) -> 10437.4 | W43: =ROUND((O43)*(0.9629-1),2) -> -371 | AC43: =SUM(O43:T43)+SUM(V43:AB43) -> 10066.4 | AE43: 202606 | AF43: =VLOOKUP(BW43,'HR|社保明细'!C:F,4,0) -> 7460 | AG43: =VLOOKUP($BW43,'HR|社保明细'!$C:G,5,0) -> 7384 | AH43: =VLOOKUP($BW43,'HR|社保明细'!$C:H,6,0) -> 596.8 | AI43: =VLOOKUP($BW43,'HR|社保明细'!$C:I,7,0) -> 149.2 | AJ43: =VLOOKUP($BW43,'HR|社保明细'!$C:J,8,0) -> 37.3 | AK43: =VLOOKUP($BW43,'HR|社保明细'!$C:K,9,0) -> 517 | AL43: =VLOOKUP($BW43,'HR|社保明细'!$C:L,10,0) -> 369 | AM43: =SUM(AH43:AL43) -> 1669.3 | AQ43: 3000 | AS43: =AC43-AM43-SUM(AN43:AR43) -> 5397.1 | AU43: =VLOOKUP(BW43,hr.个税累计数据!C:DS,121,0) -> 61411.31 | AV43: =IF(AU43-5000*N43-VLOOKUP(A43,hr.个税累计数据!C:DT,122,0)-VLOOKUP(A43,hr.个税累计数据!C:DU,123,0)>0,AU43-5000*N43-VLOOKUP(A43,hr.个税累计数据!C:DT,122,0)-VLOOKUP(A43,hr.个税累计数据!C:DU,123,0),0) -> 0 | AW43: =VLOOKUP(BW43,hr.个税累计数据!C:DV,124,0) -> 0 | AY43: =IF(ROUND(MAX(AV43*{0.03,0.1,0.2,0.25,0.3,0.35,0.45}-{0,210,1410,2660,4410,7160,15160}*12)-AW43,2)<=0,0,ROUND(MAX(AV43*{0.03,0.1,0.2,0.25,0.3,0.35,0.45}-{0,210,1410,2660,4410,7160,15160}*12)-AW43,2)) -> 0 | AZ43: =-S43 -> -267.4 | BB43: =AC43-AM43-AY43-AX43+SUM(AZ43:BA43) -> 8129.7 | BD43: =AC43-AM43-AX43-AY43+SUM(AZ43:BA43) -> 8129.7 | BE43: =VLOOKUP($BW43,'HR|社保明细'!C:T,11,0) -> 1193.6 | BF43: =VLOOKUP($BW43,'HR|社保明细'!$C:U,12,0) -> 596.8 | BG43: =VLOOKUP($BW43,'HR|社保明细'!$C:V,13,0) -> 37.3 | BH43: =VLOOKUP($BW43,'HR|社保明细'!$C:W,14,0) -> 14.92 | BI43: =VLOOKUP($BW43,'HR|社保明细'!$C:X,15,0) -> 74.6 | BJ43: =VLOOKUP($BW43,'HR|社保明细'!$C:Y,16,0) -> 517 | BK43: =VLOOKUP($BW43,'HR|社保明细'!$C:Z,17,0) -> 369 | BL43: =SUM(BE43:BK43) -> 2803.22 | BR43: =SUM(BN43:BQ43) -> 0 | BS43: =SUM(V43:AB43) -> -371 | BT43: 1250 | BW43: =C43&I43 -> 开弈投资韩燕 | BY43: 有 | BZ43: 后台 | CA43: =VLOOKUP(A43,hr.个税累计数据!C:C,1,0) -> 开弈投资韩燕 | CB43: 开弈投资韩燕 | CC43: 有 | CD43: =H43=I43 -> TRUE
A44: =C44&I44 -> 开弈投资金学忠 | B44: 物业维修部 | C44: 开弈投资 | D44: 正常计税 | E44: 物业维修部 | F44: 方有保 | G44: 水电工程师 | H44: 金学忠 | I44: 金学忠 | J44: 不定时工作制 | K44: =AC44+BL44 -> 12421.8 | L44: =AC44-AM44-AX44-AY44+SUM(AZ44:BA44) -> 8147.82 | N44: 6 | O44: 9350 | Q44: =VLOOKUP(I44,考勤调整记录!I:W,15,0) -> 0 | S44: 155.8 | U44: =SUM(O44:T44) -> 9505.8 | Y44: 300 | AC44: =SUM(O44:T44)+SUM(V44:AB44) -> 9805.8 | AE44: 202606 | AF44: =VLOOKUP(BW44,'HR|社保明细'!C:F,4,0) -> 8000 | AG44: =VLOOKUP($BW44,'HR|社保明细'!$C:G,5,0) -> 8000 | AH44: =VLOOKUP($BW44,'HR|社保明细'!$C:H,6,0) -> 640 | AI44: =VLOOKUP($BW44,'HR|社保明细'!$C:I,7,0) -> 160 | AJ44: =VLOOKUP($BW44,'HR|社保明细'!$C:J,8,0) -> 40 | AK44: =VLOOKUP($BW44,'HR|社保明细'!$C:K,9,0) -> 560 | AL44: =VLOOKUP($BW44,'HR|社保明细'!$C:L,10,0) -> 0 | AM44: =SUM(AH44:AL44) -> 1400 | AS44: =AC44-AM44-SUM(AN44:AR44) -> 8405.8 | AU44: =VLOOKUP(BW44,hr.个税累计数据!C:DS,121,0) -> 60648.54 | AV44: =IF(AU44-5000*N44-VLOOKUP(A44,hr.个税累计数据!C:DT,122,0)-VLOOKUP(A44,hr.个税累计数据!C:DU,123,0)>0,AU44-5000*N44-VLOOKUP(A44,hr.个税累计数据!C:DT,122,0)-VLOOKUP(A44,hr.个税累计数据!C:DU,123,0),0) -> 22248.54 | AW44: =VLOOKUP(BW44,hr.个税累计数据!C:DV,124,0) -> 565.28 | AY44: =IF(ROUND(MAX(AV44*{0.03,0.1,0.2,0.25,0.3,0.35,0.45}-{0,210,1410,2660,4410,7160,15160}*12)-AW44,2)<=0,0,ROUND(MAX(AV44*{0.03,0.1,0.2,0.25,0.3,0.35,0.45}-{0,210,1410,2660,4410,7160,15160}*12)-AW44,2)) -> 102.18 | AZ44: =-S44 -> -155.8 | BB44: =AC44-AM44-AY44-AX44+SUM(AZ44:BA44) -> 8147.82 | BD44: =AC44-AM44-AX44-AY44+SUM(AZ44:BA44) -> 8147.82 | BE44: =VLOOKUP($BW44,'HR|社保明细'!C:T,11,0) -> 1280 | BF44: =VLOOKUP($BW44,'HR|社保明细'!$C:U,12,0) -> 640 | BG44: =VLOOKUP($BW44,'HR|社保明细'!$C:V,13,0) -> 40 | BH44: =VLOOKUP($BW44,'HR|社保明细'!$C:W,14,0) -> 16 | BI44: =VLOOKUP($BW44,'HR|社保明细'!$C:X,15,0) -> 80 | BJ44: =VLOOKUP($BW44,'HR|社保明细'!$C:Y,16,0) -> 560 | BK44: =VLOOKUP($BW44,'HR|社保明细'!$C:Z,17,0) -> 0 | BL44: =SUM(BE44:BK44) -> 2616 | BR44: =SUM(BN44:BQ44) -> 0 | BS44: =SUM(V44:AB44) -> 300 | BT44: 1250 | BW44: =C44&I44 -> 开弈投资金学忠 | BY44: 有 | BZ44: 物业 | CA44: =VLOOKUP(A44,hr.个税累计数据!C:C,1,0) -> 开弈投资金学忠 | CB44: 开弈投资金学忠 | CC44: 有 | CD44: =H44=I44 -> TRUE
A45: =C45&I45 -> 开弈投资韩喆 | B45: 园区-商办&企业服务 | C45: 开弈投资 | D45: 劳务计税 | E45: 办公&企业服务 | F45: 张毅 | G45: 商办总经理 | H45: 韩喆 | I45: 韩喆 | J45: 非全日制 | K45: =AC45+BL45 -> 24285.28 | L45: =AC45-AM45-AX45-AY45+SUM(AZ45:BA45) -> 20399.64 | N45: 6 | O45: 50000 | Q45: =VLOOKUP(I45,考勤调整记录!I:W,15,0) -> -22988.51 | U45: =SUM(O45:T45) -> 27011.49 | W45: -2726.21 | AC45: =SUM(O45:T45)+SUM(V45:AB45) -> 24285.28 | AE45: 202606 | AF45: =VLOOKUP(BW45,'HR|社保明细'!C:F,4,0) -> 0 | AG45: =VLOOKUP($BW45,'HR|社保明细'!$C:G,5,0) -> 0 | AH45: =VLOOKUP($BW45,'HR|社保明细'!$C:H,6,0) -> 0 | AI45: =VLOOKUP($BW45,'HR|社保明细'!$C:I,7,0) -> 0 | AJ45: =VLOOKUP($BW45,'HR|社保明细'!$C:J,8,0) -> 0 | AK45: =VLOOKUP($BW45,'HR|社保明细'!$C:K,9,0) -> 0 | AL45: =VLOOKUP($BW45,'HR|社保明细'!$C:L,10,0) -> 0 | AM45: =SUM(AH45:AL45) -> 0 | AS45: =AC45-AM45-SUM(AN45:AR45) -> 24285.28 | AU45: =VLOOKUP(BW45,hr.个税累计数据!C:DS,121,0) -> 246445.34 | AV45: =IF(AU45-5000*N45-VLOOKUP(A45,hr.个税累计数据!C:DT,122,0)-VLOOKUP(A45,hr.个税累计数据!C:DU,123,0)>0,AU45-5000*N45-VLOOKUP(A45,hr.个税累计数据!C:DT,122,0)-VLOOKUP(A45,hr.个税累计数据!C:DU,123,0),0) -> 216445.34 | AW45: =VLOOKUP(BW45,hr.个税累计数据!C:DV,124,0) -> 52484.57 | AY45: {=IF(D45="国内不计税",0,IF(D45="正常计税",ROUND(MAX(AS45*{0.03,0.1,0.2,0.25,0.3,0.35,0.45}-{0,210,1410,2660,4410,7160,15160},0),2),IF(D45="外籍人",ROUND(MAX(AS45*{0.03,0.1,0.2,0.25,0.3,0.35,0.45}-{0,210,1410,2660,4410,7160,15160},0),2),ROUND(MAX((AS45-IF(AS45<4000,800,AS45*0.2))*10%*{2,3,4}-1000*{0,2,7},0),2))))} -> 3885.64 | AZ45: =-S45 -> 0 | BB45: =AC45-AM45-AY45-AX45+SUM(AZ45:BA45) -> 20399.64 | BD45: =AC45-AM45-AX45-AY45+SUM(AZ45:BA45) -> 20399.64 | BE45: =VLOOKUP($BW45,'HR|社保明细'!C:T,11,0) -> 0 | BF45: =VLOOKUP($BW45,'HR|社保明细'!$C:U,12,0) -> 0 | BG45: =VLOOKUP($BW45,'HR|社保明细'!$C:V,13,0) -> 0 | BH45: =VLOOKUP($BW45,'HR|社保明细'!$C:W,14,0) -> 0 | BI45: =VLOOKUP($BW45,'HR|社保明细'!$C:X,15,0) -> 0 | BJ45: =VLOOKUP($BW45,'HR|社保明细'!$C:Y,16,0) -> 0 | BK45: =VLOOKUP($BW45,'HR|社保明细'!$C:Z,17,0) -> 0 | BL45: =SUM(BE45:BK45) -> 0 | BR45: =SUM(BN45:BQ45) -> 0 | BS45: =SUM(V45:AB45) -> -2726.21 | BT45: 1250 | BW45: =C45&I45 -> 开弈投资韩喆 | BY45: 无 | BZ45: 商办 | CA45: =VLOOKUP(A45,hr.个税累计数据!C:C,1,0) -> 开弈投资韩喆 | CB45: 开弈投资韩喆 | CD45: =H45=I45 -> TRUE
A46: =C46&I46 -> 开弈投资李佳 | B46: F-账务部 | C46: 开弈投资 | D46: 正常计税 | E46: 账务部 | F46: 王倩 | G46: 账务专员 | H46: 李佳 | I46: 李佳 | J46: 全日制 | K46: =AC46+BL46 -> 11204.28 | L46: =AC46-AM46-AX46-AY46+SUM(AZ46:BA46) -> 6268.28 | N46: 6 | O46: 8200 | Q46: =VLOOKUP(I46,考勤调整记录!I:W,15,0) -> 0 | S46: 267.4 | U46: =SUM(O46:T46) -> 8467.4 | W46: =ROUND((O46)*(0.9629-1),2) -> -304.22 | AC46: =SUM(O46:T46)+SUM(V46:AB46) -> 8163.18 | AE46: 202606 | AF46: =VLOOKUP(BW46,'HR|社保明细'!C:F,4,0) -> 9300 | AG46: =VLOOKUP($BW46,'HR|社保明细'!$C:G,5,0) -> 9300 | AH46: =VLOOKUP($BW46,'HR|社保明细'!$C:H,6,0) -> 744 | AI46: =VLOOKUP($BW46,'HR|社保明细'!$C:I,7,0) -> 186 | AJ46: =VLOOKUP($BW46,'HR|社保明细'!$C:J,8,0) -> 46.5 | AK46: =VLOOKUP($BW46,'HR|社保明细'!$C:K,9,0) -> 651 | AL46: =VLOOKUP($BW46,'HR|社保明细'!$C:L,10,0) -> 0 | AM46: =SUM(AH46:AL46) -> 1627.5 | AP46: 1500 | AQ46: 3000 | AS46: =AC46-AM46-SUM(AN46:AR46) -> 2035.68 | AU46: =VLOOKUP(BW46,hr.个税累计数据!C:DS,121,0) -> 46340.34 | AV46: =IF(AU46-5000*N46-VLOOKUP(A46,hr.个税累计数据!C:DT,122,0)-VLOOKUP(A46,hr.个税累计数据!C:DU,123,0)>0,AU46-5000*N46-VLOOKUP(A46,hr.个税累计数据!C:DT,122,0)-VLOOKUP(A46,hr.个税累计数据!C:DU,123,0),0) -> 0 | AW46: =VLOOKUP(BW46,hr.个税累计数据!C:DV,124,0) -> 0 | AY46: =IF(ROUND(MAX(AV46*{0.03,0.1,0.2,0.25,0.3,0.35,0.45}-{0,210,1410,2660,4410,7160,15160}*12)-AW46,2)<=0,0,ROUND(MAX(AV46*{0.03,0.1,0.2,0.25,0.3,0.35,0.45}-{0,210,1410,2660,4410,7160,15160}*12)-AW46,2)) -> 0 | AZ46: =-S46 -> -267.4 | BB46: =AC46-AM46-AY46-AX46+SUM(AZ46:BA46) -> 6268.28 | BD46: =AC46-AM46-AX46-AY46+SUM(AZ46:BA46) -> 6268.28 | BE46: =VLOOKUP($BW46,'HR|社保明细'!C:T,11,0) -> 1488 | BF46: =VLOOKUP($BW46,'HR|社保明细'!$C:U,12,0) -> 744 | BG46: =VLOOKUP($BW46,'HR|社保明细'!$C:V,13,0) -> 46.5 | BH46: =VLOOKUP($BW46,'HR|社保明细'!$C:W,14,0) -> 18.6 | BI46: =VLOOKUP($BW46,'HR|社保明细'!$C:X,15,0) -> 93 | BJ46: =VLOOKUP($BW46,'HR|社保明细'!$C:Y,16,0) -> 651 | BK46: =VLOOKUP($BW46,'HR|社保明细'!$C:Z,17,0) -> 0 | BL46: =SUM(BE46:BK46) -> 3041.1 | BR46: =SUM(BN46:BQ46) -> 0 | BS46: =SUM(V46:AB46) -> -304.22 | BT46: 1250 | BW46: =C46&I46 -> 开弈投资李佳 | BY46: 有 | BZ46: 后台 | CA46: =VLOOKUP(A46,hr.个税累计数据!C:C,1,0) -> 开弈投资李佳 | CB46: 开弈投资李佳 | CC46: 有 | CD46: =H46=I46 -> TRUE
A47: =C47&I47 -> 开弈投资周凯楠 | B47: C-大后台-行政 | C47: 开弈投资 | D47: 正常计税 | E47: 行政部 | F47: 蔡心宇 | G47: 人事助理 | H47: 周凯楠 | I47: 周凯楠 | J47: 全日制 | K47: =AC47+BL47 -> 8848.87 | L47: =AC47-AM47-AX47-AY47+SUM(AZ47:BA47) -> 4958.55 | N47: 6 | O47: =6500 -> 6500 | Q47: =VLOOKUP(I47,考勤调整记录!I:W,15,0) -> 0 | S47: 155.8 | U47: =SUM(O47:T47) -> 6655.8 | W47: -241.15 | AC47: =SUM(O47:T47)+SUM(V47:AB47) -> 6414.65 | AE47: 202606 | AF47: =VLOOKUP(BW47,'HR|社保明细'!C:F,4,0) -> 7460 | AG47: =VLOOKUP($BW47,'HR|社保明细'!$C:G,5,0) -> 7384 | AH47: =VLOOKUP($BW47,'HR|社保明细'!$C:H,6,0) -> 596.8 | AI47: =VLOOKUP($BW47,'HR|社保明细'!$C:I,7,0) -> 149.2 | AJ47: =VLOOKUP($BW47,'HR|社保明细'!$C:J,8,0) -> 37.3 | AK47: =VLOOKUP($BW47,'HR|社保明细'!$C:K,9,0) -> 517 | AL47: =VLOOKUP($BW47,'HR|社保明细'!$C:L,10,0) -> 0 | AM47: =SUM(AH47:AL47) -> 1300.3 | AS47: =AC47-AM47-SUM(AN47:AR47) -> 5114.35 | AU47: =VLOOKUP(BW47,hr.个税累计数据!C:DS,121,0) -> 36351.12 | AV47: =IF(AU47-5000*N47-VLOOKUP(A47,hr.个税累计数据!C:DT,122,0)-VLOOKUP(A47,hr.个税累计数据!C:DU,123,0)>0,AU47-5000*N47-VLOOKUP(A47,hr.个税累计数据!C:DT,122,0)-VLOOKUP(A47,hr.个税累计数据!C:DU,123,0),0) -> 0 | AW47: =VLOOKUP(BW47,hr.个税累计数据!C:DV,124,0) -> 10.34 | AY47: =IF(ROUND(MAX(AV47*{0.03,0.1,0.2,0.25,0.3,0.35,0.45}-{0,210,1410,2660,4410,7160,15160}*12)-AW47,2)<=0,0,ROUND(MAX(AV47*{0.03,0.1,0.2,0.25,0.3,0.35,0.45}-{0,210,1410,2660,4410,7160,15160}*12)-AW47,2)) -> 0 | AZ47: =-S47 -> -155.8 | BB47: =AC47-AM47-AY47-AX47+SUM(AZ47:BA47) -> 4958.55 | BD47: =AC47-AM47-AX47-AY47+SUM(AZ47:BA47) -> 4958.55 | BE47: =VLOOKUP($BW47,'HR|社保明细'!C:T,11,0) -> 1193.6 | BF47: =VLOOKUP($BW47,'HR|社保明细'!$C:U,12,0) -> 596.8 | BG47: =VLOOKUP($BW47,'HR|社保明细'!$C:V,13,0) -> 37.3 | BH47: =VLOOKUP($BW47,'HR|社保明细'!$C:W,14,0) -> 14.92 | BI47: =VLOOKUP($BW47,'HR|社保明细'!$C:X,15,0) -> 74.6 | BJ47: =VLOOKUP($BW47,'HR|社保明细'!$C:Y,16,0) -> 517 | BK47: =VLOOKUP($BW47,'HR|社保明细'!$C:Z,17,0) -> 0 | BL47: =SUM(BE47:BK47) -> 2434.22 | BR47: =SUM(BN47:BQ47) -> 0 | BS47: =SUM(V47:AB47) -> -241.15 | BT47: 1250 | BW47: =C47&I47 -> 开弈投资周凯楠 | BY47: 有 | BZ47: 后台 | CA47: =VLOOKUP(A47,hr.个税累计数据!C:C,1,0) -> 开弈投资周凯楠 | CB47: 开弈投资周凯楠 | CC47: 有 | CD47: =H47=I47 -> TRUE
A48: =C48&I48 -> 老龙馄饨-灵工谢志毅 | B48: 老龙馄饨 | C48: 老龙馄饨-灵工 | D48: 正常计税 | E48: 老龙馄饨 | F48: 蔡心宇 | G48: 厨师 | H48: 谢志毅 | I48: 谢志毅 | J48: 全日制 | K48: =AC48+BL48 -> 13873.6 | L48: =AC48-AM48-AX48-AY48+SUM(AZ48:BA48) -> 12838 | N48: 6 | O48: 13873.6 | Q48: =VLOOKUP(I48,考勤调整记录!I:W,15,0) -> 0 | U48: =SUM(O48:T48) -> 13873.6 | AC48: =SUM(O48:T48)+SUM(V48:AB48) -> 13873.6 | AE48: 202606 | AM48: =SUM(AH48:AL48) -> 0 | AY48: =873.6+162 -> 1035.6 | AZ48: =-S48 -> 0 | BB48: =AC48-AM48-AY48-AX48+SUM(AZ48:BA48) -> 12838 | BD48: =AC48-AM48-AX48-AY48+SUM(AZ48:BA48) -> 12838 | BL48: =SUM(BE48:BK48) -> 0 | BR48: =SUM(BN48:BQ48) -> 0 | BS48: =SUM(V48:AB48) -> 0 | BW48: =C48&I48 -> 老龙馄饨-灵工谢志毅 | BY48: 有 | CA48: =VLOOKUP(A48,hr.个税累计数据!C:C,1,0) -> #N/A | CB48: 老龙馄饨-灵工谢志毅 | CD48: =H48=I48 -> TRUE
A49: =C49&I49 -> 老龙馄饨-灵工钱玉连 | B49: 老龙馄饨 | C49: 老龙馄饨-灵工 | D49: 正常计税 | E49: 老龙馄饨 | F49: 蔡心宇 | G49: 保洁 | H49: 钱玉连 | I49: 钱玉连 | J49: 全日制 | K49: =AC49+BL49 -> 6830.08 | L49: =AC49-AM49-AX49-AY49+SUM(AZ49:BA49) -> 6396.4 | N49: 6 | O49: 6830.08 | Q49: =VLOOKUP(I49,考勤调整记录!I:W,15,0) -> 0 | U49: =SUM(O49:T49) -> 6830.08 | AC49: =SUM(O49:T49)+SUM(V49:AB49) -> 6830.08 | AE49: 202606 | AM49: =SUM(AH49:AL49) -> 0 | AY49: =430.08+3.6 -> 433.68 | AZ49: =-S49 -> 0 | BB49: =AC49-AM49-AY49-AX49+SUM(AZ49:BA49) -> 6396.4 | BD49: =AC49-AM49-AX49-AY49+SUM(AZ49:BA49) -> 6396.4 | BL49: =SUM(BE49:BK49) -> 0 | BR49: =SUM(BN49:BQ49) -> 0 | BS49: =SUM(V49:AB49) -> 0 | BW49: =C49&I49 -> 老龙馄饨-灵工钱玉连 | BY49: 有 | CA49: =VLOOKUP(A49,hr.个税累计数据!C:C,1,0) -> #N/A | CB49: 老龙馄饨-灵工钱玉连 | CD49: =H49=I49 -> TRUE
A50: =C50&I50 -> 老龙馄饨-灵工蔡明燕 | B50: 老龙馄饨 | C50: 老龙馄饨-灵工 | D50: 正常计税 | E50: 老龙馄饨 | F50: 蔡心宇 | G50: 保洁 | H50: 蔡明燕 | I50: 蔡明燕 | J50: 全日制 | K50: =AC50+BL50 -> 7363.68 | L50: =AC50-AM50-AX50-AY50+SUM(AZ50:BA50) -> 6884.4 | N50: 6 | O50: 7363.68 | Q50: =VLOOKUP(I50,考勤调整记录!I:W,15,0) -> 0 | U50: =SUM(O50:T50) -> 7363.68 | AC50: =SUM(O50:T50)+SUM(V50:AB50) -> 7363.68 | AE50: 202606 | AM50: =SUM(AH50:AL50) -> 0 | AY50: =463.68+15.6 -> 479.28 | AZ50: =-S50 -> 0 | BB50: =AC50-AM50-AY50-AX50+SUM(AZ50:BA50) -> 6884.4 | BD50: =AC50-AM50-AX50-AY50+SUM(AZ50:BA50) -> 6884.4 | BL50: =SUM(BE50:BK50) -> 0 | BR50: =SUM(BN50:BQ50) -> 0 | BS50: =SUM(V50:AB50) -> 0 | BW50: =C50&I50 -> 老龙馄饨-灵工蔡明燕 | BY50: 有 | CA50: =VLOOKUP(A50,hr.个税累计数据!C:C,1,0) -> #N/A | CB50: 老龙馄饨-灵工蔡明燕 | CD50: =H50=I50 -> TRUE
A51: =C51&I51 -> 开弈投资李蕾 | B51: F-大财务部 | C51: 开弈投资 | D51: 正常计税 | E51: 财务部 | F51: 芦智蔚 | G51: 会计 | H51: 李蕾 | I51: 李蕾 | J51: 全日制 | K51: =AC51+BL51 -> 12219.02 | L51: =AC51-AM51-AX51-AY51+SUM(AZ51:BA51) -> 8224.17 | N51: 6 | O51: 10000 | Q51: =VLOOKUP(I51,考勤调整记录!I:W,15,0) -> 0 | S51: 155.8 | U51: =SUM(O51:T51) -> 10155.8 | W51: =ROUND((O51)*(0.9629-1),2) -> -371 | AC51: =SUM(O51:T51)+SUM(V51:AB51) -> 9784.8 | AE51: 202606 | AF51: =VLOOKUP(BW51,'HR|社保明细'!C:F,4,0) -> 7460 | AG51: =VLOOKUP($BW51,'HR|社保明细'!$C:G,5,0) -> 7384 | AH51: =VLOOKUP($BW51,'HR|社保明细'!$C:H,6,0) -> 596.8 | AI51: =VLOOKUP($BW51,'HR|社保明细'!$C:I,7,0) -> 149.2 | AJ51: =VLOOKUP($BW51,'HR|社保明细'!$C:J,8,0) -> 37.3 | AK51: =VLOOKUP($BW51,'HR|社保明细'!$C:K,9,0) -> 517 | AL51: =VLOOKUP($BW51,'HR|社保明细'!$C:L,10,0) -> 0 | AM51: =SUM(AH51:AL51) -> 1300.3 | AS51: =AC51-AM51-SUM(AN51:AR51) -> 8484.5 | AU51: =VLOOKUP(BW51,hr.个税累计数据!C:DS,121,0) -> 57071.63 | AV51: =IF(AU51-5000*N51-VLOOKUP(A51,hr.个税累计数据!C:DT,122,0)-VLOOKUP(A51,hr.个税累计数据!C:DU,123,0)>0,AU51-5000*N51-VLOOKUP(A51,hr.个税累计数据!C:DT,122,0)-VLOOKUP(A51,hr.个税累计数据!C:DU,123,0),0) -> 19269.83 | AW51: =VLOOKUP(BW51,hr.个税累计数据!C:DV,124,0) -> 473.56 | AY51: =IF(ROUND(MAX(AV51*{0.03,0.1,0.2,0.25,0.3,0.35,0.45}-{0,210,1410,2660,4410,7160,15160}*12)-AW51,2)<=0,0,ROUND(MAX(AV51*{0.03,0.1,0.2,0.25,0.3,0.35,0.45}-{0,210,1410,2660,4410,7160,15160}*12)-AW51,2)) -> 104.53 | AZ51: =-S51 -> -155.8 | BB51: =AC51-AM51-AY51-AX51+SUM(AZ51:BA51) -> 8224.17 | BD51: =AC51-AM51-AX51-AY51+SUM(AZ51:BA51) -> 8224.17 | BE51: =VLOOKUP($BW51,'HR|社保明细'!C:T,11,0) -> 1193.6 | BF51: =VLOOKUP($BW51,'HR|社保明细'!$C:U,12,0) -> 596.8 | BG51: =VLOOKUP($BW51,'HR|社保明细'!$C:V,13,0) -> 37.3 | BH51: =VLOOKUP($BW51,'HR|社保明细'!$C:W,14,0) -> 14.92 | BI51: =VLOOKUP($BW51,'HR|社保明细'!$C:X,15,0) -> 74.6 | BJ51: =VLOOKUP($BW51,'HR|社保明细'!$C:Y,16,0) -> 517 | BK51: =VLOOKUP($BW51,'HR|社保明细'!$C:Z,17,0) -> 0 | BL51: =SUM(BE51:BK51) -> 2434.22 | BR51: =SUM(BN51:BQ51) -> 0 | BS51: =SUM(V51:AB51) -> -371 | BT51: 1250 | BW51: =C51&I51 -> 开弈投资李蕾 | BY51: 有 | BZ51: 后台 | CA51: =VLOOKUP(A51,hr.个税累计数据!C:C,1,0) -> 开弈投资李蕾 | CB51: 开弈投资李蕾 | CC51: 有 | CD51: =H51=I51 -> TRUE
A52: =C52&I52 -> 开弈投资林水桃 | B52: G-Jenny-家庭 | C52: 开弈投资 | D52: 正常计税 | E52: Jenny-家庭 | F52: 蔡心宇 | G52: 驾驶员 | H52: 林水桃 | I52: 林水桃 | J52: 全日制 | K52: =AC52+BL52 -> 4155.8 | L52: =AC52-AM52-AX52-AY52+SUM(AZ52:BA52) -> 4000 | N52: 6 | O52: 4000 | Q52: =VLOOKUP(I52,考勤调整记录!I:W,15,0) -> 0 | S52: 155.8 | U52: =SUM(O52:T52) -> 4155.8 | AC52: =SUM(O52:T52)+SUM(V52:AB52) -> 4155.8 | AE52: 202606 | AF52: =VLOOKUP(BW52,'HR|社保明细'!C:F,4,0) -> 0 | AG52: =VLOOKUP($BW52,'HR|社保明细'!$C:G,5,0) -> 0 | AH52: =VLOOKUP($BW52,'HR|社保明细'!$C:H,6,0) -> 0 | AI52: =VLOOKUP($BW52,'HR|社保明细'!$C:I,7,0) -> 0 | AJ52: =VLOOKUP($BW52,'HR|社保明细'!$C:J,8,0) -> 0 | AK52: =VLOOKUP($BW52,'HR|社保明细'!$C:K,9,0) -> 0 | AL52: =VLOOKUP($BW52,'HR|社保明细'!$C:L,10,0) -> 0 | AM52: =SUM(AH52:AL52) -> 0 | AS52: =AC52-AM52-SUM(AN52:AR52) -> 4155.8 | AU52: =VLOOKUP(BW52,hr.个税累计数据!C:DS,121,0) -> 24901.95 | AV52: =IF(AU52-5000*N52-VLOOKUP(A52,hr.个税累计数据!C:DT,122,0)-VLOOKUP(A52,hr.个税累计数据!C:DU,123,0)>0,AU52-5000*N52-VLOOKUP(A52,hr.个税累计数据!C:DT,122,0)-VLOOKUP(A52,hr.个税累计数据!C:DU,123,0),0) -> 0 | AW52: =VLOOKUP(BW52,hr.个税累计数据!C:DV,124,0) -> 0 | AY52: =IF(ROUND(MAX(AV52*{0.03,0.1,0.2,0.25,0.3,0.35,0.45}-{0,210,1410,2660,4410,7160,15160}*12)-AW52,2)<=0,0,ROUND(MAX(AV52*{0.03,0.1,0.2,0.25,0.3,0.35,0.45}-{0,210,1410,2660,4410,7160,15160}*12)-AW52,2)) -> 0 | AZ52: =-S52 -> -155.8 | BB52: =AC52-AM52-AY52-AX52+SUM(AZ52:BA52) -> 4000 | BD52: =AC52-AM52-AX52-AY52+SUM(AZ52:BA52) -> 4000 | BE52: =VLOOKUP($BW52,'HR|社保明细'!C:T,11,0) -> 0 | BF52: =VLOOKUP($BW52,'HR|社保明细'!$C:U,12,0) -> 0 | BG52: =VLOOKUP($BW52,'HR|社保明细'!$C:V,13,0) -> 0 | BH52: =VLOOKUP($BW52,'HR|社保明细'!$C:W,14,0) -> 0 | BI52: =VLOOKUP($BW52,'HR|社保明细'!$C:X,15,0) -> 0 | BJ52: =VLOOKUP($BW52,'HR|社保明细'!$C:Y,16,0) -> 0 | BK52: =VLOOKUP($BW52,'HR|社保明细'!$C:Z,17,0) -> 0 | BL52: =SUM(BE52:BK52) -> 0 | BR52: =SUM(BN52:BQ52) -> 0 | BS52: =SUM(V52:AB52) -> 0 | BT52: 1250 | BW52: =C52&I52 -> 开弈投资林水桃 | BX52: 无社公 | BY52: 有 | CA52: =VLOOKUP(A52,hr.个税累计数据!C:C,1,0) -> 开弈投资林水桃 | CB52: 开弈投资林水桃 | CC52: 有 | CD52: =H52=I52 -> TRUE
A53: =C53&I53 -> 开弈投资邵吴慧 | B53: 园区-商办&企业服务 | C53: 开弈投资 | D53: 正常计税 | E53: 办公&企业服务 | F53: 韩喆 | G53: 商办账务专员 | H53: 邵吴慧 | I53: 邵吴慧 | J53: 全日制 | K53: =AC53+BL53 -> 12650.89 | L53: =AC53-AM53-AX53-AY53+SUM(AZ53:BA53) -> 8643.08 | N53: 6 | O53: 11000 | Q53: =VLOOKUP(I53,考勤调整记录!I:W,15,0) -> -531.03 | S53: 155.8 | U53: =SUM(O53:T53) -> 10624.77 | W53: -408.1 | AC53: =SUM(O53:T53)+SUM(V53:AB53) -> 10216.67 | AE53: 202606 | AF53: =VLOOKUP(BW53,'HR|社保明细'!C:F,4,0) -> 7460 | AG53: =VLOOKUP($BW53,'HR|社保明细'!$C:G,5,0) -> 7384 | AH53: =VLOOKUP($BW53,'HR|社保明细'!$C:H,6,0) -> 596.8 | AI53: =VLOOKUP($BW53,'HR|社保明细'!$C:I,7,0) -> 149.2 | AJ53: =VLOOKUP($BW53,'HR|社保明细'!$C:J,8,0) -> 37.3 | AK53: =VLOOKUP($BW53,'HR|社保明细'!$C:K,9,0) -> 517 | AL53: =VLOOKUP($BW53,'HR|社保明细'!$C:L,10,0) -> 0 | AM53: =SUM(AH53:AL53) -> 1300.3 | AS53: =AC53-AM53-SUM(AN53:AR53) -> 8916.37 | AU53: =VLOOKUP(BW53,hr.个税累计数据!C:DS,121,0) -> 59374.47 | AV53: =IF(AU53-5000*N53-VLOOKUP(A53,hr.个税累计数据!C:DT,122,0)-VLOOKUP(A53,hr.个税累计数据!C:DU,123,0)>0,AU53-5000*N53-VLOOKUP(A53,hr.个税累计数据!C:DT,122,0)-VLOOKUP(A53,hr.个税累计数据!C:DU,123,0),0) -> 21572.67 | AW53: =VLOOKUP(BW53,hr.个税累计数据!C:DV,124,0) -> 529.69 | AY53: =IF(ROUND(MAX(AV53*{0.03,0.1,0.2,0.25,0.3,0.35,0.45}-{0,210,1410,2660,4410,7160,15160}*12)-AW53,2)<=0,0,ROUND(MAX(AV53*{0.03,0.1,0.2,0.25,0.3,0.35,0.45}-{0,210,1410,2660,4410,7160,15160}*12)-AW53,2)) -> 117.49 | AZ53: =-S53 -> -155.8 | BB53: =AC53-AM53-AY53-AX53+SUM(AZ53:BA53) -> 8643.08 | BD53: =AC53-AM53-AX53-AY53+SUM(AZ53:BA53) -> 8643.08 | BE53: =VLOOKUP($BW53,'HR|社保明细'!C:T,11,0) -> 1193.6 | BF53: =VLOOKUP($BW53,'HR|社保明细'!$C:U,12,0) -> 596.8 | BG53: =VLOOKUP($BW53,'HR|社保明细'!$C:V,13,0) -> 37.3 | BH53: =VLOOKUP($BW53,'HR|社保明细'!$C:W,14,0) -> 14.92 | BI53: =VLOOKUP($BW53,'HR|社保明细'!$C:X,15,0) -> 74.6 | BJ53: =VLOOKUP($BW53,'HR|社保明细'!$C:Y,16,0) -> 517 | BK53: =VLOOKUP($BW53,'HR|社保明细'!$C:Z,17,0) -> 0 | BL53: =SUM(BE53:BK53) -> 2434.22 | BR53: =SUM(BN53:BQ53) -> 0 | BS53: =SUM(V53:AB53) -> -408.1 | BT53: 1250 | BW53: =C53&I53 -> 开弈投资邵吴慧 | BY53: 有 | BZ53: 后台 | CA53: =VLOOKUP(A53,hr.个税累计数据!C:C,1,0) -> 开弈投资邵吴慧 | CB53: 开弈投资邵吴慧 | CC53: 有 | CD53: =H53=I53 -> TRUE
A54: =C54&I54 -> 开弈投资王建平 | B54: 物业保洁部 | C54: 开弈投资 | D54: 正常计税 | E54: 物业保洁部 | F54: 宣国英 | G54: 保洁 | H54: 王建平 | I54: 王建平 | J54: 全日制 | K54: =AC54+BL54 -> 9644.02 | L54: =AC54-AM54-AX54-AY54+SUM(AZ54:BA54) -> 5726.42 | N54: 6 | O54: 6754 | Q54: =VLOOKUP(I54,考勤调整记录!I:W,15,0) -> 0 | S54: 155.8 | U54: =SUM(O54:T54) -> 6909.8 | Y54: 300 | AC54: =SUM(O54:T54)+SUM(V54:AB54) -> 7209.8 | AE54: 202606 | AF54: =VLOOKUP(BW54,'HR|社保明细'!C:F,4,0) -> 7460 | AG54: =VLOOKUP($BW54,'HR|社保明细'!$C:G,5,0) -> 7384 | AH54: =VLOOKUP($BW54,'HR|社保明细'!$C:H,6,0) -> 596.8 | AI54: =VLOOKUP($BW54,'HR|社保明细'!$C:I,7,0) -> 149.2 | AJ54: =VLOOKUP($BW54,'HR|社保明细'!$C:J,8,0) -> 37.3 | AK54: =VLOOKUP($BW54,'HR|社保明细'!$C:K,9,0) -> 517 | AL54: =VLOOKUP($BW54,'HR|社保明细'!$C:L,10,0) -> 0 | AM54: =SUM(AH54:AL54) -> 1300.3 | AS54: =AC54-AM54-SUM(AN54:AR54) -> 5909.5 | AU54: =VLOOKUP(BW54,hr.个税累计数据!C:DS,121,0) -> 41725.95 | AV54: =IF(AU54-5000*N54-VLOOKUP(A54,hr.个税累计数据!C:DT,122,0)-VLOOKUP(A54,hr.个税累计数据!C:DU,123,0)>0,AU54-5000*N54-VLOOKUP(A54,hr.个税累计数据!C:DT,122,0)-VLOOKUP(A54,hr.个税累计数据!C:DU,123,0),0) -> 3924.15 | AW54: =VLOOKUP(BW54,hr.个税累计数据!C:DV,124,0) -> 90.44 | AY54: =IF(ROUND(MAX(AV54*{0.03,0.1,0.2,0.25,0.3,0.35,0.45}-{0,210,1410,2660,4410,7160,15160}*12)-AW54,2)<=0,0,ROUND(MAX(AV54*{0.03,0.1,0.2,0.25,0.3,0.35,0.45}-{0,210,1410,2660,4410,7160,15160}*12)-AW54,2)) -> 27.28 | AZ54: =-S54 -> -155.8 | BB54: =AC54-AM54-AY54-AX54+SUM(AZ54:BA54) -> 5726.42 | BD54: =AC54-AM54-AX54-AY54+SUM(AZ54:BA54) -> 5726.42 | BE54: =VLOOKUP($BW54,'HR|社保明细'!C:T,11,0) -> 1193.6 | BF54: =VLOOKUP($BW54,'HR|社保明细'!$C:U,12,0) -> 596.8 | BG54: =VLOOKUP($BW54,'HR|社保明细'!$C:V,13,0) -> 37.3 | BH54: =VLOOKUP($BW54,'HR|社保明细'!$C:W,14,0) -> 14.92 | BI54: =VLOOKUP($BW54,'HR|社保明细'!$C:X,15,0) -> 74.6 | BJ54: =VLOOKUP($BW54,'HR|社保明细'!$C:Y,16,0) -> 517 | BK54: =VLOOKUP($BW54,'HR|社保明细'!$C:Z,17,0) -> 0 | BL54: =SUM(BE54:BK54) -> 2434.22 | BR54: =SUM(BN54:BQ54) -> 0 | BS54: =SUM(V54:AB54) -> 300 | BT54: 1250 | BW54: =C54&I54 -> 开弈投资王建平 | BY54: 有 | CA54: =VLOOKUP(A54,hr.个税累计数据!C:C,1,0) -> 开弈投资王建平 | CB54: 开弈投资王建平 | CC54: 有 | CD54: =H54=I54 -> TRUE
A55: =C55&I55 -> 开弈投资王韬 | B55: 物业管理部 | C55: 开弈投资 | D55: 正常计税 | E55: 物业管理部 | F55: 汪顺 | G55: 物业管理 | H55: 王韬 | I55: 王韬 | J55: 全日制 | K55: =AC55+BL55 -> 21543.75 | L55: =AC55-AM55-AX55-AY55+SUM(AZ55:BA55) -> 16451.42 | N55: 6 | O55: 12600 | Q55: =VLOOKUP(I55,考勤调整记录!I:W,15,0) -> 0 | S55: 155.8 | U55: =SUM(O55:T55) -> 12755.8 | W55: 1171.95 | Z55: 5000 | AC55: =SUM(O55:T55)+SUM(V55:AB55) -> 18927.75 | AE55: 202606 | AF55: =VLOOKUP(BW55,'HR|社保明细'!C:F,4,0) -> 8000 | AG55: =VLOOKUP($BW55,'HR|社保明细'!$C:G,5,0) -> 8000 | AH55: =VLOOKUP($BW55,'HR|社保明细'!$C:H,6,0) -> 640 | AI55: =VLOOKUP($BW55,'HR|社保明细'!$C:I,7,0) -> 160 | AJ55: =VLOOKUP($BW55,'HR|社保明细'!$C:J,8,0) -> 40 | AK55: =VLOOKUP($BW55,'HR|社保明细'!$C:K,9,0) -> 560 | AL55: =VLOOKUP($BW55,'HR|社保明细'!$C:L,10,0) -> 0 | AM55: =SUM(AH55:AL55) -> 1400 | AN55: 1000 | AQ55: 3000 | AS55: =AC55-AM55-SUM(AN55:AR55) -> 13527.75 | AU55: =VLOOKUP(BW55,hr.个税累计数据!C:DS,121,0) -> 104467.05 | AV55: =IF(AU55-5000*N55-VLOOKUP(A55,hr.个税累计数据!C:DT,122,0)-VLOOKUP(A55,hr.个税累计数据!C:DU,123,0)>0,AU55-5000*N55-VLOOKUP(A55,hr.个税累计数据!C:DT,122,0)-VLOOKUP(A55,hr.个税累计数据!C:DU,123,0),0) -> 45067.05 | AW55: =VLOOKUP(BW55,hr.个税累计数据!C:DV,124,0) -> 1066.18 | AY55: {=IF(ROUND(MAX(AV55*{0.03,0.1,0.2,0.25,0.3,0.35,0.45}-{0,210,1410,2660,4410,7160,15160}*12)-AW55,2)<=0,0,ROUND(MAX(AV55*{0.03,0.1,0.2,0.25,0.3,0.35,0.45}-{0,210,1410,2660,4410,7160,15160}*12)-AW55,2))+0.01} -> 920.53 | AZ55: =-S55 -> -155.8 | BB55: =AC55-AM55-AY55-AX55+SUM(AZ55:BA55) -> 16451.42 | BD55: =AC55-AM55-AX55-AY55+SUM(AZ55:BA55) -> 16451.42 | BE55: =VLOOKUP($BW55,'HR|社保明细'!C:T,11,0) -> 1280 | BF55: =VLOOKUP($BW55,'HR|社保明细'!$C:U,12,0) -> 640 | BG55: =VLOOKUP($BW55,'HR|社保明细'!$C:V,13,0) -> 40 | BH55: =VLOOKUP($BW55,'HR|社保明细'!$C:W,14,0) -> 16 | BI55: =VLOOKUP($BW55,'HR|社保明细'!$C:X,15,0) -> 80 | BJ55: =VLOOKUP($BW55,'HR|社保明细'!$C:Y,16,0) -> 560 | BK55: =VLOOKUP($BW55,'HR|社保明细'!$C:Z,17,0) -> 0 | BL55: =SUM(BE55:BK55) -> 2616 | BR55: =SUM(BN55:BQ55) -> 0 | BS55: =SUM(V55:AB55) -> 6171.95 | BT55: 1250 | BW55: =C55&I55 -> 开弈投资王韬 | BY55: 有 | BZ55: 物业 | CA55: =VLOOKUP(A55,hr.个税累计数据!C:C,1,0) -> 开弈投资王韬 | CB55: 开弈投资王韬 | CC55: 有 | CD55: =H55=I55 -> TRUE
A56: =C56&I56 -> 开弈投资王永佳 | B56: F-大财务部 | C56: 开弈投资 | D56: 正常计税 | E56: 财务部 | F56: 蔡心宇 | G56: 会计 | H56: 王永佳 | I56: 王永佳 | J56: 全日制 | K56: =AC56+BL56 -> 12400.8 | L56: =AC56-AM56-AX56-AY56+SUM(AZ56:BA56) -> 8127.45 | N56: 6 | O56: 10000 | Q56: =VLOOKUP(I56,考勤调整记录!I:W,15,0) -> 0 | S56: 155.8 | U56: =SUM(O56:T56) -> 10155.8 | W56: =ROUND((O56)*(0.9629-1),2) -> -371 | AC56: =SUM(O56:T56)+SUM(V56:AB56) -> 9784.8 | AE56: 202606 | AF56: =VLOOKUP(BW56,'HR|社保明细'!C:F,4,0) -> 8000 | AG56: =VLOOKUP($BW56,'HR|社保明细'!$C:G,5,0) -> 8000 | AH56: =VLOOKUP($BW56,'HR|社保明细'!$C:H,6,0) -> 640 | AI56: =VLOOKUP($BW56,'HR|社保明细'!$C:I,7,0) -> 160 | AJ56: =VLOOKUP($BW56,'HR|社保明细'!$C:J,8,0) -> 40 | AK56: =VLOOKUP($BW56,'HR|社保明细'!$C:K,9,0) -> 560 | AL56: =VLOOKUP($BW56,'HR|社保明细'!$C:L,10,0) -> 0 | AM56: =SUM(AH56:AL56) -> 1400 | AS56: =AC56-AM56-SUM(AN56:AR56) -> 8384.8 | AU56: =VLOOKUP(BW56,hr.个税累计数据!C:DS,121,0) -> 59111.63 | AV56: =IF(AU56-5000*N56-VLOOKUP(A56,hr.个税累计数据!C:DT,122,0)-VLOOKUP(A56,hr.个税累计数据!C:DU,123,0)>0,AU56-5000*N56-VLOOKUP(A56,hr.个税累计数据!C:DT,122,0)-VLOOKUP(A56,hr.个税累计数据!C:DU,123,0),0) -> 20711.63 | AW56: =VLOOKUP(BW56,hr.个税累计数据!C:DV,124,0) -> 519.8 | AY56: =IF(ROUND(MAX(AV56*{0.03,0.1,0.2,0.25,0.3,0.35,0.45}-{0,210,1410,2660,4410,7160,15160}*12)-AW56,2)<=0,0,ROUND(MAX(AV56*{0.03,0.1,0.2,0.25,0.3,0.35,0.45}-{0,210,1410,2660,4410,7160,15160}*12)-AW56,2)) -> 101.55 | AZ56: =-S56 -> -155.8 | BB56: =AC56-AM56-AY56-AX56+SUM(AZ56:BA56) -> 8127.45 | BD56: =AC56-AM56-AX56-AY56+SUM(AZ56:BA56) -> 8127.45 | BE56: =VLOOKUP($BW56,'HR|社保明细'!C:T,11,0) -> 1280 | BF56: =VLOOKUP($BW56,'HR|社保明细'!$C:U,12,0) -> 640 | BG56: =VLOOKUP($BW56,'HR|社保明细'!$C:V,13,0) -> 40 | BH56: =VLOOKUP($BW56,'HR|社保明细'!$C:W,14,0) -> 16 | BI56: =VLOOKUP($BW56,'HR|社保明细'!$C:X,15,0) -> 80 | BJ56: =VLOOKUP($BW56,'HR|社保明细'!$C:Y,16,0) -> 560 | BK56: =VLOOKUP($BW56,'HR|社保明细'!$C:Z,17,0) -> 0 | BL56: =SUM(BE56:BK56) -> 2616 | BR56: =SUM(BN56:BQ56) -> 0 | BS56: =SUM(V56:AB56) -> -371 | BT56: 1250 | BW56: =C56&I56 -> 开弈投资王永佳 | BY56: 有 | BZ56: 后台 | CA56: =VLOOKUP(A56,hr.个税累计数据!C:C,1,0) -> 开弈投资王永佳 | CB56: 开弈投资王永佳 | CC56: 有 | CD56: =H56=I56 -> TRUE
A57: =C57&I57 -> 开弈投资杨美玲 | B57: C-大后台-行政 | C57: 开弈投资 | D57: 正常计税 | E57: 行政部 | F57: 宣国英 | G57: 保洁 | H57: 杨美玲 | I57: 杨美玲 | J57: 全日制 | K57: =AC57+BL57 -> 6279.25 | L57: =AC57-AM57-AX57-AY57+SUM(AZ57:BA57) -> 6106.8 | N57: 6 | O57: 4216.8 | Q57: =VLOOKUP(I57,考勤调整记录!I:W,15,0) -> 1890 | S57: 172.45 | U57: =SUM(O57:T57) -> 6279.25 | AC57: =SUM(O57:T57)+SUM(V57:AB57) -> 6279.25 | AE57: 202606 | AF57: =VLOOKUP(BW57,'HR|社保明细'!C:F,4,0) -> 0 | AG57: =VLOOKUP($BW57,'HR|社保明细'!$C:G,5,0) -> 0 | AH57: =VLOOKUP($BW57,'HR|社保明细'!$C:H,6,0) -> 0 | AI57: =VLOOKUP($BW57,'HR|社保明细'!$C:I,7,0) -> 0 | AJ57: =VLOOKUP($BW57,'HR|社保明细'!$C:J,8,0) -> 0 | AK57: =VLOOKUP($BW57,'HR|社保明细'!$C:K,9,0) -> 0 | AL57: =VLOOKUP($BW57,'HR|社保明细'!$C:L,10,0) -> 0 | AM57: =SUM(AH57:AL57) -> 0 | AS57: =AC57-AM57-SUM(AN57:AR57) -> 6279.25 | AU57: =VLOOKUP(BW57,hr.个税累计数据!C:DS,121,0) -> 37361.7 | AV57: =IF(AU57-5000*N57-VLOOKUP(A57,hr.个税累计数据!C:DT,122,0)-VLOOKUP(A57,hr.个税累计数据!C:DU,123,0)>0,AU57-5000*N57-VLOOKUP(A57,hr.个税累计数据!C:DT,122,0)-VLOOKUP(A57,hr.个税累计数据!C:DU,123,0),0) -> 0 | AW57: =VLOOKUP(BW57,hr.个税累计数据!C:DV,124,0) -> 0 | AY57: {=IF(ROUND(MAX(AV57*{0.03,0.1,0.2,0.25,0.3,0.35,0.45}-{0,210,1410,2660,4410,7160,15160}*12)-AW57,2)<=0,0,ROUND(MAX(AV57*{0.03,0.1,0.2,0.25,0.3,0.35,0.45}-{0,210,1410,2660,4410,7160,15160}*12)-AW57,2))} -> 0 | AZ57: =-S57 -> -172.45 | BB57: =AC57-AM57-AY57-AX57+SUM(AZ57:BA57) -> 6106.8 | BD57: =AC57-AM57-AX57-AY57+SUM(AZ57:BA57) -> 6106.8 | BE57: =VLOOKUP($BW57,'HR|社保明细'!C:T,11,0) -> 0 | BF57: =VLOOKUP($BW57,'HR|社保明细'!$C:U,12,0) -> 0 | BG57: =VLOOKUP($BW57,'HR|社保明细'!$C:V,13,0) -> 0 | BH57: =VLOOKUP($BW57,'HR|社保明细'!$C:W,14,0) -> 0 | BI57: =VLOOKUP($BW57,'HR|社保明细'!$C:X,15,0) -> 0 | BJ57: =VLOOKUP($BW57,'HR|社保明细'!$C:Y,16,0) -> 0 | BK57: =VLOOKUP($BW57,'HR|社保明细'!$C:Z,17,0) -> 0 | BL57: =SUM(BE57:BK57) -> 0 | BR57: =SUM(BN57:BQ57) -> 0 | BS57: =SUM(V57:AB57) -> 0 | BT57: 1250 | BW57: =C57&I57 -> 开弈投资杨美玲 | BX57: 无社公 | BY57: 有 | CA57: =VLOOKUP(A57,hr.个税累计数据!C:C,1,0) -> 开弈投资杨美玲 | CB57: 开弈投资杨美玲 | CC57: 有 | CD57: =H57=I57 -> TRUE
A58: =C58&I58 -> 开弈信息杜宪 | B58: 园区-商办&企业服务 | C58: 开弈信息 | D58: 正常计税 | E58: 办公&企业服务 | F58: 韩喆 | G58: 业务拓展经理 | H58: 杜宪 | I58: 杜宪 | J58: 全日制 | K58: =AC58+BL58 -> 31718.2 | L58: =AC58-AM58-AX58-AY58+SUM(AZ58:BA58) -> 20187.58 | N58: 6 | O58: 14000 | Q58: =VLOOKUP(I58,考勤调整记录!I:W,15,0) -> 0 | S58: 155.8 | T58: 11000 | U58: =SUM(O58:T58) -> 25155.8 | V58: 1152.4 | W58: -1575 | AC58: =SUM(O58:T58)+SUM(V58:AB58) -> 24733.2 | AE58: 202606 | AF58: =VLOOKUP(BW58,'HR|社保明细'!C:F,4,0) -> 25000 | AG58: =VLOOKUP($BW58,'HR|社保明细'!$C:G,5,0) -> 8000 | AH58: =VLOOKUP($BW58,'HR|社保明细'!$C:H,6,0) -> 2000 | AI58: =VLOOKUP($BW58,'HR|社保明细'!$C:I,7,0) -> 500 | AJ58: =VLOOKUP($BW58,'HR|社保明细'!$C:J,8,0) -> 125 | AK58: =VLOOKUP($BW58,'HR|社保明细'!$C:K,9,0) -> 560 | AL58: =VLOOKUP($BW58,'HR|社保明细'!$C:L,10,0) -> 0 | AM58: =SUM(AH58:AL58) -> 3185 | AS58: =AC58-AM58-SUM(AN58:AR58) -> 21548.2 | AU58: =VLOOKUP(BW58,hr.个税累计数据!C:DS,121,0) -> 153034.85 | AV58: =IF(AU58-5000*N58-VLOOKUP(A58,hr.个税累计数据!C:DT,122,0)-VLOOKUP(A58,hr.个税累计数据!C:DU,123,0)>0,AU58-5000*N58-VLOOKUP(A58,hr.个税累计数据!C:DT,122,0)-VLOOKUP(A58,hr.个税累计数据!C:DU,123,0),0) -> 88924.85 | AW58: =VLOOKUP(BW58,hr.个税累计数据!C:DV,124,0) -> 5167.67 | AY58: =IF(ROUND(MAX(AV58*{0.03,0.1,0.2,0.25,0.3,0.35,0.45}-{0,210,1410,2660,4410,7160,15160}*12)-AW58,2)<=0,0,ROUND(MAX(AV58*{0.03,0.1,0.2,0.25,0.3,0.35,0.45}-{0,210,1410,2660,4410,7160,15160}*12)-AW58,2)) -> 1204.82 | AZ58: =-S58 -> -155.8 | BB58: =AC58-AM58-AY58-AX58+SUM(AZ58:BA58) -> 20187.58 | BD58: =AC58-AM58-AX58-AY58+SUM(AZ58:BA58) -> 20187.58 | BE58: =VLOOKUP($BW58,'HR|社保明细'!C:T,11,0) -> 4000 | BF58: =VLOOKUP($BW58,'HR|社保明细'!$C:U,12,0) -> 2000 | BG58: =VLOOKUP($BW58,'HR|社保明细'!$C:V,13,0) -> 125 | BH58: =VLOOKUP($BW58,'HR|社保明细'!$C:W,14,0) -> 50 | BI58: =VLOOKUP($BW58,'HR|社保明细'!$C:X,15,0) -> 250 | BJ58: =VLOOKUP($BW58,'HR|社保明细'!$C:Y,16,0) -> 560 | BK58: =VLOOKUP($BW58,'HR|社保明细'!$C:Z,17,0) -> 0 | BL58: =SUM(BE58:BK58) -> 6985 | BR58: =SUM(BN58:BQ58) -> 0 | BS58: =SUM(V58:AB58) -> -422.6 | BT58: 1250 | BW58: =C58&I58 -> 开弈信息杜宪 | BY58: 有 | CA58: =VLOOKUP(A58,hr.个税累计数据!C:C,1,0) -> 开弈信息杜宪 | CB58: 开弈信息杜宪 | CC58: 有 | CD58: =H58=I58 -> TRUE
A59: =C59&I59 -> 开弈信息黄欢欢 | B59: F-账务部 | C59: 开弈信息 | D59: 正常计税 | E59: 账务部 | F59: 张毅 | G59: 账务经理 | H59: 黄欢欢 | I59: 黄欢欢 | J59: 全日制 | K59: =AC59+BL59 -> 31353.3 | L59: =AC59-AM59-AX59-AY59+SUM(AZ59:BA59) -> 19307.17 | N59: 6 | O59: 25000 | Q59: =VLOOKUP(I59,考勤调整记录!I:W,15,0) -> 0 | S59: 155.8 | U59: =SUM(O59:T59) -> 25155.8 | W59: =ROUND((O59)*(0.9629-1),2) -> -927.5 | AC59: =SUM(O59:T59)+SUM(V59:AB59) -> 24228.3 | AE59: 202606 | AF59: =VLOOKUP(BW59,'HR|社保明细'!C:F,4,0) -> 25000 | AG59: =VLOOKUP($BW59,'HR|社保明细'!$C:G,5,0) -> 10000 | AH59: =VLOOKUP($BW59,'HR|社保明细'!$C:H,6,0) -> 2000 | AI59: =VLOOKUP($BW59,'HR|社保明细'!$C:I,7,0) -> 500 | AJ59: =VLOOKUP($BW59,'HR|社保明细'!$C:J,8,0) -> 125 | AK59: =VLOOKUP($BW59,'HR|社保明细'!$C:K,9,0) -> 700 | AL59: =VLOOKUP($BW59,'HR|社保明细'!$C:L,10,0) -> 0 | AM59: =SUM(AH59:AL59) -> 3325 | AP59: 1500 | AS59: =AC59-AM59-SUM(AN59:AR59) -> 19403.3 | AU59: =VLOOKUP(BW59,hr.个税累计数据!C:DS,121,0) -> 135445.65 | AV59: =IF(AU59-5000*N59-VLOOKUP(A59,hr.个税累计数据!C:DT,122,0)-VLOOKUP(A59,hr.个税累计数据!C:DU,123,0)>0,AU59-5000*N59-VLOOKUP(A59,hr.个税累计数据!C:DT,122,0)-VLOOKUP(A59,hr.个税累计数据!C:DU,123,0),0) -> 76495.65 | AW59: =VLOOKUP(BW59,hr.个税累计数据!C:DV,124,0) -> 3689.24 | AY59: =IF(ROUND(MAX(AV59*{0.03,0.1,0.2,0.25,0.3,0.35,0.45}-{0,210,1410,2660,4410,7160,15160}*12)-AW59,2)<=0,0,ROUND(MAX(AV59*{0.03,0.1,0.2,0.25,0.3,0.35,0.45}-{0,210,1410,2660,4410,7160,15160}*12)-AW59,2)) -> 1440.33 | AZ59: =-S59 -> -155.8 | BB59: =AC59-AM59-AY59-AX59+SUM(AZ59:BA59) -> 19307.17 | BD59: =AC59-AM59-AX59-AY59+SUM(AZ59:BA59) -> 19307.17 | BE59: =VLOOKUP($BW59,'HR|社保明细'!C:T,11,0) -> 4000 | BF59: =VLOOKUP($BW59,'HR|社保明细'!$C:U,12,0) -> 2000 | BG59: =VLOOKUP($BW59,'HR|社保明细'!$C:V,13,0) -> 125 | BH59: =VLOOKUP($BW59,'HR|社保明细'!$C:W,14,0) -> 50 | BI59: =VLOOKUP($BW59,'HR|社保明细'!$C:X,15,0) -> 250 | BJ59: =VLOOKUP($BW59,'HR|社保明细'!$C:Y,16,0) -> 700 | BK59: =VLOOKUP($BW59,'HR|社保明细'!$C:Z,17,0) -> 0 | BL59: =SUM(BE59:BK59) -> 7125 | BR59: =SUM(BN59:BQ59) -> 0 | BS59: =SUM(V59:AB59) -> -927.5 | BT59: 1250 | BW59: =C59&I59 -> 开弈信息黄欢欢 | BY59: 有 | BZ59: 后台 | CA59: =VLOOKUP(A59,hr.个税累计数据!C:C,1,0) -> 开弈信息黄欢欢 | CB59: 开弈信息黄欢欢 | CC59: 有 | CD59: =H59=I59 -> TRUE
A60: =C60&I60 -> 开弈信息沈明明 | B60: F-账务部 | C60: 开弈信息 | D60: 正常计税 | E60: 账务部 | F60: 黄欢欢 | G60: 泰系统专员 | H60: 沈明明 | I60: 沈明明 | J60: 全日制 | K60: =AC60+BL60 -> 12090.02 | L60: =AC60-AM60-AX60-AY60+SUM(AZ60:BA60) -> 8144.03 | N60: 6 | O60: 9500 | Q60: =VLOOKUP(I60,考勤调整记录!I:W,15,0) -> 0 | S60: 155.8 | U60: =SUM(O60:T60) -> 9655.8 | AC60: =SUM(O60:T60)+SUM(V60:AB60) -> 9655.8 | AE60: 202606 | AF60: =VLOOKUP(BW60,'HR|社保明细'!C:F,4,0) -> 7460 | AG60: =VLOOKUP($BW60,'HR|社保明细'!$C:G,5,0) -> 7384 | AH60: =VLOOKUP($BW60,'HR|社保明细'!$C:H,6,0) -> 596.8 | AI60: =VLOOKUP($BW60,'HR|社保明细'!$C:I,7,0) -> 149.2 | AJ60: =VLOOKUP($BW60,'HR|社保明细'!$C:J,8,0) -> 37.3 | AK60: =VLOOKUP($BW60,'HR|社保明细'!$C:K,9,0) -> 517 | AL60: =VLOOKUP($BW60,'HR|社保明细'!$C:L,10,0) -> 0 | AM60: =SUM(AH60:AL60) -> 1300.3 | AP60: 1500 | AS60: =AC60-AM60-SUM(AN60:AR60) -> 6855.5 | AU60: =VLOOKUP(BW60,hr.个税累计数据!C:DS,121,0) -> 56459.01 | AV60: =IF(AU60-5000*N60-VLOOKUP(A60,hr.个税累计数据!C:DT,122,0)-VLOOKUP(A60,hr.个税累计数据!C:DU,123,0)>0,AU60-5000*N60-VLOOKUP(A60,hr.个税累计数据!C:DT,122,0)-VLOOKUP(A60,hr.个税累计数据!C:DU,123,0),0) -> 9657.21 | AW60: =VLOOKUP(BW60,hr.个税累计数据!C:DV,124,0) -> 234.05 | AY60: =IF(ROUND(MAX(AV60*{0.03,0.1,0.2,0.25,0.3,0.35,0.45}-{0,210,1410,2660,4410,7160,15160}*12)-AW60,2)<=0,0,ROUND(MAX(AV60*{0.03,0.1,0.2,0.25,0.3,0.35,0.45}-{0,210,1410,2660,4410,7160,15160}*12)-AW60,2)) -> 55.67 | AZ60: =-S60 -> -155.8 | BB60: =AC60-AM60-AY60-AX60+SUM(AZ60:BA60) -> 8144.03 | BD60: =AC60-AM60-AX60-AY60+SUM(AZ60:BA60) -> 8144.03 | BE60: =VLOOKUP($BW60,'HR|社保明细'!C:T,11,0) -> 1193.6 | BF60: =VLOOKUP($BW60,'HR|社保明细'!$C:U,12,0) -> 596.8 | BG60: =VLOOKUP($BW60,'HR|社保明细'!$C:V,13,0) -> 37.3 | BH60: =VLOOKUP($BW60,'HR|社保明细'!$C:W,14,0) -> 14.92 | BI60: =VLOOKUP($BW60,'HR|社保明细'!$C:X,15,0) -> 74.6 | BJ60: =VLOOKUP($BW60,'HR|社保明细'!$C:Y,16,0) -> 517 | BK60: =VLOOKUP($BW60,'HR|社保明细'!$C:Z,17,0) -> 0 | BL60: =SUM(BE60:BK60) -> 2434.22 | BR60: =SUM(BN60:BQ60) -> 0 | BS60: =SUM(V60:AB60) -> 0 | BT60: 1250 | BW60: =C60&I60 -> 开弈信息沈明明 | BY60: 有 | BZ60: 后台 | CA60: =VLOOKUP(A60,hr.个税累计数据!C:C,1,0) -> 开弈信息沈明明 | CB60: 开弈信息沈明明 | CC60: 有 | CD60: =H60=I60 -> TRUE
A61: =C61&I61 -> 开弈信息黄燕婷 | B61: C-大后台-人事 | C61: 开弈信息 | D61: 正常计税 | E61: 人事部 | F61: 王妤扬 | G61: 人事专员 | H61: 黄燕婷 | I61: 黄燕婷 | J61: 全日制 | K61: =AC61+BL61 -> 14979.67 | L61: =AC61-AM61-AX61-AY61+SUM(AZ61:BA61) -> 10892.3 | N61: 6 | O61: 8500 | Q61: =VLOOKUP(I61,考勤调整记录!I:W,15,0) -> 4200 | S61: 155.8 | U61: =SUM(O61:T61) -> 12855.8 | W61: -315.35 | AC61: =SUM(O61:T61)+SUM(V61:AB61) -> 12540.45 | AE61: 202606 | AF61: =VLOOKUP(BW61,'HR|社保明细'!C:F,4,0) -> 7460 | AG61: =VLOOKUP($BW61,'HR|社保明细'!$C:G,5,0) -> 7460 | AH61: =VLOOKUP($BW61,'HR|社保明细'!$C:H,6,0) -> 596.8 | AI61: =VLOOKUP($BW61,'HR|社保明细'!$C:I,7,0) -> 149.2 | AJ61: =VLOOKUP($BW61,'HR|社保明细'!$C:J,8,0) -> 37.3 | AK61: =VLOOKUP($BW61,'HR|社保明细'!$C:K,9,0) -> 522 | AL61: =VLOOKUP($BW61,'HR|社保明细'!$C:L,10,0) -> 0 | AM61: =SUM(AH61:AL61) -> 1305.3 | AS61: =AC61-AM61-SUM(AN61:AR61) -> 11235.15 | AU61: =VLOOKUP(BW61,hr.个税累计数据!C:DS,121,0) -> 50989.59 | AV61: =IF(AU61-5000*N61-VLOOKUP(A61,hr.个税累计数据!C:DT,122,0)-VLOOKUP(A61,hr.个税累计数据!C:DU,123,0)>0,AU61-5000*N61-VLOOKUP(A61,hr.个税累计数据!C:DT,122,0)-VLOOKUP(A61,hr.个税累计数据!C:DU,123,0),0) -> 13157.79 | AW61: =VLOOKUP(BW61,hr.个税累计数据!C:DV,124,0) -> 207.68 | AY61: =IF(ROUND(MAX(AV61*{0.03,0.1,0.2,0.25,0.3,0.35,0.45}-{0,210,1410,2660,4410,7160,15160}*12)-AW61,2)<=0,0,ROUND(MAX(AV61*{0.03,0.1,0.2,0.25,0.3,0.35,0.45}-{0,210,1410,2660,4410,7160,15160}*12)-AW61,2)) -> 187.05 | AZ61: =-S61 -> -155.8 | BB61: =AC61-AM61-AY61-AX61+SUM(AZ61:BA61) -> 10892.3 | BD61: =AC61-AM61-AX61-AY61+SUM(AZ61:BA61) -> 10892.3 | BE61: =VLOOKUP($BW61,'HR|社保明细'!C:T,11,0) -> 1193.6 | BF61: =VLOOKUP($BW61,'HR|社保明细'!$C:U,12,0) -> 596.8 | BG61: =VLOOKUP($BW61,'HR|社保明细'!$C:V,13,0) -> 37.3 | BH61: =VLOOKUP($BW61,'HR|社保明细'!$C:W,14,0) -> 14.92 | BI61: =VLOOKUP($BW61,'HR|社保明细'!$C:X,15,0) -> 74.6 | BJ61: =VLOOKUP($BW61,'HR|社保明细'!$C:Y,16,0) -> 522 | BK61: =VLOOKUP($BW61,'HR|社保明细'!$C:Z,17,0) -> 0 | BL61: =SUM(BE61:BK61) -> 2439.22 | BR61: =SUM(BN61:BQ61) -> 0 | BS61: =SUM(V61:AB61) -> -315.35 | BT61: 1250 | BW61: =C61&I61 -> 开弈信息黄燕婷 | BY61: 有 | BZ61: 后台 | CA61: =VLOOKUP(A61,hr.个税累计数据!C:C,1,0) -> 开弈信息黄燕婷 | CB61: 开弈信息黄燕婷 | CC61: 有 | CD61: =H61=I61 -> TRUE
A62: =C62&I62 -> 开弈信息王倩 | B62: 公司费用-待结算&法人&智名 | C62: 开弈信息 | D62: 劳务计税 | E62: 公司费用-法人 | F62: 张毅 | G62: 法人 | H62: 王倩 | I62: 王倩 | J62: 非全日制 | K62: =AC62+BL62 -> 1000 | L62: =AC62-AM62-AX62-AY62+SUM(AZ62:BA62) -> 960 | N62: 6 | O62: 1000 | U62: =SUM(O62:T62) -> 1000 | AC62: =SUM(O62:T62)+SUM(V62:AB62) -> 1000 | AE62: 202606 | AF62: =VLOOKUP(BW62,'HR|社保明细'!C:F,4,0) -> 0 | AG62: =VLOOKUP($BW62,'HR|社保明细'!$C:G,5,0) -> 0 | AH62: =VLOOKUP($BW62,'HR|社保明细'!$C:H,6,0) -> 0 | AI62: =VLOOKUP($BW62,'HR|社保明细'!$C:I,7,0) -> 0 | AJ62: =VLOOKUP($BW62,'HR|社保明细'!$C:J,8,0) -> 0 | AK62: =VLOOKUP($BW62,'HR|社保明细'!$C:K,9,0) -> 0 | AL62: =VLOOKUP($BW62,'HR|社保明细'!$C:L,10,0) -> 0 | AM62: =SUM(AH62:AL62) -> 0 | AS62: 1000 | AU62: =VLOOKUP(BW62,hr.个税累计数据!C:DS,121,0) -> 6000 | AV62: =IF(AU62-5000*N62-VLOOKUP(A62,hr.个税累计数据!C:DT,122,0)-VLOOKUP(A62,hr.个税累计数据!C:DU,123,0)>0,AU62-5000*N62-VLOOKUP(A62,hr.个税累计数据!C:DT,122,0)-VLOOKUP(A62,hr.个税累计数据!C:DU,123,0),0) -> 0 | AW62: =VLOOKUP(BW62,hr.个税累计数据!C:DV,124,0) -> 200 | AY62: =IF(D62="国内不计税",0,IF(D62="正常计税",ROUND(MAX(AS62*{0.03,0.1,0.2,0.25,0.3,0.35,0.45}-{0,210,1410,2660,4410,7160,15160},0),2),IF(D62="外籍人",ROUND(MAX(AS62*{0.03,0.1,0.2,0.25,0.3,0.35,0.45}-{0,210,1410,2660,4410,7160,15160},0),2),ROUND(MAX((AS62-IF(AS62<4000,800,AS62*0.2))*10%*{2,3,4}-1000*{0,2,7},0),2)))) -> 40 | AZ62: =-S62 -> 0 | BB62: =AC62-AM62-AY62-AX62+SUM(AZ62:BA62) -> 960 | BD62: =AC62-AM62-AX62-AY62+SUM(AZ62:BA62) -> 960 | BE62: =VLOOKUP($BW62,'HR|社保明细'!C:T,11,0) -> 0 | BF62: =VLOOKUP($BW62,'HR|社保明细'!$C:U,12,0) -> 0 | BG62: =VLOOKUP($BW62,'HR|社保明细'!$C:V,13,0) -> 0 | BH62: =VLOOKUP($BW62,'HR|社保明细'!$C:W,14,0) -> 0 | BI62: =VLOOKUP($BW62,'HR|社保明细'!$C:X,15,0) -> 0 | BJ62: =VLOOKUP($BW62,'HR|社保明细'!$C:Y,16,0) -> 0 | BK62: =VLOOKUP($BW62,'HR|社保明细'!$C:Z,17,0) -> 0 | BL62: =SUM(BE62:BK62) -> 0 | BR62: =SUM(BN62:BQ62) -> 0 | BS62: =SUM(V62:AB62) -> 0 | BW62: =C62&I62 -> 开弈信息王倩 | BX62: 无社公 | BY62: 无 | CA62: =VLOOKUP(A62,hr.个税累计数据!C:C,1,0) -> 开弈信息王倩 | CB62: 开弈信息王倩 | CD62: =H62=I62 -> TRUE
A63: =C63&I63 -> 人力资源研究院王妤扬 | B63: C-大后台-法务 | C63: 人力资源研究院 | D63: 正常计税 | E63: 法务部 | F63: 张毅 | G63: 法务经理 | H63: 王妤扬 | I63: 王妤扬 | J63: 全日制 | K63: =AC63+BL63 -> 3899.27 | L63: =AC63-AM63-AX63-AY63+SUM(AZ63:BA63) -> 0 | N63: 6 | O63: 12000 | Q63: =VLOOKUP(I63,考勤调整记录!I:W,15,0) -> 0 | R63: =-10280.9+764.4+1336.8-2074.8 -> -10254.5 | S63: 155.8 | U63: =SUM(O63:T63) -> 1901.3 | W63: =ROUND((O63)*(0.9629-1),2) -> -445.2 | AC63: =SUM(O63:T63)+SUM(V63:AB63) -> 1456.1 | AE63: 202606 | AF63: =VLOOKUP(BW63,'HR|社保明细'!C:F,4,0) -> 7460 | AG63: =VLOOKUP($BW63,'HR|社保明细'!$C:G,5,0) -> 7384 | AH63: =VLOOKUP($BW63,'HR|社保明细'!$C:H,6,0) -> 596.8 | AI63: =VLOOKUP($BW63,'HR|社保明细'!$C:I,7,0) -> 149.2 | AJ63: =VLOOKUP($BW63,'HR|社保明细'!$C:J,8,0) -> 37.3 | AK63: =VLOOKUP($BW63,'HR|社保明细'!$C:K,9,0) -> 517 | AL63: =VLOOKUP($BW63,'HR|社保明细'!$C:L,10,0) -> 0 | AM63: =SUM(AH63:AL63) -> 1300.3 | AS63: =AC63-AM63-SUM(AN63:AR63) -> 155.8 | AU63: =VLOOKUP(BW63,hr.个税累计数据!C:DS,121,0) -> 8858.83 | AV63: =IF(AU63-5000*N63-VLOOKUP(A63,hr.个税累计数据!C:DT,122,0)-VLOOKUP(A63,hr.个税累计数据!C:DU,123,0)>0,AU63-5000*N63-VLOOKUP(A63,hr.个税累计数据!C:DT,122,0)-VLOOKUP(A63,hr.个税累计数据!C:DU,123,0),0) -> 0 | AW63: =VLOOKUP(BW63,hr.个税累计数据!C:DV,124,0) -> 0 | AY63: =IF(ROUND(MAX(AV63*{0.03,0.1,0.2,0.25,0.3,0.35,0.45}-{0,210,1410,2660,4410,7160,15160}*12)-AW63,2)<=0,0,ROUND(MAX(AV63*{0.03,0.1,0.2,0.25,0.3,0.35,0.45}-{0,210,1410,2660,4410,7160,15160}*12)-AW63,2)) -> 0 | AZ63: =-S63 -> -155.8 | BB63: =AC63-AM63-AY63-AX63+SUM(AZ63:BA63) -> 0 | BD63: =AC63-AM63-AX63-AY63+SUM(AZ63:BA63) -> 0 | BE63: =VLOOKUP($BW63,'HR|社保明细'!C:T,11,0) -> 1193.6 | BF63: =VLOOKUP($BW63,'HR|社保明细'!$C:U,12,0) -> 596.8 | BG63: =VLOOKUP($BW63,'HR|社保明细'!$C:V,13,0) -> 37.3 | BH63: =VLOOKUP($BW63,'HR|社保明细'!$C:W,14,0) -> 23.87 | BI63: =VLOOKUP($BW63,'HR|社保明细'!$C:X,15,0) -> 74.6 | BJ63: =VLOOKUP($BW63,'HR|社保明细'!$C:Y,16,0) -> 517 | BK63: =VLOOKUP($BW63,'HR|社保明细'!$C:Z,17,0) -> 0 | BL63: =SUM(BE63:BK63) -> 2443.17 | BR63: =SUM(BN63:BQ63) -> 0 | BS63: =SUM(V63:AB63) -> -445.2 | BT63: 1250 | BW63: =C63&I63 -> 人力资源研究院王妤扬 | BY63: 有 | BZ63: 后台 | CA63: =VLOOKUP(A63,hr.个税累计数据!C:C,1,0) -> 人力资源研究院王妤扬 | CB63: 人力资源研究院王妤扬 | CC63: 有 | CD63: =H63=I63 -> TRUE
A64: =C64&I64 -> 开弈信息张毅 | B64: G-集团管理层 | C64: 开弈信息 | D64: 正常计税 | E64: 总裁办 | F64: 张毅 | G64: 执行董事&CEO | H64: 张毅 | I64: 张毅 | J64: 全日制 | K64: =AC64+BL64 -> 36908.76 | L64: =AC64-AM64-AX64-AY64+SUM(AZ64:BA64) -> 24463.13 | N64: 6 | O64: 30000 | S64: 368.76 | U64: =SUM(O64:T64) -> 30368.76 | AC64: =SUM(O64:T64)+SUM(V64:AB64) -> 30368.76 | AE64: 202606 | AF64: =VLOOKUP(BW64,'HR|社保明细'!C:F,4,0) -> 20000 | AG64: =VLOOKUP($BW64,'HR|社保明细'!$C:G,5,0) -> 20000 | AH64: =VLOOKUP($BW64,'HR|社保明细'!$C:H,6,0) -> 1600 | AI64: =VLOOKUP($BW64,'HR|社保明细'!$C:I,7,0) -> 400 | AJ64: =VLOOKUP($BW64,'HR|社保明细'!$C:J,8,0) -> 100 | AK64: =VLOOKUP($BW64,'HR|社保明细'!$C:K,9,0) -> 1400 | AL64: =VLOOKUP($BW64,'HR|社保明细'!$C:L,10,0) -> 0 | AM64: =SUM(AH64:AL64) -> 3500 | AQ64: 1500 | AS64: =AC64-AM64-SUM(AN64:AR64) -> 25368.76 | AU64: =VLOOKUP(BW64,hr.个税累计数据!C:DS,121,0) -> 182041.92 | AV64: =IF(AU64-5000*N64-VLOOKUP(A64,hr.个税累计数据!C:DT,122,0)-VLOOKUP(A64,hr.个税累计数据!C:DU,123,0)>0,AU64-5000*N64-VLOOKUP(A64,hr.个税累计数据!C:DT,122,0)-VLOOKUP(A64,hr.个税累计数据!C:DU,123,0),0) -> 122041.92 | AW64: =VLOOKUP(BW64,hr.个税累计数据!C:DV,124,0) -> 7647.32 | AY64: =IF(ROUND(MAX(AV64*{0.03,0.1,0.2,0.25,0.3,0.35,0.45}-{0,210,1410,2660,4410,7160,15160}*12)-AW64,2)<=0,0,ROUND(MAX(AV64*{0.03,0.1,0.2,0.25,0.3,0.35,0.45}-{0,210,1410,2660,4410,7160,15160}*12)-AW64,2)) -> 2036.87 | AZ64: =-S64 -> -368.76 | BB64: =AC64-AM64-AY64-AX64+SUM(AZ64:BA64) -> 24463.13 | BD64: =AC64-AM64-AX64-AY64+SUM(AZ64:BA64) -> 24463.13 | BE64: =VLOOKUP($BW64,'HR|社保明细'!C:T,11,0) -> 3200 | BF64: =VLOOKUP($BW64,'HR|社保明细'!$C:U,12,0) -> 1600 | BG64: =VLOOKUP($BW64,'HR|社保明细'!$C:V,13,0) -> 100 | BH64: =VLOOKUP($BW64,'HR|社保明细'!$C:W,14,0) -> 40 | BI64: =VLOOKUP($BW64,'HR|社保明细'!$C:X,15,0) -> 200 | BJ64: =VLOOKUP($BW64,'HR|社保明细'!$C:Y,16,0) -> 1400 | BK64: =VLOOKUP($BW64,'HR|社保明细'!$C:Z,17,0) -> 0 | BL64: =SUM(BE64:BK64) -> 6540 | BR64: =SUM(BN64:BQ64) -> 0 | BS64: =SUM(V64:AB64) -> 0 | BT64: 1250 | BW64: =C64&I64 -> 开弈信息张毅 | BY64: 有 | CA64: =VLOOKUP(A64,hr.个税累计数据!C:C,1,0) -> 开弈信息张毅 | CB64: 开弈信息张毅 | CC64: 有 | CD64: =H64=I64 -> TRUE
A65: =C65&I65 -> 开弈信息郑昌杰 | B65: Shaun-客服部 | C65: 开弈信息 | D65: 正常计税 | E65: 客服部（S） | F65: 杨漾 | G65: 客服专员 | H65: 郑昌杰 | I65: 郑昌杰 | J65: 全日制 | K65: =AC65+BL65 -> 10590.02 | L65: =AC65-AM65-AX65-AY65+SUM(AZ65:BA65) -> 6699.7 | N65: 6 | O65: 8000 | Q65: =VLOOKUP(I65,考勤调整记录!I:W,15,0) -> 0 | S65: 155.8 | U65: =SUM(O65:T65) -> 8155.8 | AC65: =SUM(O65:T65)+SUM(V65:AB65) -> 8155.8 | AE65: 202606 | AF65: =VLOOKUP(BW65,'HR|社保明细'!C:F,4,0) -> 7460 | AG65: =VLOOKUP($BW65,'HR|社保明细'!$C:G,5,0) -> 7384 | AH65: =VLOOKUP($BW65,'HR|社保明细'!$C:H,6,0) -> 596.8 | AI65: =VLOOKUP($BW65,'HR|社保明细'!$C:I,7,0) -> 149.2 | AJ65: =VLOOKUP($BW65,'HR|社保明细'!$C:J,8,0) -> 37.3 | AK65: =VLOOKUP($BW65,'HR|社保明细'!$C:K,9,0) -> 517 | AL65: =VLOOKUP($BW65,'HR|社保明细'!$C:L,10,0) -> 0 | AM65: =SUM(AH65:AL65) -> 1300.3 | AQ65: 3000 | AS65: =AC65-AM65-SUM(AN65:AR65) -> 3855.5 | AU65: =VLOOKUP(BW65,hr.个税累计数据!C:DS,121,0) -> 58051.93 | AV65: =IF(AU65-5000*N65-VLOOKUP(A65,hr.个税累计数据!C:DT,122,0)-VLOOKUP(A65,hr.个税累计数据!C:DU,123,0)>0,AU65-5000*N65-VLOOKUP(A65,hr.个税累计数据!C:DT,122,0)-VLOOKUP(A65,hr.个税累计数据!C:DU,123,0),0) -> 2250.13 | AW65: =VLOOKUP(BW65,hr.个税累计数据!C:DV,124,0) -> 101.84 | AY65: =IF(ROUND(MAX(AV65*{0.03,0.1,0.2,0.25,0.3,0.35,0.45}-{0,210,1410,2660,4410,7160,15160}*12)-AW65,2)<=0,0,ROUND(MAX(AV65*{0.03,0.1,0.2,0.25,0.3,0.35,0.45}-{0,210,1410,2660,4410,7160,15160}*12)-AW65,2)) -> 0 | AZ65: =-S65 -> -155.8 | BB65: =AC65-AM65-AY65-AX65+SUM(AZ65:BA65) -> 6699.7 | BD65: =AC65-AM65-AX65-AY65+SUM(AZ65:BA65) -> 6699.7 | BE65: =VLOOKUP($BW65,'HR|社保明细'!C:T,11,0) -> 1193.6 | BF65: =VLOOKUP($BW65,'HR|社保明细'!$C:U,12,0) -> 596.8 | BG65: =VLOOKUP($BW65,'HR|社保明细'!$C:V,13,0) -> 37.3 | BH65: =VLOOKUP($BW65,'HR|社保明细'!$C:W,14,0) -> 14.92 | BI65: =VLOOKUP($BW65,'HR|社保明细'!$C:X,15,0) -> 74.6 | BJ65: =VLOOKUP($BW65,'HR|社保明细'!$C:Y,16,0) -> 517 | BK65: =VLOOKUP($BW65,'HR|社保明细'!$C:Z,17,0) -> 0 | BL65: =SUM(BE65:BK65) -> 2434.22 | BR65: =SUM(BN65:BQ65) -> 0 | BS65: =SUM(V65:AB65) -> 0 | BT65: 1250 | BW65: =C65&I65 -> 开弈信息郑昌杰 | BY65: 有 | BZ65: 人才 | CA65: =VLOOKUP(A65,hr.个税累计数据!C:C,1,0) -> 开弈信息郑昌杰 | CB65: 开弈信息郑昌杰 | CC65: 有 | CD65: =H65=I65 -> TRUE
A66: =C66&I66 -> 开弈信息蔡心宇 | B66: F-大财务部 | C66: 开弈信息 | D66: 正常计税 | E66: 财务部 | F66: 张毅 | G66: 财务经理 | H66: 蔡心宇 | I66: 蔡心宇 | J66: 全日制 | K66: =AC66+BL66 -> 25953.8 | L66: =AC66-AM66-AX66-AY66+SUM(AZ66:BA66) -> 14666.62 | N66: 6 | O66: 20000 | Q66: =VLOOKUP(I66,考勤调整记录!I:W,15,0) -> 0 | S66: 155.8 | U66: =SUM(O66:T66) -> 20155.8 | W66: =ROUND((O66)*(0.9629-1),2) -> -742 | AC66: =SUM(O66:T66)+SUM(V66:AB66) -> 19413.8 | AE66: 202606 | AF66: =VLOOKUP(BW66,'HR|社保明细'!C:F,4,0) -> 20000 | AG66: =VLOOKUP($BW66,'HR|社保明细'!$C:G,5,0) -> 20000 | AH66: =VLOOKUP($BW66,'HR|社保明细'!$C:H,6,0) -> 1600 | AI66: =VLOOKUP($BW66,'HR|社保明细'!$C:I,7,0) -> 400 | AJ66: =VLOOKUP($BW66,'HR|社保明细'!$C:J,8,0) -> 100 | AK66: =VLOOKUP($BW66,'HR|社保明细'!$C:K,9,0) -> 1400 | AL66: =VLOOKUP($BW66,'HR|社保明细'!$C:L,10,0) -> 0 | AM66: =SUM(AH66:AL66) -> 3500 | AS66: =AC66-AM66-SUM(AN66:AR66) -> 15913.8 | AU66: =VLOOKUP(BW66,hr.个税累计数据!C:DS,121,0) -> 110711.95 | AV66: =IF(AU66-5000*N66-VLOOKUP(A66,hr.个税累计数据!C:DT,122,0)-VLOOKUP(A66,hr.个税累计数据!C:DU,123,0)>0,AU66-5000*N66-VLOOKUP(A66,hr.个税累计数据!C:DT,122,0)-VLOOKUP(A66,hr.个税累计数据!C:DU,123,0),0) -> 59711.95 | AW66: =VLOOKUP(BW66,hr.个税累计数据!C:DV,124,0) -> 2359.82 | AY66: =IF(ROUND(MAX(AV66*{0.03,0.1,0.2,0.25,0.3,0.35,0.45}-{0,210,1410,2660,4410,7160,15160}*12)-AW66,2)<=0,0,ROUND(MAX(AV66*{0.03,0.1,0.2,0.25,0.3,0.35,0.45}-{0,210,1410,2660,4410,7160,15160}*12)-AW66,2)) -> 1091.38 | AZ66: =-S66 -> -155.8 | BB66: =AC66-AM66-AY66-AX66+SUM(AZ66:BA66) -> 14666.62 | BD66: =AC66-AM66-AX66-AY66+SUM(AZ66:BA66) -> 14666.62 | BE66: =VLOOKUP($BW66,'HR|社保明细'!C:T,11,0) -> 3200 | BF66: =VLOOKUP($BW66,'HR|社保明细'!$C:U,12,0) -> 1600 | BG66: =VLOOKUP($BW66,'HR|社保明细'!$C:V,13,0) -> 100 | BH66: =VLOOKUP($BW66,'HR|社保明细'!$C:W,14,0) -> 40 | BI66: =VLOOKUP($BW66,'HR|社保明细'!$C:X,15,0) -> 200 | BJ66: =VLOOKUP($BW66,'HR|社保明细'!$C:Y,16,0) -> 1400 | BK66: =VLOOKUP($BW66,'HR|社保明细'!$C:Z,17,0) -> 0 | BL66: =SUM(BE66:BK66) -> 6540 | BR66: =SUM(BN66:BQ66) -> 0 | BS66: =SUM(V66:AB66) -> -742 | BT66: 1250 | BW66: =C66&I66 -> 开弈信息蔡心宇 | BY66: 有 | BZ66: 后台 | CA66: =VLOOKUP(A66,hr.个税累计数据!C:C,1,0) -> 开弈信息蔡心宇 | CB66: 开弈信息蔡心宇 | CC66: 有 | CD66: =H66=I66 -> TRUE
A67: =C67&I67 -> 开弈中国王妤扬 | B67: C-大后台-法务 | C67: 开弈中国 | D67: 国内不计税 | E67: 法务部 | F67: 张毅 | G67: 法务经理 | H67: 王妤扬 | I67: 王妤扬 | J67: 全日制 | K67: =AC67+BL67 -> 32606.05 | L67: =AC67-AM67-AX67-AY67+SUM(AZ67:BA67) -> 29606.05 | N67: 6 | O67: 20000 | Q67: =考勤调整记录!W6 -> 0 | R67: =-ROUND(R63*1.1554,2) -> 11848.05 | U67: =SUM(O67:T67) -> 31848.05 | W67: =ROUND((O67)*(0.9629-1),2) -> -742 | AC67: =SUM(O67:T67)+SUM(V67:AB67) -> 31106.05 | AE67: 202606 | AF67: =VLOOKUP(BW67,'HR|社保明细'!C:F,4,0) -> 0 | AG67: =VLOOKUP($BW67,'HR|社保明细'!$C:G,5,0) -> 0 | AH67: =VLOOKUP($BW67,'HR|社保明细'!$C:H,6,0) -> 0 | AI67: =VLOOKUP($BW67,'HR|社保明细'!$C:I,7,0) -> 0 | AJ67: =VLOOKUP($BW67,'HR|社保明细'!$C:J,8,0) -> 0 | AK67: 1500 | AL67: =VLOOKUP($BW67,'HR|社保明细'!$C:L,10,0) -> 0 | AM67: =SUM(AH67:AL67) -> 1500 | AS67: 0 | AU67: =VLOOKUP(BW67,hr.个税累计数据!C:DS,121,0) -> 199913.08 | AW67: =VLOOKUP(BW67,hr.个税累计数据!C:DV,124,0) -> 0 | AZ67: =-S67 -> 0 | BB67: =AC67-AM67-AY67-AX67+SUM(AZ67:BA67) -> 29606.05 | BD67: =AC67-AM67-AX67-AY67+SUM(AZ67:BA67) -> 29606.05 | BE67: =VLOOKUP($BW67,'HR|社保明细'!C:T,11,0) -> 0 | BF67: =VLOOKUP($BW67,'HR|社保明细'!$C:U,12,0) -> 0 | BG67: =VLOOKUP($BW67,'HR|社保明细'!$C:V,13,0) -> 0 | BH67: =VLOOKUP($BW67,'HR|社保明细'!$C:W,14,0) -> 0 | BI67: =VLOOKUP($BW67,'HR|社保明细'!$C:X,15,0) -> 0 | BJ67: 1500 | BK67: =VLOOKUP($BW67,'HR|社保明细'!$C:Z,17,0) -> 0 | BL67: =SUM(BE67:BK67) -> 1500 | BR67: =SUM(BN67:BQ67) -> 0 | BS67: =SUM(V67:AB67) -> -742 | BW67: =C67&I67 -> 开弈中国王妤扬 | BX67: 无社公 | BY67: 无 | BZ67: 后台 | CA67: =VLOOKUP(A67,hr.个税累计数据!C:C,1,0) -> 开弈中国王妤扬 | CB67: 开弈中国王妤扬 | CD67: =H67=I67 -> TRUE
A68: =C68&I68 -> 开弈中国李向榮 | B68: G-香港办 | C68: 开弈中国 | D68: 国内不计税 | E68: 香港办 | F68: 王妤扬 | G68: 行政专员 | H68: 李向榮 | I68: 李向榮 | J68: 全日制 | K68: =AC68+BL68 -> 13650 | L68: =AC68-AM68-AX68-AY68+SUM(AZ68:BA68) -> 12350 | N68: 6 | O68: 13000 | U68: =SUM(O68:T68) -> 13000 | AC68: =SUM(O68:T68)+SUM(V68:AB68) -> 13000 | AE68: 202606 | AG68: =O68 -> 13000 | AK68: =AG68*0.05 -> 650 | AM68: =SUM(AH68:AL68) -> 650 | AS68: 0 | AZ68: =-S68 -> 0 | BB68: =AC68-AM68-AY68-AX68+SUM(AZ68:BA68) -> 12350 | BD68: =AC68-AM68-AX68-AY68+SUM(AZ68:BA68) -> 12350 | BJ68: =AK68 -> 650 | BL68: =SUM(BE68:BK68) -> 650 | BR68: =SUM(BN68:BQ68) -> 0 | BS68: =SUM(V68:AB68) -> 0 | BW68: =C68&I68 -> 开弈中国李向榮 | BX68: 无社公 | BY68: 无 | CA68: =VLOOKUP(A68,hr.个税累计数据!C:C,1,0) -> #N/A | CB68: 开弈中国李向榮 | CD68: =H68=I68 -> TRUE
A69: =C69&I69 -> 开弈中国劉梓霖 | B69: G-香港办 | C69: 开弈中国 | D69: 国内不计税 | E69: 香港办 | F69: 王妤扬 | G69: 数据服务 | H69: 劉梓霖 | I69: 劉梓霖 | J69: 全日制 | K69: =AC69+BL69 -> 18900 | L69: =AC69-AM69-AX69-AY69+SUM(AZ69:BA69) -> 17100 | N69: 6 | O69: 18000 | U69: =SUM(O69:T69) -> 18000 | AC69: =SUM(O69:T69)+SUM(V69:AB69) -> 18000 | AE69: 202606 | AG69: =O69 -> 18000 | AK69: =AG69*0.05 -> 900 | AM69: =SUM(AH69:AL69) -> 900 | AS69: 0 | AZ69: =-S69 -> 0 | BB69: =AC69-AM69-AY69-AX69+SUM(AZ69:BA69) -> 17100 | BD69: =AC69-AM69-AX69-AY69+SUM(AZ69:BA69) -> 17100 | BJ69: =AK69 -> 900 | BL69: =SUM(BE69:BK69) -> 900 | BR69: =SUM(BN69:BQ69) -> 0 | BS69: =SUM(V69:AB69) -> 0 | BW69: =C69&I69 -> 开弈中国劉梓霖 | BX69: 无社公 | BY69: 无 | CA69: =VLOOKUP(A69,hr.个税累计数据!C:C,1,0) -> #N/A | CB69: 开弈中国劉梓霖 | CD69: =H69=I69 -> TRUE
A70: =C70&I70 -> 开弈中国賴淑賢 | B70: G-香港办 | C70: 开弈中国 | D70: 国内不计税 | E70: 香港办 | F70: Jenny | G70: 财务经理 | H70: 賴淑賢 | I70: 賴淑賢 | J70: 全日制 | K70: =AC70+BL70 -> 31500 | L70: =AC70-AM70-AX70-AY70+SUM(AZ70:BA70) -> 28500 | N70: 6 | O70: 30000 | Q70: =VLOOKUP(I70,考勤调整记录!I:W,15,0) -> 0 | U70: =SUM(O70:T70) -> 30000 | AC70: =SUM(O70:T70)+SUM(V70:AB70) -> 30000 | AE70: 202606 | AG70: =O70 -> 30000 | AK70: =AG70*0.05 -> 1500 | AM70: =SUM(AH70:AL70) -> 1500 | AS70: 0 | AZ70: =-S70 -> 0 | BB70: =AC70-AM70-AY70-AX70+SUM(AZ70:BA70) -> 28500 | BD70: =AC70-AM70-AX70-AY70+SUM(AZ70:BA70) -> 28500 | BJ70: =AK70 -> 1500 | BL70: =SUM(BE70:BK70) -> 1500 | BR70: =SUM(BN70:BQ70) -> 0 | BS70: =SUM(V70:AB70) -> 0 | BW70: =C70&I70 -> 开弈中国賴淑賢 | BX70: 无社公 | BY70: 无 | CA70: =VLOOKUP(A70,hr.个税累计数据!C:C,1,0) -> #N/A | CB70: 开弈中国賴淑賢 | CD70: =H70=I70 -> TRUE
A71: =C71&I71 -> 开弈中国张毅 | B71: G-集团管理层 | C71: 开弈中国 | D71: 国内不计税 | E71: 总裁办 | F71: 张毅 | G71: 执行董事&CEO | H71: 张毅 | I71: 张毅 | J71: 全日制 | K71: =AC71+BL71 -> 70000 | L71: =AC71-AM71-AX71-AY71+SUM(AZ71:BA71) -> 70000 | N71: 6 | O71: 70000 | U71: =SUM(O71:T71) -> 70000 | AC71: =SUM(O71:T71)+SUM(V71:AB71) -> 70000 | AE71: 202606 | AF71: =VLOOKUP(BW71,'HR|社保明细'!C:F,4,0) -> 0 | AG71: =VLOOKUP($BW71,'HR|社保明细'!$C:G,5,0) -> 0 | AH71: =VLOOKUP($BW71,'HR|社保明细'!$C:H,6,0) -> 0 | AI71: =VLOOKUP($BW71,'HR|社保明细'!$C:I,7,0) -> 0 | AJ71: =VLOOKUP($BW71,'HR|社保明细'!$C:J,8,0) -> 0 | AK71: =VLOOKUP($BW71,'HR|社保明细'!$C:K,9,0) -> 0 | AL71: =VLOOKUP($BW71,'HR|社保明细'!$C:L,10,0) -> 0 | AM71: =SUM(AH71:AL71) -> 0 | AS71: 0 | AU71: =VLOOKUP(BW71,hr.个税累计数据!C:DS,121,0) -> 420000 | AW71: =VLOOKUP(BW71,hr.个税累计数据!C:DV,124,0) -> 0 | AZ71: =-S71 -> 0 | BB71: =AC71-AM71-AY71-AX71+SUM(AZ71:BA71) -> 70000 | BD71: =AC71-AM71-AX71-AY71+SUM(AZ71:BA71) -> 70000 | BE71: =VLOOKUP($BW71,'HR|社保明细'!C:T,11,0) -> 0 | BF71: =VLOOKUP($BW71,'HR|社保明细'!$C:U,12,0) -> 0 | BG71: =VLOOKUP($BW71,'HR|社保明细'!$C:V,13,0) -> 0 | BH71: =VLOOKUP($BW71,'HR|社保明细'!$C:W,14,0) -> 0 | BI71: =VLOOKUP($BW71,'HR|社保明细'!$C:X,15,0) -> 0 | BJ71: =VLOOKUP($BW71,'HR|社保明细'!$C:Y,16,0) -> 0 | BK71: =VLOOKUP($BW71,'HR|社保明细'!$C:Z,17,0) -> 0 | BL71: =SUM(BE71:BK71) -> 0 | BR71: =SUM(BN71:BQ71) -> 0 | BS71: =SUM(V71:AB71) -> 0 | BW71: =C71&I71 -> 开弈中国张毅 | BX71: 无社公 | BY71: 无 | CA71: =VLOOKUP(A71,hr.个税累计数据!C:C,1,0) -> 开弈中国张毅 | CB71: 开弈中国张毅 | CD71: =H71=I71 -> TRUE
A72: =C72&I72 -> 靠普人力杜宪 | B72: 公司费用-待结算&法人&智名 | C72: 靠普人力 | D72: 劳务计税 | E72: 公司费用-法人 | F72: 张毅 | G72: 法人 | H72: 杜宪 | I72: 杜宪 | J72: 非全日制 | K72: =AC72+BL72 -> 1000 | L72: =AC72-AM72-AX72-AY72+SUM(AZ72:BA72) -> 960 | N72: 6 | O72: 1000 | U72: =SUM(O72:T72) -> 1000 | AC72: =SUM(O72:T72)+SUM(V72:AB72) -> 1000 | AE72: 202606 | AF72: =VLOOKUP(BW72,'HR|社保明细'!C:F,4,0) -> 0 | AG72: =VLOOKUP($BW72,'HR|社保明细'!$C:G,5,0) -> 0 | AH72: =VLOOKUP($BW72,'HR|社保明细'!$C:H,6,0) -> 0 | AI72: =VLOOKUP($BW72,'HR|社保明细'!$C:I,7,0) -> 0 | AJ72: =VLOOKUP($BW72,'HR|社保明细'!$C:J,8,0) -> 0 | AK72: =VLOOKUP($BW72,'HR|社保明细'!$C:K,9,0) -> 0 | AL72: =VLOOKUP($BW72,'HR|社保明细'!$C:L,10,0) -> 0 | AM72: =SUM(AH72:AL72) -> 0 | AS72: 1000 | AU72: =VLOOKUP(BW72,hr.个税累计数据!C:DS,121,0) -> 6000 | AV72: =IF(AU72-5000*N72-VLOOKUP(A72,hr.个税累计数据!C:DT,122,0)-VLOOKUP(A72,hr.个税累计数据!C:DU,123,0)>0,AU72-5000*N72-VLOOKUP(A72,hr.个税累计数据!C:DT,122,0)-VLOOKUP(A72,hr.个税累计数据!C:DU,123,0),0) -> 0 | AW72: =VLOOKUP(BW72,hr.个税累计数据!C:DV,124,0) -> 200 | AY72: =IF(D72="国内不计税",0,IF(D72="正常计税",ROUND(MAX(AS72*{0.03,0.1,0.2,0.25,0.3,0.35,0.45}-{0,210,1410,2660,4410,7160,15160},0),2),IF(D72="外籍人",ROUND(MAX(AS72*{0.03,0.1,0.2,0.25,0.3,0.35,0.45}-{0,210,1410,2660,4410,7160,15160},0),2),ROUND(MAX((AS72-IF(AS72<4000,800,AS72*0.2))*10%*{2,3,4}-1000*{0,2,7},0),2)))) -> 40 | AZ72: =-S72 -> 0 | BB72: =AC72-AM72-AY72-AX72+SUM(AZ72:BA72) -> 960 | BD72: =AC72-AM72-AX72-AY72+SUM(AZ72:BA72) -> 960 | BE72: =VLOOKUP($BW72,'HR|社保明细'!C:T,11,0) -> 0 | BF72: =VLOOKUP($BW72,'HR|社保明细'!$C:U,12,0) -> 0 | BG72: =VLOOKUP($BW72,'HR|社保明细'!$C:V,13,0) -> 0 | BH72: =VLOOKUP($BW72,'HR|社保明细'!$C:W,14,0) -> 0 | BI72: =VLOOKUP($BW72,'HR|社保明细'!$C:X,15,0) -> 0 | BJ72: =VLOOKUP($BW72,'HR|社保明细'!$C:Y,16,0) -> 0 | BK72: =VLOOKUP($BW72,'HR|社保明细'!$C:Z,17,0) -> 0 | BL72: =SUM(BE72:BK72) -> 0 | BR72: =SUM(BN72:BQ72) -> 0 | BS72: =SUM(V72:AB72) -> 0 | BW72: =C72&I72 -> 靠普人力杜宪 | BX72: 无社公 | BY72: 无 | CA72: =VLOOKUP(A72,hr.个税累计数据!C:C,1,0) -> 靠普人力杜宪 | CB72: 靠普人力杜宪 | CD72: =H72=I72 -> TRUE
A73: =C73&I73 -> 靠普人力季嘉莉 | B73: F-账务部 | C73: 靠普人力 | D73: 正常计税 | E73: 账务部 | F73: 黄欢欢 | G73: 账务专员 | H73: 季嘉莉 | I73: 季嘉莉 | J73: 全日制 | K73: =AC73+BL73 -> 15967.97 | L73: =AC73-AM73-AX73-AY73+SUM(AZ73:BA73) -> 11226.11 | N73: 6 | O73: 9000 | Q73: =VLOOKUP(I73,考勤调整记录!I:W,15,0) -> 0 | S73: 155.8 | T73: 4000 | U73: =SUM(O73:T73) -> 13155.8 | AC73: =SUM(O73:T73)+SUM(V73:AB73) -> 13155.8 | AE73: 202606 | AF73: =VLOOKUP(BW73,'HR|社保明细'!C:F,4,0) -> 7460 | AG73: =VLOOKUP($BW73,'HR|社保明细'!$C:G,5,0) -> 7384 | AH73: =VLOOKUP($BW73,'HR|社保明细'!$C:H,6,0) -> 596.8 | AI73: =VLOOKUP($BW73,'HR|社保明细'!$C:I,7,0) -> 149.2 | AJ73: =VLOOKUP($BW73,'HR|社保明细'!$C:J,8,0) -> 37.3 | AK73: =VLOOKUP($BW73,'HR|社保明细'!$C:K,9,0) -> 517 | AL73: =VLOOKUP($BW73,'HR|社保明细'!$C:L,10,0) -> 369 | AM73: =SUM(AH73:AL73) -> 1669.3 | AP73: 1500 | AQ73: 1500 | AS73: =AC73-AM73-SUM(AN73:AR73) -> 8486.5 | AU73: =VLOOKUP(BW73,hr.个税累计数据!C:DS,121,0) -> 77741.85 | AV73: =IF(AU73-5000*N73-VLOOKUP(A73,hr.个税累计数据!C:DT,122,0)-VLOOKUP(A73,hr.个税累计数据!C:DU,123,0)>0,AU73-5000*N73-VLOOKUP(A73,hr.个税累计数据!C:DT,122,0)-VLOOKUP(A73,hr.个税累计数据!C:DU,123,0),0) -> 19726.05 | AW73: =VLOOKUP(BW73,hr.个税累计数据!C:DV,124,0) -> 487.19 | AY73: =IF(ROUND(MAX(AV73*{0.03,0.1,0.2,0.25,0.3,0.35,0.45}-{0,210,1410,2660,4410,7160,15160}*12)-AW73,2)<=0,0,ROUND(MAX(AV73*{0.03,0.1,0.2,0.25,0.3,0.35,0.45}-{0,210,1410,2660,4410,7160,15160}*12)-AW73,2)) -> 104.59 | AZ73: =-S73 -> -155.8 | BB73: =AC73-AM73-AY73-AX73+SUM(AZ73:BA73) -> 11226.11 | BD73: =AC73-AM73-AX73-AY73+SUM(AZ73:BA73) -> 11226.11 | BE73: =VLOOKUP($BW73,'HR|社保明细'!C:T,11,0) -> 1193.6 | BF73: =VLOOKUP($BW73,'HR|社保明细'!$C:U,12,0) -> 596.8 | BG73: =VLOOKUP($BW73,'HR|社保明细'!$C:V,13,0) -> 37.3 | BH73: =VLOOKUP($BW73,'HR|社保明细'!$C:W,14,0) -> 23.87 | BI73: =VLOOKUP($BW73,'HR|社保明细'!$C:X,15,0) -> 74.6 | BJ73: =VLOOKUP($BW73,'HR|社保明细'!$C:Y,16,0) -> 517 | BK73: =VLOOKUP($BW73,'HR|社保明细'!$C:Z,17,0) -> 369 | BL73: =SUM(BE73:BK73) -> 2812.17 | BR73: =SUM(BN73:BQ73) -> 0 | BS73: =SUM(V73:AB73) -> 0 | BT73: 1250 | BW73: =C73&I73 -> 靠普人力季嘉莉 | BY73: 有 | BZ73: 后台 | CA73: =VLOOKUP(A73,hr.个税累计数据!C:C,1,0) -> 靠普人力季嘉莉 | CB73: 靠普人力季嘉莉 | CC73: 有 | CD73: =H73=I73 -> TRUE
A74: =C74&I74 -> 开弈人力资源张家喜 | B74: HRO服务-代收代付残疾人 | C74: 开弈人力资源 | D74: 正常计税 | E74: 客户残疾人 | F74: 葛豪平 | G74: 残疾人 | H74: 张家喜 | I74: 张家喜 | J74: 代收代付残疾人 | K74: =AC74+BL74 -> 5449.47 | L74: =AC74-AM74-AX74-AY74+SUM(AZ74:BA74) -> 2740 | N74: 6 | O74: =3457.55+15.54-7.77+50+23.94-15.96 -> 3523.3 | U74: =SUM(O74:T74) -> 3523.3 | AC74: =SUM(O74:T74)+SUM(V74:AB74) -> 3523.3 | AE74: 202606 | AF74: =VLOOKUP(BW74,'HR|社保明细'!C:F,4,0) -> 7460 | AG74: =VLOOKUP($BW74,'HR|社保明细'!$C:G,5,0) -> 0 | AH74: =VLOOKUP($BW74,'HR|社保明细'!$C:H,6,0) -> 596.8 | AI74: =VLOOKUP($BW74,'HR|社保明细'!$C:I,7,0) -> 149.2 | AJ74: =VLOOKUP($BW74,'HR|社保明细'!$C:J,8,0) -> 37.3 | AK74: =VLOOKUP($BW74,'HR|社保明细'!$C:K,9,0) -> 0 | AL74: =VLOOKUP($BW74,'HR|社保明细'!$C:L,10,0) -> 0 | AM74: =SUM(AH74:AL74) -> 783.3 | AS74: =AC74-AM74-SUM(AN74:AR74) -> 2740 | AU74: =VLOOKUP(BW74,hr.个税累计数据!C:DS,121,0) -> 21139.8 | AV74: =IF(AU74-5000*N74-VLOOKUP(A74,hr.个税累计数据!C:DT,122,0)-VLOOKUP(A74,hr.个税累计数据!C:DU,123,0)>0,AU74-5000*N74-VLOOKUP(A74,hr.个税累计数据!C:DT,122,0)-VLOOKUP(A74,hr.个税累计数据!C:DU,123,0),0) -> 0 | AW74: =VLOOKUP(BW74,hr.个税累计数据!C:DV,124,0) -> 0 | AY74: =IF(ROUND(MAX(AV74*{0.03,0.1,0.2,0.25,0.3,0.35,0.45}-{0,210,1410,2660,4410,7160,15160}*12)-AW74,2)<=0,0,ROUND(MAX(AV74*{0.03,0.1,0.2,0.25,0.3,0.35,0.45}-{0,210,1410,2660,4410,7160,15160}*12)-AW74,2)) -> 0 | AZ74: =-S74 -> 0 | BB74: =AC74-AM74-AY74-AX74+SUM(AZ74:BA74) -> 2740 | BD74: =AC74-AM74-AX74-AY74+SUM(AZ74:BA74) -> 2740 | BE74: =VLOOKUP($BW74,'HR|社保明细'!C:T,11,0) -> 1193.6 | BF74: =VLOOKUP($BW74,'HR|社保明细'!$C:U,12,0) -> 596.8 | BG74: =VLOOKUP($BW74,'HR|社保明细'!$C:V,13,0) -> 37.3 | BH74: =VLOOKUP($BW74,'HR|社保明细'!$C:W,14,0) -> 23.87 | BI74: =VLOOKUP($BW74,'HR|社保明细'!$C:X,15,0) -> 74.6 | BJ74: =VLOOKUP($BW74,'HR|社保明细'!$C:Y,16,0) -> 0 | BK74: =VLOOKUP($BW74,'HR|社保明细'!$C:Z,17,0) -> 0 | BL74: =SUM(BE74:BK74) -> 1926.17 | BR74: =SUM(BN74:BQ74) -> 0 | BS74: =SUM(V74:AB74) -> 0 | BW74: =C74&I74 -> 开弈人力资源张家喜 | BY74: 无 | CA74: =VLOOKUP(A74,hr.个税累计数据!C:C,1,0) -> 开弈人力资源张家喜 | CB74: 开弈人力资源张家喜 | CD74: =H74=I74 -> TRUE
A75: =C75&I75 -> 开弈人力资源杜宪 | B75: 公司费用-待结算&法人&智名 | C75: 开弈人力资源 | D75: 劳务计税 | E75: 公司费用-法人 | F75: 张毅 | G75: 法人 | H75: 杜宪 | I75: 杜宪 | J75: 非全日制 | K75: =AC75+BL75 -> 1000 | L75: =AC75-AM75-AX75-AY75+SUM(AZ75:BA75) -> 960 | N75: 6 | O75: 1000 | U75: =SUM(O75:T75) -> 1000 | AC75: =SUM(O75:T75)+SUM(V75:AB75) -> 1000 | AE75: 202606 | AF75: =VLOOKUP(BW75,'HR|社保明细'!C:F,4,0) -> 0 | AG75: =VLOOKUP($BW75,'HR|社保明细'!$C:G,5,0) -> 0 | AH75: =VLOOKUP($BW75,'HR|社保明细'!$C:H,6,0) -> 0 | AI75: =VLOOKUP($BW75,'HR|社保明细'!$C:I,7,0) -> 0 | AJ75: =VLOOKUP($BW75,'HR|社保明细'!$C:J,8,0) -> 0 | AK75: =VLOOKUP($BW75,'HR|社保明细'!$C:K,9,0) -> 0 | AL75: =VLOOKUP($BW75,'HR|社保明细'!$C:L,10,0) -> 0 | AM75: =SUM(AH75:AL75) -> 0 | AS75: 1000 | AU75: =VLOOKUP(BW75,hr.个税累计数据!C:DS,121,0) -> 6000 | AV75: =IF(AU75-5000*N75-VLOOKUP(A75,hr.个税累计数据!C:DT,122,0)-VLOOKUP(A75,hr.个税累计数据!C:DU,123,0)>0,AU75-5000*N75-VLOOKUP(A75,hr.个税累计数据!C:DT,122,0)-VLOOKUP(A75,hr.个税累计数据!C:DU,123,0),0) -> 0 | AW75: =VLOOKUP(BW75,hr.个税累计数据!C:DV,124,0) -> 200 | AY75: =IF(D75="国内不计税",0,IF(D75="正常计税",ROUND(MAX(AS75*{0.03,0.1,0.2,0.25,0.3,0.35,0.45}-{0,210,1410,2660,4410,7160,15160},0),2),IF(D75="外籍人",ROUND(MAX(AS75*{0.03,0.1,0.2,0.25,0.3,0.35,0.45}-{0,210,1410,2660,4410,7160,15160},0),2),ROUND(MAX((AS75-IF(AS75<4000,800,AS75*0.2))*10%*{2,3,4}-1000*{0,2,7},0),2)))) -> 40 | AZ75: =-S75 -> 0 | BB75: =AC75-AM75-AY75-AX75+SUM(AZ75:BA75) -> 960 | BD75: =AC75-AM75-AX75-AY75+SUM(AZ75:BA75) -> 960 | BE75: =VLOOKUP($BW75,'HR|社保明细'!C:T,11,0) -> 0 | BF75: =VLOOKUP($BW75,'HR|社保明细'!$C:U,12,0) -> 0 | BG75: =VLOOKUP($BW75,'HR|社保明细'!$C:V,13,0) -> 0 | BH75: =VLOOKUP($BW75,'HR|社保明细'!$C:W,14,0) -> 0 | BI75: =VLOOKUP($BW75,'HR|社保明细'!$C:X,15,0) -> 0 | BJ75: =VLOOKUP($BW75,'HR|社保明细'!$C:Y,16,0) -> 0 | BK75: =VLOOKUP($BW75,'HR|社保明细'!$C:Z,17,0) -> 0 | BL75: =SUM(BE75:BK75) -> 0 | BR75: =SUM(BN75:BQ75) -> 0 | BS75: =SUM(V75:AB75) -> 0 | BW75: =C75&I75 -> 开弈人力资源杜宪 | BX75: 无社公 | BY75: 无 | CA75: =VLOOKUP(A75,hr.个税累计数据!C:C,1,0) -> 开弈人力资源杜宪 | CB75: 开弈人力资源杜宪 | CD75: =H75=I75 -> TRUE
A76: =C76&I76 -> 深圳和弈王雷 | B76: Shaun-外地 | C76: 深圳和弈 | D76: 正常计税 | E76: 深圳事业部 | F76: 黄一萧 | G76: 客服专员 | H76: 王雷 | I76: 王雷 | J76: 全日制 | K76: =AC76+BL76 -> 7254.66 | L76: =AC76-AM76-AX76-AY76+SUM(AZ76:BA76) -> 4605.46 | N76: 6 | O76: 5400 | Q76: =VLOOKUP(I76,考勤调整记录!I:W,15,0) -> 0 | S76: 267.4 | U76: =SUM(O76:T76) -> 5667.4 | AC76: =SUM(O76:T76)+SUM(V76:AB76) -> 5667.4 | AE76: 202606 | AF76: =VLOOKUP(BW76,'HR|社保明细'!C:F,4,0) -> 5000 | AG76: =VLOOKUP($BW76,'HR|社保明细'!$C:G,5,0) -> 5000 | AH76: =VLOOKUP($BW76,'HR|社保明细'!$C:H,6,0) -> 400 | AI76: =VLOOKUP($BW76,'HR|社保明细'!$C:I,7,0) -> 134.54 | AJ76: =VLOOKUP($BW76,'HR|社保明细'!$C:J,8,0) -> 10 | AK76: =VLOOKUP($BW76,'HR|社保明细'!$C:K,9,0) -> 250 | AL76: =VLOOKUP($BW76,'HR|社保明细'!$C:L,10,0) -> 0 | AM76: =SUM(AH76:AL76) -> 794.54 | AS76: =AC76-AM76-SUM(AN76:AR76) -> 4872.86 | AU76: =VLOOKUP(BW76,hr.个税累计数据!C:DS,121,0) -> 33462.87 | AV76: =IF(AU76-5000*N76-VLOOKUP(A76,hr.个税累计数据!C:DT,122,0)-VLOOKUP(A76,hr.个税累计数据!C:DU,123,0)>0,AU76-5000*N76-VLOOKUP(A76,hr.个税累计数据!C:DT,122,0)-VLOOKUP(A76,hr.个税累计数据!C:DU,123,0),0) -> 0 | AW76: =VLOOKUP(BW76,hr.个税累计数据!C:DV,124,0) -> 0 | AY76: =IF(ROUND(MAX(AV76*{0.03,0.1,0.2,0.25,0.3,0.35,0.45}-{0,210,1410,2660,4410,7160,15160}*12)-AW76,2)<=0,0,ROUND(MAX(AV76*{0.03,0.1,0.2,0.25,0.3,0.35,0.45}-{0,210,1410,2660,4410,7160,15160}*12)-AW76,2)) -> 0 | AZ76: =-S76 -> -267.4 | BB76: =AC76-AM76-AY76-AX76+SUM(AZ76:BA76) -> 4605.46 | BD76: =AC76-AM76-AX76-AY76+SUM(AZ76:BA76) -> 4605.46 | BE76: =VLOOKUP($BW76,'HR|社保明细'!C:T,11,0) -> 850 | BF76: =VLOOKUP($BW76,'HR|社保明细'!$C:U,12,0) -> 403.62 | BG76: =VLOOKUP($BW76,'HR|社保明细'!$C:V,13,0) -> 40 | BH76: =VLOOKUP($BW76,'HR|社保明细'!$C:W,14,0) -> 10 | BI76: =VLOOKUP($BW76,'HR|社保明细'!$C:X,15,0) -> 33.64 | BJ76: =VLOOKUP($BW76,'HR|社保明细'!$C:Y,16,0) -> 250 | BK76: =VLOOKUP($BW76,'HR|社保明细'!$C:Z,17,0) -> 0 | BL76: =SUM(BE76:BK76) -> 1587.26 | BR76: =SUM(BN76:BQ76) -> 0 | BS76: =SUM(V76:AB76) -> 0 | BT76: 600 | BW76: =C76&I76 -> 深圳和弈王雷 | BY76: 有 | BZ76: 人才 | CA76: =VLOOKUP(A76,hr.个税累计数据!C:C,1,0) -> 深圳和弈王雷 | CB76: 深圳和弈王雷 | CC76: 有 | CD76: =H76=I76 -> TRUE
A77: =C77&I77 -> 深圳和弈王倩 | B77: 公司费用-待结算&法人&智名 | C77: 深圳和弈 | D77: 劳务计税 | E77: 公司费用-法人 | F77: 张毅 | G77: 法人 | H77: 王倩 | I77: 王倩 | J77: 非全日制 | K77: =AC77+BL77 -> 1000 | L77: =AC77-AM77-AX77-AY77+SUM(AZ77:BA77) -> 960 | N77: 6 | O77: 1000 | U77: =SUM(O77:T77) -> 1000 | AC77: =SUM(O77:T77)+SUM(V77:AB77) -> 1000 | AE77: 202606 | AF77: =VLOOKUP(BW77,'HR|社保明细'!C:F,4,0) -> 0 | AG77: =VLOOKUP($BW77,'HR|社保明细'!$C:G,5,0) -> 0 | AH77: =VLOOKUP($BW77,'HR|社保明细'!$C:H,6,0) -> 0 | AI77: =VLOOKUP($BW77,'HR|社保明细'!$C:I,7,0) -> 0 | AJ77: =VLOOKUP($BW77,'HR|社保明细'!$C:J,8,0) -> 0 | AK77: =VLOOKUP($BW77,'HR|社保明细'!$C:K,9,0) -> 0 | AL77: =VLOOKUP($BW77,'HR|社保明细'!$C:L,10,0) -> 0 | AM77: =SUM(AH77:AL77) -> 0 | AS77: 1000 | AU77: =VLOOKUP(BW77,hr.个税累计数据!C:DS,121,0) -> 6000 | AV77: =IF(AU77-5000*N77-VLOOKUP(A77,hr.个税累计数据!C:DT,122,0)-VLOOKUP(A77,hr.个税累计数据!C:DU,123,0)>0,AU77-5000*N77-VLOOKUP(A77,hr.个税累计数据!C:DT,122,0)-VLOOKUP(A77,hr.个税累计数据!C:DU,123,0),0) -> 0 | AW77: =VLOOKUP(BW77,hr.个税累计数据!C:DV,124,0) -> 200 | AY77: =IF(D77="国内不计税",0,IF(D77="正常计税",ROUND(MAX(AS77*{0.03,0.1,0.2,0.25,0.3,0.35,0.45}-{0,210,1410,2660,4410,7160,15160},0),2),IF(D77="外籍人",ROUND(MAX(AS77*{0.03,0.1,0.2,0.25,0.3,0.35,0.45}-{0,210,1410,2660,4410,7160,15160},0),2),ROUND(MAX((AS77-IF(AS77<4000,800,AS77*0.2))*10%*{2,3,4}-1000*{0,2,7},0),2)))) -> 40 | AZ77: =-S77 -> 0 | BB77: =AC77-AM77-AY77-AX77+SUM(AZ77:BA77) -> 960 | BD77: =AC77-AM77-AX77-AY77+SUM(AZ77:BA77) -> 960 | BE77: =VLOOKUP($BW77,'HR|社保明细'!C:T,11,0) -> 0 | BF77: =VLOOKUP($BW77,'HR|社保明细'!$C:U,12,0) -> 0 | BG77: =VLOOKUP($BW77,'HR|社保明细'!$C:V,13,0) -> 0 | BH77: =VLOOKUP($BW77,'HR|社保明细'!$C:W,14,0) -> 0 | BI77: =VLOOKUP($BW77,'HR|社保明细'!$C:X,15,0) -> 0 | BJ77: =VLOOKUP($BW77,'HR|社保明细'!$C:Y,16,0) -> 0 | BK77: =VLOOKUP($BW77,'HR|社保明细'!$C:Z,17,0) -> 0 | BL77: =SUM(BE77:BK77) -> 0 | BR77: =SUM(BN77:BQ77) -> 0 | BS77: =SUM(V77:AB77) -> 0 | BW77: =C77&I77 -> 深圳和弈王倩 | BX77: 无社公 | BY77: 无 | CA77: =VLOOKUP(A77,hr.个税累计数据!C:C,1,0) -> 深圳和弈王倩 | CB77: 深圳和弈王倩 | CD77: =H77=I77 -> TRUE
A78: =C78&I78 -> 弈工分信息安东生 | B78: 物业保安部 | C78: 弈工分信息 | D78: 正常计税 | E78: 物业保安部 | F78: 贾飞龙 | G78: 园区保安副队长 | H78: 安东生 | I78: 安东生 | J78: 全日制 | K78: =AC78+BL78 -> 14043.69 | L78: =AC78-AM78-AX78-AY78+SUM(AZ78:BA78) -> 10453.87 | N78: 6 | O78: 11400 | Q78: =VLOOKUP(I78,考勤调整记录!I:W,15,0) -> 0 | S78: 155.8 | U78: =SUM(O78:T78) -> 11555.8 | W78: -9.33 | Y78: 300 | AC78: =SUM(O78:T78)+SUM(V78:AB78) -> 11846.47 | AE78: 202606 | AF78: =VLOOKUP(BW78,'HR|社保明细'!C:F,4,0) -> 7460 | AG78: =VLOOKUP($BW78,'HR|社保明细'!$C:G,5,0) -> 4000 | AH78: =VLOOKUP($BW78,'HR|社保明细'!$C:H,6,0) -> 596.8 | AI78: =VLOOKUP($BW78,'HR|社保明细'!$C:I,7,0) -> 149.2 | AJ78: =VLOOKUP($BW78,'HR|社保明细'!$C:J,8,0) -> 37.3 | AK78: =VLOOKUP($BW78,'HR|社保明细'!$C:K,9,0) -> 280 | AL78: =VLOOKUP($BW78,'HR|社保明细'!$C:L,10,0) -> 0 | AM78: =SUM(AH78:AL78) -> 1063.3 | AS78: =AC78-AM78-SUM(AN78:AR78) -> 10783.17 | AU78: =VLOOKUP(BW78,hr.个税累计数据!C:DS,121,0) -> 67793.64 | AV78: =IF(AU78-5000*N78-VLOOKUP(A78,hr.个税累计数据!C:DT,122,0)-VLOOKUP(A78,hr.个税累计数据!C:DU,123,0)>0,AU78-5000*N78-VLOOKUP(A78,hr.个税累计数据!C:DT,122,0)-VLOOKUP(A78,hr.个税累计数据!C:DU,123,0),0) -> 31413.84 | AW78: =VLOOKUP(BW78,hr.个税累计数据!C:DV,124,0) -> 768.92 | AY78: =IF(ROUND(MAX(AV78*{0.03,0.1,0.2,0.25,0.3,0.35,0.45}-{0,210,1410,2660,4410,7160,15160}*12)-AW78,2)<=0,0,ROUND(MAX(AV78*{0.03,0.1,0.2,0.25,0.3,0.35,0.45}-{0,210,1410,2660,4410,7160,15160}*12)-AW78,2)) -> 173.5 | AZ78: =-S78 -> -155.8 | BB78: =AC78-AM78-AY78-AX78+SUM(AZ78:BA78) -> 10453.87 | BD78: =AC78-AM78-AX78-AY78+SUM(AZ78:BA78) -> 10453.87 | BE78: =VLOOKUP($BW78,'HR|社保明细'!C:T,11,0) -> 1193.6 | BF78: =VLOOKUP($BW78,'HR|社保明细'!$C:U,12,0) -> 596.8 | BG78: =VLOOKUP($BW78,'HR|社保明细'!$C:V,13,0) -> 37.3 | BH78: =VLOOKUP($BW78,'HR|社保明细'!$C:W,14,0) -> 14.92 | BI78: =VLOOKUP($BW78,'HR|社保明细'!$C:X,15,0) -> 74.6 | BJ78: =VLOOKUP($BW78,'HR|社保明细'!$C:Y,16,0) -> 280 | BK78: =VLOOKUP($BW78,'HR|社保明细'!$C:Z,17,0) -> 0 | BL78: =SUM(BE78:BK78) -> 2197.22 | BR78: =SUM(BN78:BQ78) -> 0 | BS78: =SUM(V78:AB78) -> 290.67 | BT78: 1250 | BW78: =C78&I78 -> 弈工分信息安东生 | BY78: 有 | BZ78: 物业 | CA78: =VLOOKUP(A78,hr.个税累计数据!C:C,1,0) -> 弈工分信息安东生 | CB78: 弈工分信息安东生 | CC78: 有 | CD78: =H78=I78 -> TRUE
A79: =C79&I79 -> 时代人才常虹 | B79: G-时代人才 | C79: 时代人才 | D79: 正常计税 | E79: 时代人才 | F79: 蒋孝峰 | G79: 顾问 | H79: 常虹 | I79: 常虹 | J79: 全日制 | K79: =AC79+BL79 -> 21666.67 | L79: =AC79-AM79-AX79-AY79+SUM(AZ79:BA79) -> 20000 | N79: 6 | O79: =21272.16+394.51 -> 21666.67 | Q79: =VLOOKUP(I79,考勤调整记录!I:W,15,0) -> 0 | U79: =SUM(O79:T79) -> 21666.67 | AC79: =SUM(O79:T79)+SUM(V79:AB79) -> 21666.67 | AE79: 202606 | AF79: =VLOOKUP(BW79,'HR|社保明细'!C:F,4,0) -> 0 | AG79: =VLOOKUP($BW79,'HR|社保明细'!$C:G,5,0) -> 0 | AH79: =VLOOKUP($BW79,'HR|社保明细'!$C:H,6,0) -> 0 | AI79: =VLOOKUP($BW79,'HR|社保明细'!$C:I,7,0) -> 0 | AJ79: =VLOOKUP($BW79,'HR|社保明细'!$C:J,8,0) -> 0 | AK79: =VLOOKUP($BW79,'HR|社保明细'!$C:K,9,0) -> 0 | AL79: =VLOOKUP($BW79,'HR|社保明细'!$C:L,10,0) -> 0 | AM79: =SUM(AH79:AL79) -> 0 | AS79: =AC79-AM79-SUM(AN79:AR79) -> 21666.67 | AU79: =VLOOKUP(BW79,hr.个税累计数据!C:DS,121,0) -> 127200 | AV79: =IF(AU79-5000*N79-VLOOKUP(A79,hr.个税累计数据!C:DT,122,0)-VLOOKUP(A79,hr.个税累计数据!C:DU,123,0)>0,AU79-5000*N79-VLOOKUP(A79,hr.个税累计数据!C:DT,122,0)-VLOOKUP(A79,hr.个税累计数据!C:DU,123,0),0) -> 97200 | AW79: =VLOOKUP(BW79,hr.个税累计数据!C:DV,124,0) -> 5533.33 | AY79: =IF(ROUND(MAX(AV79*{0.03,0.1,0.2,0.25,0.3,0.35,0.45}-{0,210,1410,2660,4410,7160,15160}*12)-AW79,2)<=0,0,ROUND(MAX(AV79*{0.03,0.1,0.2,0.25,0.3,0.35,0.45}-{0,210,1410,2660,4410,7160,15160}*12)-AW79,2)) -> 1666.67 | AZ79: =-S79 -> 0 | BB79: =AC79-AM79-AY79-AX79+SUM(AZ79:BA79) -> 20000 | BD79: =AC79-AM79-AX79-AY79+SUM(AZ79:BA79) -> 20000 | BE79: =VLOOKUP($BW79,'HR|社保明细'!C:T,11,0) -> 0 | BF79: =VLOOKUP($BW79,'HR|社保明细'!$C:U,12,0) -> 0 | BG79: =VLOOKUP($BW79,'HR|社保明细'!$C:V,13,0) -> 0 | BH79: =VLOOKUP($BW79,'HR|社保明细'!$C:W,14,0) -> 0 | BI79: =VLOOKUP($BW79,'HR|社保明细'!$C:X,15,0) -> 0 | BJ79: =VLOOKUP($BW79,'HR|社保明细'!$C:Y,16,0) -> 0 | BK79: =VLOOKUP($BW79,'HR|社保明细'!$C:Z,17,0) -> 0 | BL79: =SUM(BE79:BK79) -> 0 | BR79: =SUM(BN79:BQ79) -> 0 | BS79: =SUM(V79:AB79) -> 0 | BW79: =C79&I79 -> 时代人才常虹 | BX79: 无社公 | BY79: 无 | CA79: =VLOOKUP(A79,hr.个税累计数据!C:C,1,0) -> 时代人才常虹 | CB79: 时代人才常虹 | CD79: =H79=I79 -> TRUE
A80: =C80&I80 -> 时代人才蒋孝峰 | B80: G-时代人才 | C80: 时代人才 | D80: 正常计税 | E80: 时代人才 | F80: 蔡心宇 | G80: 业务经理 | H80: 蒋孝峰 | I80: 蒋孝峰 | J80: 全日制 | K80: =AC80+BL80 -> 13939.02 | L80: =AC80-AM80-AX80-AY80+SUM(AZ80:BA80) -> 10348.71 | N80: 6 | O80: 11500 | Q80: =VLOOKUP(I80,考勤调整记录!I:W,15,0) -> 0 | R80: 30 | S80: 155.8 | U80: =SUM(O80:T80) -> 11685.8 | AC80: =SUM(O80:T80)+SUM(V80:AB80) -> 11685.8 | AE80: 202606 | AF80: =VLOOKUP(BW80,'HR|社保明细'!C:F,4,0) -> 7460 | AG80: =VLOOKUP($BW80,'HR|社保明细'!$C:G,5,0) -> 4800 | AH80: =VLOOKUP($BW80,'HR|社保明细'!$C:H,6,0) -> 596.8 | AI80: =VLOOKUP($BW80,'HR|社保明细'!$C:I,7,0) -> 149.2 | AJ80: =VLOOKUP($BW80,'HR|社保明细'!$C:J,8,0) -> 37.3 | AK80: =VLOOKUP($BW80,'HR|社保明细'!$C:K,9,0) -> 336 | AL80: =VLOOKUP($BW80,'HR|社保明细'!$C:L,10,0) -> 0 | AM80: =SUM(AH80:AL80) -> 1119.3 | AS80: =AC80-AM80-SUM(AN80:AR80) -> 10566.5 | AU80: =VLOOKUP(BW80,hr.个税累计数据!C:DS,121,0) -> 70081.95 | AV80: =IF(AU80-5000*N80-VLOOKUP(A80,hr.个税累计数据!C:DT,122,0)-VLOOKUP(A80,hr.个税累计数据!C:DU,123,0)>0,AU80-5000*N80-VLOOKUP(A80,hr.个税累计数据!C:DT,122,0)-VLOOKUP(A80,hr.个税累计数据!C:DU,123,0),0) -> 12366.15 | AW80: =VLOOKUP(BW80,hr.个税累计数据!C:DV,124,0) -> 308.99 | AY80: =IF(ROUND(MAX(AV80*{0.03,0.1,0.2,0.25,0.3,0.35,0.45}-{0,210,1410,2660,4410,7160,15160}*12)-AW80,2)<=0,0,ROUND(MAX(AV80*{0.03,0.1,0.2,0.25,0.3,0.35,0.45}-{0,210,1410,2660,4410,7160,15160}*12)-AW80,2)) -> 61.99 | AZ80: =-S80 -> -155.8 | BB80: =AC80-AM80-AY80-AX80+SUM(AZ80:BA80) -> 10348.71 | BD80: =AC80-AM80-AX80-AY80+SUM(AZ80:BA80) -> 10348.71 | BE80: =VLOOKUP($BW80,'HR|社保明细'!C:T,11,0) -> 1193.6 | BF80: =VLOOKUP($BW80,'HR|社保明细'!$C:U,12,0) -> 596.8 | BG80: =VLOOKUP($BW80,'HR|社保明细'!$C:V,13,0) -> 37.3 | BH80: =VLOOKUP($BW80,'HR|社保明细'!$C:W,14,0) -> 14.92 | BI80: =VLOOKUP($BW80,'HR|社保明细'!$C:X,15,0) -> 74.6 | BJ80: =VLOOKUP($BW80,'HR|社保明细'!$C:Y,16,0) -> 336 | BK80: =VLOOKUP($BW80,'HR|社保明细'!$C:Z,17,0) -> 0 | BL80: =SUM(BE80:BK80) -> 2253.22 | BR80: =SUM(BN80:BQ80) -> 0 | BS80: =SUM(V80:AB80) -> 0 | BT80: 1250 | BW80: =C80&I80 -> 时代人才蒋孝峰 | BY80: 有 | CA80: =VLOOKUP(A80,hr.个税累计数据!C:C,1,0) -> 时代人才蒋孝峰 | CB80: 时代人才蒋孝峰 | CC80: 有 | CD80: =H80=I80 -> TRUE
A81: =C81&I81 -> 天津英才陈一卓 | B81: Shaun-外地 | C81: 天津英才 | D81: 正常计税 | E81: 天津事业部 | F81: 郭双红 | G81: 客服专员 | H81: 陈一卓 | I81: 陈一卓 | J81: 全日制 | K81: =AC81+BL81 -> 14812.23 | L81: =AC81-AM81-AX81-AY81+SUM(AZ81:BA81) -> 10868.12 | N81: 6 | O81: =5500+2500 -> 8000 | Q81: =VLOOKUP(I81,考勤调整记录!I:W,15,0) -> 0 | S81: 155.8 | T81: 4352 | U81: =SUM(O81:T81) -> 12507.8 | Y81: 250.7 | AC81: =SUM(O81:T81)+SUM(V81:AB81) -> 12758.5 | AE81: 202606 | AF81: =VLOOKUP(BW81,'HR|社保明细'!C:F,4,0) -> 5124 | AG81: =VLOOKUP($BW81,'HR|社保明细'!$C:G,5,0) -> 6000 | AH81: =VLOOKUP($BW81,'HR|社保明细'!$C:H,6,0) -> 409.92 | AI81: =VLOOKUP($BW81,'HR|社保明细'!$C:I,7,0) -> 124.48 | AJ81: =VLOOKUP($BW81,'HR|社保明细'!$C:J,8,0) -> 25.62 | AK81: =VLOOKUP($BW81,'HR|社保明细'!$C:K,9,0) -> 660 | AL81: =VLOOKUP($BW81,'HR|社保明细'!$C:L,10,0) -> 0 | AM81: =SUM(AH81:AL81) -> 1220.02 | AS81: =AC81-AM81-SUM(AN81:AR81) -> 11538.48 | AU81: =VLOOKUP(BW81,hr.个税累计数据!C:DS,121,0) -> 77768.05 | AV81: =IF(AU81-5000*N81-VLOOKUP(A81,hr.个税累计数据!C:DT,122,0)-VLOOKUP(A81,hr.个税累计数据!C:DU,123,0)>0,AU81-5000*N81-VLOOKUP(A81,hr.个税累计数据!C:DT,122,0)-VLOOKUP(A81,hr.个税累计数据!C:DU,123,0),0) -> 40548.58 | AW81: =VLOOKUP(BW81,hr.个税累计数据!C:DV,124,0) -> 1020.3 | AY81: =IF(ROUND(MAX(AV81*{0.03,0.1,0.2,0.25,0.3,0.35,0.45}-{0,210,1410,2660,4410,7160,15160}*12)-AW81,2)<=0,0,ROUND(MAX(AV81*{0.03,0.1,0.2,0.25,0.3,0.35,0.45}-{0,210,1410,2660,4410,7160,15160}*12)-AW81,2)) -> 514.56 | AZ81: =-S81 -> -155.8 | BB81: =AC81-AM81-AY81-AX81+SUM(AZ81:BA81) -> 10868.12 | BD81: =AC81-AM81-AX81-AY81+SUM(AZ81:BA81) -> 10868.12 | BE81: =VLOOKUP($BW81,'HR|社保明细'!C:T,11,0) -> 819.84 | BF81: =VLOOKUP($BW81,'HR|社保明细'!$C:U,12,0) -> 512.4 | BG81: =VLOOKUP($BW81,'HR|社保明细'!$C:V,13,0) -> 25.62 | BH81: =VLOOKUP($BW81,'HR|社保明细'!$C:W,14,0) -> 10.25 | BI81: =VLOOKUP($BW81,'HR|社保明细'!$C:X,15,0) -> 25.62 | BJ81: =VLOOKUP($BW81,'HR|社保明细'!$C:Y,16,0) -> 660 | BK81: =VLOOKUP($BW81,'HR|社保明细'!$C:Z,17,0) -> 0 | BL81: =SUM(BE81:BK81) -> 2053.73 | BR81: =SUM(BN81:BQ81) -> 0 | BS81: =SUM(V81:AB81) -> 250.7 | BT81: 600 | BW81: =C81&I81 -> 天津英才陈一卓 | BY81: 有 | BZ81: 人才 | CA81: =VLOOKUP(A81,hr.个税累计数据!C:C,1,0) -> 天津英才陈一卓 | CB81: 天津英才陈一卓 | CC81: 有 | CD81: =H81=I81 -> TRUE
A82: =C82&I82 -> 天津英才郭双红 | B82: Shaun-外地 | C82: 天津英才 | D82: 正常计税 | E82: 天津事业部 | F82: 黄一萧 | G82: 客服主管 | H82: 郭双红 | I82: 郭双红 | J82: 全日制 | K82: =AC82+BL82 -> 10706.5 | L82: =AC82-AM82-AX82-AY82+SUM(AZ82:BA82) -> 10379.5 | N82: 6 | O82: 10000 | Q82: =VLOOKUP(I82,考勤调整记录!I:W,15,0) -> 0 | S82: 155.8 | T82: 300 | U82: =SUM(O82:T82) -> 10455.8 | Y82: 250.7 | AC82: =SUM(O82:T82)+SUM(V82:AB82) -> 10706.5 | AE82: 202606 | AF82: =VLOOKUP(BW82,'HR|社保明细'!C:F,4,0) -> 0 | AG82: =VLOOKUP($BW82,'HR|社保明细'!$C:G,5,0) -> 0 | AH82: =VLOOKUP($BW82,'HR|社保明细'!$C:H,6,0) -> 0 | AI82: =VLOOKUP($BW82,'HR|社保明细'!$C:I,7,0) -> 0 | AJ82: =VLOOKUP($BW82,'HR|社保明细'!$C:J,8,0) -> 0 | AK82: =VLOOKUP($BW82,'HR|社保明细'!$C:K,9,0) -> 0 | AL82: =VLOOKUP($BW82,'HR|社保明细'!$C:L,10,0) -> 0 | AM82: =SUM(AH82:AL82) -> 0 | AS82: =AC82-AM82-SUM(AN82:AR82) -> 10706.5 | AU82: =VLOOKUP(BW82,hr.个税累计数据!C:DS,121,0) -> 65802.65 | AV82: =IF(AU82-5000*N82-VLOOKUP(A82,hr.个税累计数据!C:DT,122,0)-VLOOKUP(A82,hr.个税累计数据!C:DU,123,0)>0,AU82-5000*N82-VLOOKUP(A82,hr.个税累计数据!C:DT,122,0)-VLOOKUP(A82,hr.个税累计数据!C:DU,123,0),0) -> 35802.65 | AW82: =VLOOKUP(BW82,hr.个税累计数据!C:DV,124,0) -> 902.88 | AY82: =IF(ROUND(MAX(AV82*{0.03,0.1,0.2,0.25,0.3,0.35,0.45}-{0,210,1410,2660,4410,7160,15160}*12)-AW82,2)<=0,0,ROUND(MAX(AV82*{0.03,0.1,0.2,0.25,0.3,0.35,0.45}-{0,210,1410,2660,4410,7160,15160}*12)-AW82,2)) -> 171.2 | AZ82: =-S82 -> -155.8 | BB82: =AC82-AM82-AY82-AX82+SUM(AZ82:BA82) -> 10379.5 | BD82: =AC82-AM82-AX82-AY82+SUM(AZ82:BA82) -> 10379.5 | BE82: =VLOOKUP($BW82,'HR|社保明细'!C:T,11,0) -> 0 | BF82: =VLOOKUP($BW82,'HR|社保明细'!$C:U,12,0) -> 0 | BG82: =VLOOKUP($BW82,'HR|社保明细'!$C:V,13,0) -> 0 | BH82: =VLOOKUP($BW82,'HR|社保明细'!$C:W,14,0) -> 0 | BI82: =VLOOKUP($BW82,'HR|社保明细'!$C:X,15,0) -> 0 | BJ82: =VLOOKUP($BW82,'HR|社保明细'!$C:Y,16,0) -> 0 | BK82: =VLOOKUP($BW82,'HR|社保明细'!$C:Z,17,0) -> 0 | BL82: =SUM(BE82:BK82) -> 0 | BR82: =SUM(BN82:BQ82) -> 0 | BS82: =SUM(V82:AB82) -> 250.7 | BT82: 600 | BW82: =C82&I82 -> 天津英才郭双红 | BX82: 无社公 | BY82: 有 | BZ82: 人才 | CA82: =VLOOKUP(A82,hr.个税累计数据!C:C,1,0) -> 天津英才郭双红 | CB82: 天津英才郭双红 | CC82: 有 | CD82: =H82=I82 -> TRUE
A83: =C83&I83 -> 天津英才王倩 | B83: 公司费用-待结算&法人&智名 | C83: 天津英才 | D83: 劳务计税 | E83: 公司费用-法人 | F83: 张毅 | G83: 法人 | H83: 王倩 | I83: 王倩 | J83: 非全日制 | K83: =AC83+BL83 -> 1000 | L83: =AC83-AM83-AX83-AY83+SUM(AZ83:BA83) -> 960 | N83: 6 | O83: 1000 | U83: =SUM(O83:T83) -> 1000 | AC83: =SUM(O83:T83)+SUM(V83:AB83) -> 1000 | AE83: 202606 | AF83: =VLOOKUP(BW83,'HR|社保明细'!C:F,4,0) -> 0 | AG83: =VLOOKUP($BW83,'HR|社保明细'!$C:G,5,0) -> 0 | AH83: =VLOOKUP($BW83,'HR|社保明细'!$C:H,6,0) -> 0 | AI83: =VLOOKUP($BW83,'HR|社保明细'!$C:I,7,0) -> 0 | AJ83: =VLOOKUP($BW83,'HR|社保明细'!$C:J,8,0) -> 0 | AK83: =VLOOKUP($BW83,'HR|社保明细'!$C:K,9,0) -> 0 | AL83: =VLOOKUP($BW83,'HR|社保明细'!$C:L,10,0) -> 0 | AM83: =SUM(AH83:AL83) -> 0 | AS83: 1000 | AU83: =VLOOKUP(BW83,hr.个税累计数据!C:DS,121,0) -> 6000 | AV83: =IF(AU83-5000*N83-VLOOKUP(A83,hr.个税累计数据!C:DT,122,0)-VLOOKUP(A83,hr.个税累计数据!C:DU,123,0)>0,AU83-5000*N83-VLOOKUP(A83,hr.个税累计数据!C:DT,122,0)-VLOOKUP(A83,hr.个税累计数据!C:DU,123,0),0) -> 0 | AW83: =VLOOKUP(BW83,hr.个税累计数据!C:DV,124,0) -> 200 | AY83: =IF(D83="国内不计税",0,IF(D83="正常计税",ROUND(MAX(AS83*{0.03,0.1,0.2,0.25,0.3,0.35,0.45}-{0,210,1410,2660,4410,7160,15160},0),2),IF(D83="外籍人",ROUND(MAX(AS83*{0.03,0.1,0.2,0.25,0.3,0.35,0.45}-{0,210,1410,2660,4410,7160,15160},0),2),ROUND(MAX((AS83-IF(AS83<4000,800,AS83*0.2))*10%*{2,3,4}-1000*{0,2,7},0),2)))) -> 40 | AZ83: =-S83 -> 0 | BB83: =AC83-AM83-AY83-AX83+SUM(AZ83:BA83) -> 960 | BD83: =AC83-AM83-AX83-AY83+SUM(AZ83:BA83) -> 960 | BE83: =VLOOKUP($BW83,'HR|社保明细'!C:T,11,0) -> 0 | BF83: =VLOOKUP($BW83,'HR|社保明细'!$C:U,12,0) -> 0 | BG83: =VLOOKUP($BW83,'HR|社保明细'!$C:V,13,0) -> 0 | BH83: =VLOOKUP($BW83,'HR|社保明细'!$C:W,14,0) -> 0 | BI83: =VLOOKUP($BW83,'HR|社保明细'!$C:X,15,0) -> 0 | BJ83: =VLOOKUP($BW83,'HR|社保明细'!$C:Y,16,0) -> 0 | BK83: =VLOOKUP($BW83,'HR|社保明细'!$C:Z,17,0) -> 0 | BL83: =SUM(BE83:BK83) -> 0 | BR83: =SUM(BN83:BQ83) -> 0 | BS83: =SUM(V83:AB83) -> 0 | BW83: =C83&I83 -> 天津英才王倩 | BX83: 无社公 | BY83: 无 | CA83: =VLOOKUP(A83,hr.个税累计数据!C:C,1,0) -> 天津英才王倩 | CB83: 天津英才王倩 | CD83: =H83=I83 -> TRUE
A84: =C84&I84 -> 天津英才吴靖娴 | B84: Shaun-外地 | C84: 天津英才 | D84: 正常计税 | E84: 天津事业部 | F84: 郭双红 | G84: 客服专员 | H84: 吴靖娴 | I84: 吴靖娴 | J84: 全日制 | K84: =AC84+BL84 -> 7351.23 | L84: =AC84-AM84-AX84-AY84+SUM(AZ84:BA84) -> 4139.68 | N84: 6 | O84: 5000 | Q84: =VLOOKUP(I84,考勤调整记录!I:W,15,0) -> 0 | S84: 155.8 | U84: =SUM(O84:T84) -> 5155.8 | Y84: 250.7 | AC84: =SUM(O84:T84)+SUM(V84:AB84) -> 5406.5 | AE84: 202606 | AF84: =VLOOKUP(BW84,'HR|社保明细'!C:F,4,0) -> 5124 | AG84: =VLOOKUP($BW84,'HR|社保明细'!$C:G,5,0) -> 5013 | AH84: =VLOOKUP($BW84,'HR|社保明细'!$C:H,6,0) -> 409.92 | AI84: =VLOOKUP($BW84,'HR|社保明细'!$C:I,7,0) -> 124.48 | AJ84: =VLOOKUP($BW84,'HR|社保明细'!$C:J,8,0) -> 25.62 | AK84: =VLOOKUP($BW84,'HR|社保明细'!$C:K,9,0) -> 551 | AL84: =VLOOKUP($BW84,'HR|社保明细'!$C:L,10,0) -> 0 | AM84: =SUM(AH84:AL84) -> 1111.02 | AS84: =AC84-AM84-SUM(AN84:AR84) -> 4295.48 | AU84: =VLOOKUP(BW84,hr.个税累计数据!C:DS,121,0) -> 30741.65 | AV84: =IF(AU84-5000*N84-VLOOKUP(A84,hr.个税累计数据!C:DT,122,0)-VLOOKUP(A84,hr.个税累计数据!C:DU,123,0)>0,AU84-5000*N84-VLOOKUP(A84,hr.个税累计数据!C:DT,122,0)-VLOOKUP(A84,hr.个税累计数据!C:DU,123,0),0) -> 0 | AW84: =VLOOKUP(BW84,hr.个税累计数据!C:DV,124,0) -> 0 | AY84: =IF(ROUND(MAX(AV84*{0.03,0.1,0.2,0.25,0.3,0.35,0.45}-{0,210,1410,2660,4410,7160,15160}*12)-AW84,2)<=0,0,ROUND(MAX(AV84*{0.03,0.1,0.2,0.25,0.3,0.35,0.45}-{0,210,1410,2660,4410,7160,15160}*12)-AW84,2)) -> 0 | AZ84: =-S84 -> -155.8 | BB84: =AC84-AM84-AY84-AX84+SUM(AZ84:BA84) -> 4139.68 | BD84: =AC84-AM84-AX84-AY84+SUM(AZ84:BA84) -> 4139.68 | BE84: =VLOOKUP($BW84,'HR|社保明细'!C:T,11,0) -> 819.84 | BF84: =VLOOKUP($BW84,'HR|社保明细'!$C:U,12,0) -> 512.4 | BG84: =VLOOKUP($BW84,'HR|社保明细'!$C:V,13,0) -> 25.62 | BH84: =VLOOKUP($BW84,'HR|社保明细'!$C:W,14,0) -> 10.25 | BI84: =VLOOKUP($BW84,'HR|社保明细'!$C:X,15,0) -> 25.62 | BJ84: =VLOOKUP($BW84,'HR|社保明细'!$C:Y,16,0) -> 551 | BK84: =VLOOKUP($BW84,'HR|社保明细'!$C:Z,17,0) -> 0 | BL84: =SUM(BE84:BK84) -> 1944.73 | BR84: =SUM(BN84:BQ84) -> 0 | BS84: =SUM(V84:AB84) -> 250.7 | BT84: 600 | BW84: =C84&I84 -> 天津英才吴靖娴 | BY84: 有 | BZ84: 人才 | CA84: =VLOOKUP(A84,hr.个税累计数据!C:C,1,0) -> 天津英才吴靖娴 | CB84: 天津英才吴靖娴 | CC84: 有 | CD84: =H84=I84 -> TRUE
A85: =C85&I85 -> 天津英才周梓荣 | B85: Shaun-外地 | C85: 天津英才 | D85: 正常计税 | E85: 天津事业部 | F85: 郭双红 | G85: 客服专员 | H85: 周梓荣 | I85: 周梓荣 | J85: 全日制 | K85: =AC85+BL85 -> 8351.23 | L85: =AC85-AM85-AX85-AY85+SUM(AZ85:BA85) -> 5138.25 | N85: 6 | O85: 6000 | Q85: =VLOOKUP(I85,考勤调整记录!I:W,15,0) -> 0 | S85: 155.8 | U85: =SUM(O85:T85) -> 6155.8 | Y85: 250.7 | AC85: =SUM(O85:T85)+SUM(V85:AB85) -> 6406.5 | AE85: 202606 | AF85: =VLOOKUP(BW85,'HR|社保明细'!C:F,4,0) -> 5124 | AG85: =VLOOKUP($BW85,'HR|社保明细'!$C:G,5,0) -> 5013 | AH85: =VLOOKUP($BW85,'HR|社保明细'!$C:H,6,0) -> 409.92 | AI85: =VLOOKUP($BW85,'HR|社保明细'!$C:I,7,0) -> 124.48 | AJ85: =VLOOKUP($BW85,'HR|社保明细'!$C:J,8,0) -> 25.62 | AK85: =VLOOKUP($BW85,'HR|社保明细'!$C:K,9,0) -> 551 | AL85: =VLOOKUP($BW85,'HR|社保明细'!$C:L,10,0) -> 0 | AM85: =SUM(AH85:AL85) -> 1111.02 | AS85: =AC85-AM85-SUM(AN85:AR85) -> 5295.48 | AU85: =VLOOKUP(BW85,hr.个税累计数据!C:DS,121,0) -> 36659.45 | AV85: =IF(AU85-5000*N85-VLOOKUP(A85,hr.个税累计数据!C:DT,122,0)-VLOOKUP(A85,hr.个税累计数据!C:DU,123,0)>0,AU85-5000*N85-VLOOKUP(A85,hr.个税累计数据!C:DT,122,0)-VLOOKUP(A85,hr.个税累计数据!C:DU,123,0),0) -> 93.98 | AW85: =VLOOKUP(BW85,hr.个税累计数据!C:DV,124,0) -> 1.39 | AY85: =IF(ROUND(MAX(AV85*{0.03,0.1,0.2,0.25,0.3,0.35,0.45}-{0,210,1410,2660,4410,7160,15160}*12)-AW85,2)<=0,0,ROUND(MAX(AV85*{0.03,0.1,0.2,0.25,0.3,0.35,0.45}-{0,210,1410,2660,4410,7160,15160}*12)-AW85,2)) -> 1.43 | AZ85: =-S85 -> -155.8 | BB85: =AC85-AM85-AY85-AX85+SUM(AZ85:BA85) -> 5138.25 | BD85: =AC85-AM85-AX85-AY85+SUM(AZ85:BA85) -> 5138.25 | BE85: =VLOOKUP($BW85,'HR|社保明细'!C:T,11,0) -> 819.84 | BF85: =VLOOKUP($BW85,'HR|社保明细'!$C:U,12,0) -> 512.4 | BG85: =VLOOKUP($BW85,'HR|社保明细'!$C:V,13,0) -> 25.62 | BH85: =VLOOKUP($BW85,'HR|社保明细'!$C:W,14,0) -> 10.25 | BI85: =VLOOKUP($BW85,'HR|社保明细'!$C:X,15,0) -> 25.62 | BJ85: =VLOOKUP($BW85,'HR|社保明细'!$C:Y,16,0) -> 551 | BK85: =VLOOKUP($BW85,'HR|社保明细'!$C:Z,17,0) -> 0 | BL85: =SUM(BE85:BK85) -> 1944.73 | BR85: =SUM(BN85:BQ85) -> 0 | BS85: =SUM(V85:AB85) -> 250.7 | BT85: 600 | BW85: =C85&I85 -> 天津英才周梓荣 | BY85: 有 | BZ85: 人才 | CA85: =VLOOKUP(A85,hr.个税累计数据!C:C,1,0) -> 天津英才周梓荣 | CB85: 天津英才周梓荣 | CC85: 有 | CD85: =H85=I85 -> TRUE
A86: =C86&I86 -> 微芮洺程璐 | B86: 物业管理部 | C86: 微芮洺 | D86: 正常计税 | E86: 物业管理部 | F86: 汪顺 | G86: 物业管理 | H86: 程璐 | I86: 程璐 | J86: 全日制 | K86: =AC86+BL86 -> 9590.02 | L86: =AC86-AM86-AX86-AY86+SUM(AZ86:BA86) -> 5699.7 | N86: 6 | O86: 7000 | Q86: =VLOOKUP(I86,考勤调整记录!I:W,15,0) -> 0 | S86: 155.8 | U86: =SUM(O86:T86) -> 7155.8 | AC86: =SUM(O86:T86)+SUM(V86:AB86) -> 7155.8 | AE86: 202606 | AF86: =VLOOKUP(BW86,'HR|社保明细'!C:F,4,0) -> 7460 | AG86: =VLOOKUP($BW86,'HR|社保明细'!$C:G,5,0) -> 7384 | AH86: =VLOOKUP($BW86,'HR|社保明细'!$C:H,6,0) -> 596.8 | AI86: =VLOOKUP($BW86,'HR|社保明细'!$C:I,7,0) -> 149.2 | AJ86: =VLOOKUP($BW86,'HR|社保明细'!$C:J,8,0) -> 37.3 | AK86: =VLOOKUP($BW86,'HR|社保明细'!$C:K,9,0) -> 517 | AL86: =VLOOKUP($BW86,'HR|社保明细'!$C:L,10,0) -> 0 | AM86: =SUM(AH86:AL86) -> 1300.3 | AS86: =AC86-AM86-SUM(AN86:AR86) -> 5855.5 | AU86: =VLOOKUP(BW86,hr.个税累计数据!C:DS,121,0) -> 29665.99 | AV86: =IF(AU86-5000*N86-VLOOKUP(A86,hr.个税累计数据!C:DT,122,0)-VLOOKUP(A86,hr.个税累计数据!C:DU,123,0)>0,AU86-5000*N86-VLOOKUP(A86,hr.个税累计数据!C:DT,122,0)-VLOOKUP(A86,hr.个税累计数据!C:DU,123,0),0) -> 0 | AW86: =VLOOKUP(BW86,hr.个税累计数据!C:DV,124,0) -> 0 | AY86: =IF(ROUND(MAX(AV86*{0.03,0.1,0.2,0.25,0.3,0.35,0.45}-{0,210,1410,2660,4410,7160,15160}*12)-AW86,2)<=0,0,ROUND(MAX(AV86*{0.03,0.1,0.2,0.25,0.3,0.35,0.45}-{0,210,1410,2660,4410,7160,15160}*12)-AW86,2)) -> 0 | AZ86: =-S86 -> -155.8 | BB86: =AC86-AM86-AY86-AX86+SUM(AZ86:BA86) -> 5699.7 | BD86: =AC86-AM86-AX86-AY86+SUM(AZ86:BA86) -> 5699.7 | BE86: =VLOOKUP($BW86,'HR|社保明细'!C:T,11,0) -> 1193.6 | BF86: =VLOOKUP($BW86,'HR|社保明细'!$C:U,12,0) -> 596.8 | BG86: =VLOOKUP($BW86,'HR|社保明细'!$C:V,13,0) -> 37.3 | BH86: =VLOOKUP($BW86,'HR|社保明细'!$C:W,14,0) -> 14.92 | BI86: =VLOOKUP($BW86,'HR|社保明细'!$C:X,15,0) -> 74.6 | BJ86: =VLOOKUP($BW86,'HR|社保明细'!$C:Y,16,0) -> 517 | BK86: =VLOOKUP($BW86,'HR|社保明细'!$C:Z,17,0) -> 0 | BL86: =SUM(BE86:BK86) -> 2434.22 | BR86: =SUM(BN86:BQ86) -> 0 | BS86: =SUM(V86:AB86) -> 0 | BT86: 1250 | BW86: =C86&I86 -> 微芮洺程璐 | BY86: 有 | BZ86: 物业 | CA86: =VLOOKUP(A86,hr.个税累计数据!C:C,1,0) -> 微芮洺程璐 | CB86: 微芮洺程璐 | CC86: 有 | CD86: =H86=I86 -> TRUE
A87: =C87&I87 -> 弈工分健康汪顺 | B87: 公司费用-待结算&法人&智名 | C87: 弈工分健康 | D87: 劳务计税 | E87: 公司费用-法人 | F87: 张毅 | G87: 法人 | H87: 汪顺 | I87: 汪顺 | J87: 非全日制 | K87: =AC87+BL87 -> 1000 | L87: =AC87-AM87-AX87-AY87+SUM(AZ87:BA87) -> 960 | N87: 6 | O87: 1000 | U87: =SUM(O87:T87) -> 1000 | AC87: =SUM(O87:T87)+SUM(V87:AB87) -> 1000 | AE87: 202606 | AF87: =VLOOKUP(BW87,'HR|社保明细'!C:F,4,0) -> 0 | AG87: =VLOOKUP($BW87,'HR|社保明细'!$C:G,5,0) -> 0 | AH87: =VLOOKUP($BW87,'HR|社保明细'!$C:H,6,0) -> 0 | AI87: =VLOOKUP($BW87,'HR|社保明细'!$C:I,7,0) -> 0 | AJ87: =VLOOKUP($BW87,'HR|社保明细'!$C:J,8,0) -> 0 | AK87: =VLOOKUP($BW87,'HR|社保明细'!$C:K,9,0) -> 0 | AL87: =VLOOKUP($BW87,'HR|社保明细'!$C:L,10,0) -> 0 | AM87: =SUM(AH87:AL87) -> 0 | AS87: 1000 | AU87: =VLOOKUP(BW87,hr.个税累计数据!C:DS,121,0) -> 6000 | AV87: =IF(AU87-5000*N87-VLOOKUP(A87,hr.个税累计数据!C:DT,122,0)-VLOOKUP(A87,hr.个税累计数据!C:DU,123,0)>0,AU87-5000*N87-VLOOKUP(A87,hr.个税累计数据!C:DT,122,0)-VLOOKUP(A87,hr.个税累计数据!C:DU,123,0),0) -> 0 | AW87: =VLOOKUP(BW87,hr.个税累计数据!C:DV,124,0) -> 200 | AY87: =IF(D87="国内不计税",0,IF(D87="正常计税",ROUND(MAX(AS87*{0.03,0.1,0.2,0.25,0.3,0.35,0.45}-{0,210,1410,2660,4410,7160,15160},0),2),IF(D87="外籍人",ROUND(MAX(AS87*{0.03,0.1,0.2,0.25,0.3,0.35,0.45}-{0,210,1410,2660,4410,7160,15160},0),2),ROUND(MAX((AS87-IF(AS87<4000,800,AS87*0.2))*10%*{2,3,4}-1000*{0,2,7},0),2)))) -> 40 | AZ87: =-S87 -> 0 | BB87: =AC87-AM87-AY87-AX87+SUM(AZ87:BA87) -> 960 | BD87: =AC87-AM87-AX87-AY87+SUM(AZ87:BA87) -> 960 | BE87: =VLOOKUP($BW87,'HR|社保明细'!C:T,11,0) -> 0 | BF87: =VLOOKUP($BW87,'HR|社保明细'!$C:U,12,0) -> 0 | BG87: =VLOOKUP($BW87,'HR|社保明细'!$C:V,13,0) -> 0 | BH87: =VLOOKUP($BW87,'HR|社保明细'!$C:W,14,0) -> 0 | BI87: =VLOOKUP($BW87,'HR|社保明细'!$C:X,15,0) -> 0 | BJ87: =VLOOKUP($BW87,'HR|社保明细'!$C:Y,16,0) -> 0 | BK87: =VLOOKUP($BW87,'HR|社保明细'!$C:Z,17,0) -> 0 | BL87: =SUM(BE87:BK87) -> 0 | BR87: =SUM(BN87:BQ87) -> 0 | BS87: =SUM(V87:AB87) -> 0 | BW87: =C87&I87 -> 弈工分健康汪顺 | BX87: 无社公 | BY87: 无 | CA87: =VLOOKUP(A87,hr.个税累计数据!C:C,1,0) -> 弈工分健康汪顺 | CB87: 弈工分健康戴琼琪 | CD87: =H87=I87 -> TRUE
A88: =C88&I88 -> 弈工分健康胡金明 | B88: 物业维修部 | C88: 弈工分健康 | D88: 正常计税 | E88: 物业维修部 | F88: 方有保 | G88: 水电工程师 | H88: 胡金明 | I88: 胡金明 | J88: 不定时工作制 | K88: =AC88+BL88 -> 10390.02 | L88: =AC88-AM88-AX88-AY88+SUM(AZ88:BA88) -> 6450.03 | N88: 6 | O88: 7500 | Q88: =VLOOKUP(I88,考勤调整记录!I:W,15,0) -> 0 | S88: 155.8 | U88: =SUM(O88:T88) -> 7655.8 | Y88: 300 | AC88: =SUM(O88:T88)+SUM(V88:AB88) -> 7955.8 | AE88: 202606 | AF88: =VLOOKUP(BW88,'HR|社保明细'!C:F,4,0) -> 7460 | AG88: =VLOOKUP($BW88,'HR|社保明细'!$C:G,5,0) -> 7384 | AH88: =VLOOKUP($BW88,'HR|社保明细'!$C:H,6,0) -> 596.8 | AI88: =VLOOKUP($BW88,'HR|社保明细'!$C:I,7,0) -> 149.2 | AJ88: =VLOOKUP($BW88,'HR|社保明细'!$C:J,8,0) -> 37.3 | AK88: =VLOOKUP($BW88,'HR|社保明细'!$C:K,9,0) -> 517 | AL88: =VLOOKUP($BW88,'HR|社保明细'!$C:L,10,0) -> 0 | AM88: =SUM(AH88:AL88) -> 1300.3 | AP88: 1500 | AS88: =AC88-AM88-SUM(AN88:AR88) -> 5155.5 | AU88: =VLOOKUP(BW88,hr.个税累计数据!C:DS,121,0) -> 47889.69 | AV88: =IF(AU88-5000*N88-VLOOKUP(A88,hr.个税累计数据!C:DT,122,0)-VLOOKUP(A88,hr.个税累计数据!C:DU,123,0)>0,AU88-5000*N88-VLOOKUP(A88,hr.个税累计数据!C:DT,122,0)-VLOOKUP(A88,hr.个税累计数据!C:DU,123,0),0) -> 10087.89 | AW88: =VLOOKUP(BW88,hr.个税累计数据!C:DV,124,0) -> 252.97 | AY88: =IF(ROUND(MAX(AV88*{0.03,0.1,0.2,0.25,0.3,0.35,0.45}-{0,210,1410,2660,4410,7160,15160}*12)-AW88,2)<=0,0,ROUND(MAX(AV88*{0.03,0.1,0.2,0.25,0.3,0.35,0.45}-{0,210,1410,2660,4410,7160,15160}*12)-AW88,2)) -> 49.67 | AZ88: =-S88 -> -155.8 | BB88: =AC88-AM88-AY88-AX88+SUM(AZ88:BA88) -> 6450.03 | BD88: =AC88-AM88-AX88-AY88+SUM(AZ88:BA88) -> 6450.03 | BE88: =VLOOKUP($BW88,'HR|社保明细'!C:T,11,0) -> 1193.6 | BF88: =VLOOKUP($BW88,'HR|社保明细'!$C:U,12,0) -> 596.8 | BG88: =VLOOKUP($BW88,'HR|社保明细'!$C:V,13,0) -> 37.3 | BH88: =VLOOKUP($BW88,'HR|社保明细'!$C:W,14,0) -> 14.92 | BI88: =VLOOKUP($BW88,'HR|社保明细'!$C:X,15,0) -> 74.6 | BJ88: =VLOOKUP($BW88,'HR|社保明细'!$C:Y,16,0) -> 517 | BK88: =VLOOKUP($BW88,'HR|社保明细'!$C:Z,17,0) -> 0 | BL88: =SUM(BE88:BK88) -> 2434.22 | BR88: =SUM(BN88:BQ88) -> 0 | BS88: =SUM(V88:AB88) -> 300 | BT88: 1250 | BW88: =C88&I88 -> 弈工分健康胡金明 | BY88: 有 | BZ88: 物业 | CA88: =VLOOKUP(A88,hr.个税累计数据!C:C,1,0) -> 弈工分健康胡金明 | CB88: 弈工分健康胡金明 | CC88: 有 | CD88: =H88=I88 -> TRUE
A89: =C89&I89 -> 弈工分信息赵柳文 | B89: C-大后台-法务 | C89: 弈工分信息 | D89: 正常计税 | E89: 法务部 | F89: 王妤扬 | G89: 法务专员 | H89: 赵柳文 | I89: 赵柳文 | J89: 全日制 | K89: =AC89+BL89 -> 10475 | L89: =AC89-AM89-AX89-AY89+SUM(AZ89:BA89) -> 6259.43 | N89: 3 | O89: 8000 | Q89: =VLOOKUP(I89,考勤调整记录!I:W,15,0) -> 0 | S89: 155.8 | U89: =SUM(O89:T89) -> 8155.8 | W89: -296.8 | AC89: =SUM(O89:T89)+SUM(V89:AB89) -> 7859 | AE89: 202606 | AF89: =VLOOKUP(BW89,'HR|社保明细'!C:F,4,0) -> 8000 | AG89: =VLOOKUP($BW89,'HR|社保明细'!$C:G,5,0) -> 8000 | AH89: =VLOOKUP($BW89,'HR|社保明细'!$C:H,6,0) -> 640 | AI89: =VLOOKUP($BW89,'HR|社保明细'!$C:I,7,0) -> 160 | AJ89: =VLOOKUP($BW89,'HR|社保明细'!$C:J,8,0) -> 40 | AK89: =VLOOKUP($BW89,'HR|社保明细'!$C:K,9,0) -> 560 | AL89: =VLOOKUP($BW89,'HR|社保明细'!$C:L,10,0) -> 0 | AM89: =SUM(AH89:AL89) -> 1400 | AP89: 1500 | AS89: =AC89-AM89-SUM(AN89:AR89) -> 4959 | AU89: =VLOOKUP(BW89,hr.个税累计数据!C:DS,121,0) -> 21320.03 | AV89: =IF(AU89-5000*N89-VLOOKUP(A89,hr.个税累计数据!C:DT,122,0)-VLOOKUP(A89,hr.个税累计数据!C:DU,123,0)>0,AU89-5000*N89-VLOOKUP(A89,hr.个税累计数据!C:DT,122,0)-VLOOKUP(A89,hr.个税累计数据!C:DU,123,0),0) -> 2120.03 | AW89: =VLOOKUP(BW89,hr.个税累计数据!C:DV,124,0) -> 19.83 | AY89: =IF(ROUND(MAX(AV89*{0.03,0.1,0.2,0.25,0.3,0.35,0.45}-{0,210,1410,2660,4410,7160,15160}*12)-AW89,2)<=0,0,ROUND(MAX(AV89*{0.03,0.1,0.2,0.25,0.3,0.35,0.45}-{0,210,1410,2660,4410,7160,15160}*12)-AW89,2)) -> 43.77 | AZ89: =-S89 -> -155.8 | BB89: =AC89-AM89-AY89-AX89+SUM(AZ89:BA89) -> 6259.43 | BD89: =AC89-AM89-AX89-AY89+SUM(AZ89:BA89) -> 6259.43 | BE89: =VLOOKUP($BW89,'HR|社保明细'!C:T,11,0) -> 1280 | BF89: =VLOOKUP($BW89,'HR|社保明细'!$C:U,12,0) -> 640 | BG89: =VLOOKUP($BW89,'HR|社保明细'!$C:V,13,0) -> 40 | BH89: =VLOOKUP($BW89,'HR|社保明细'!$C:W,14,0) -> 16 | BI89: =VLOOKUP($BW89,'HR|社保明细'!$C:X,15,0) -> 80 | BJ89: =VLOOKUP($BW89,'HR|社保明细'!$C:Y,16,0) -> 560 | BK89: =VLOOKUP($BW89,'HR|社保明细'!$C:Z,17,0) -> 0 | BL89: =SUM(BE89:BK89) -> 2616 | BR89: =SUM(BN89:BQ89) -> 0 | BS89: =SUM(V89:AB89) -> -296.8 | BT89: 1250 | BW89: =C89&I89 -> 弈工分信息赵柳文 | BY89: 有 | BZ89: 物业 | CA89: =VLOOKUP(A89,hr.个税累计数据!C:C,1,0) -> 弈工分信息赵柳文 | CB89: 弈工分健康胡金明 | CC89: 有 | CD89: =H89=I89 -> TRUE
A90: =C90&I90 -> 弈工分健康贾飞龙 | B90: 物业保安部 | C90: 弈工分健康 | D90: 正常计税 | E90: 物业保安部 | F90: 汪顺 | G90: 园区保安队长 | H90: 贾飞龙 | I90: 贾飞龙 | J90: 全日制 | K90: =AC90+BL90 -> 12562.43 | L90: =AC90-AM90-AX90-AY90+SUM(AZ90:BA90) -> 8557.27 | N90: 6 | O90: 8500 | Q90: =VLOOKUP(I90,考勤调整记录!I:W,15,0) -> 1172.41 | S90: 155.8 | U90: =SUM(O90:T90) -> 9828.21 | Y90: 300 | AC90: =SUM(O90:T90)+SUM(V90:AB90) -> 10128.21 | AE90: 202606 | AF90: =VLOOKUP(BW90,'HR|社保明细'!C:F,4,0) -> 7460 | AG90: =VLOOKUP($BW90,'HR|社保明细'!$C:G,5,0) -> 7384 | AH90: =VLOOKUP($BW90,'HR|社保明细'!$C:H,6,0) -> 596.8 | AI90: =VLOOKUP($BW90,'HR|社保明细'!$C:I,7,0) -> 149.2 | AJ90: =VLOOKUP($BW90,'HR|社保明细'!$C:J,8,0) -> 37.3 | AK90: =VLOOKUP($BW90,'HR|社保明细'!$C:K,9,0) -> 517 | AL90: =VLOOKUP($BW90,'HR|社保明细'!$C:L,10,0) -> 0 | AM90: =SUM(AH90:AL90) -> 1300.3 | AP90: 1500 | AS90: =AC90-AM90-SUM(AN90:AR90) -> 7327.91 | AU90: =VLOOKUP(BW90,hr.个税累计数据!C:DS,121,0) -> 56416.72 | AV90: =IF(AU90-5000*N90-VLOOKUP(A90,hr.个税累计数据!C:DT,122,0)-VLOOKUP(A90,hr.个税累计数据!C:DU,123,0)>0,AU90-5000*N90-VLOOKUP(A90,hr.个税累计数据!C:DT,122,0)-VLOOKUP(A90,hr.个税累计数据!C:DU,123,0),0) -> 18614.92 | AW90: =VLOOKUP(BW90,hr.个税累计数据!C:DV,124,0) -> 443.61 | AY90: =IF(ROUND(MAX(AV90*{0.03,0.1,0.2,0.25,0.3,0.35,0.45}-{0,210,1410,2660,4410,7160,15160}*12)-AW90,2)<=0,0,ROUND(MAX(AV90*{0.03,0.1,0.2,0.25,0.3,0.35,0.45}-{0,210,1410,2660,4410,7160,15160}*12)-AW90,2)) -> 114.84 | AZ90: =-S90 -> -155.8 | BB90: =AC90-AM90-AY90-AX90+SUM(AZ90:BA90) -> 8557.27 | BD90: =AC90-AM90-AX90-AY90+SUM(AZ90:BA90) -> 8557.27 | BE90: =VLOOKUP($BW90,'HR|社保明细'!C:T,11,0) -> 1193.6 | BF90: =VLOOKUP($BW90,'HR|社保明细'!$C:U,12,0) -> 596.8 | BG90: =VLOOKUP($BW90,'HR|社保明细'!$C:V,13,0) -> 37.3 | BH90: =VLOOKUP($BW90,'HR|社保明细'!$C:W,14,0) -> 14.92 | BI90: =VLOOKUP($BW90,'HR|社保明细'!$C:X,15,0) -> 74.6 | BJ90: =VLOOKUP($BW90,'HR|社保明细'!$C:Y,16,0) -> 517 | BK90: =VLOOKUP($BW90,'HR|社保明细'!$C:Z,17,0) -> 0 | BL90: =SUM(BE90:BK90) -> 2434.22 | BR90: =SUM(BN90:BQ90) -> 0 | BS90: =SUM(V90:AB90) -> 300 | BT90: 1250 | BW90: =C90&I90 -> 弈工分健康贾飞龙 | BY90: 有 | BZ90: 物业 | CA90: =VLOOKUP(A90,hr.个税累计数据!C:C,1,0) -> 弈工分健康贾飞龙 | CB90: 弈工分健康贾飞龙 | CC90: 有 | CD90: =H90=I90 -> TRUE
A91: =C91&I91 -> 弈工分健康殷德昌 | B91: 物业保洁部 | C91: 弈工分健康 | D91: 正常计税 | E91: 物业保洁部 | F91: 宣国英 | G91: 保洁 | H91: 殷德昌 | I91: 殷德昌 | J91: 全日制 | K91: =AC91+BL91 -> 4550 | L91: =AC91-AM91-AX91-AY91+SUM(AZ91:BA91) -> 4550 | N91: 6 | O91: 4000 | Q91: =VLOOKUP(I91,考勤调整记录!I:W,15,0) -> 200 | U91: =SUM(O91:T91) -> 4200 | Y91: 300 | AB91: 50 | AC91: =SUM(O91:T91)+SUM(V91:AB91) -> 4550 | AE91: 202606 | AS91: =AC91-AM91-SUM(AN91:AR91) -> 4550 | AU91: =VLOOKUP(BW91,hr.个税累计数据!C:DS,121,0) -> 25657.7 | AV91: =IF(AU91-5000*N91-VLOOKUP(A91,hr.个税累计数据!C:DT,122,0)-VLOOKUP(A91,hr.个税累计数据!C:DU,123,0)>0,AU91-5000*N91-VLOOKUP(A91,hr.个税累计数据!C:DT,122,0)-VLOOKUP(A91,hr.个税累计数据!C:DU,123,0),0) -> 0 | AW91: =VLOOKUP(BW91,hr.个税累计数据!C:DV,124,0) -> 0 | AY91: =IF(ROUND(MAX(AV91*{0.03,0.1,0.2,0.25,0.3,0.35,0.45}-{0,210,1410,2660,4410,7160,15160}*12)-AW91,2)<=0,0,ROUND(MAX(AV91*{0.03,0.1,0.2,0.25,0.3,0.35,0.45}-{0,210,1410,2660,4410,7160,15160}*12)-AW91,2)) -> 0 | AZ91: =-S91 -> 0 | BB91: =AC91-AM91-AY91-AX91+SUM(AZ91:BA91) -> 4550 | BD91: =AC91-AM91-AX91-AY91+SUM(AZ91:BA91) -> 4550 | BL91: =SUM(BE91:BK91) -> 0 | BS91: =SUM(V91:AB91) -> 350 | BT91: 1250 | BW91: =C91&I91 -> 弈工分健康殷德昌 | BX91: 无社公 | BY91: 保洁 | CA91: =VLOOKUP(A91,hr.个税累计数据!C:C,1,0) -> 弈工分健康殷德昌 | CB91: 弈工分健康殷德昌 | CC91: 有-意外险 | CD91: =H91=I91 -> TRUE
A92: =C92&I92 -> 弈工分健康高玉玲 | B92: 物业保洁部 | C92: 弈工分健康 | D92: 正常计税 | E92: 物业保洁部 | F92: 宣国英 | G92: 保洁 | H92: 高玉玲 | I92: 高玉玲 | J92: 全日制 | K92: =AC92+BL92 -> 4100 | L92: =AC92-AM92-AX92-AY92+SUM(AZ92:BA92) -> 4100 | N92: 6 | O92: 4000 | Q92: =VLOOKUP(I92,考勤调整记录!I:W,15,0) -> 0 | U92: =SUM(O92:T92) -> 4000 | AB92: 100 | AC92: =SUM(O92:T92)+SUM(V92:AB92) -> 4100 | AE92: 202606 | AS92: =AC92-AM92-SUM(AN92:AR92) -> 4100 | AU92: =VLOOKUP(BW92,hr.个税累计数据!C:DS,121,0) -> 24273.85 | AV92: =IF(AU92-5000*N92-VLOOKUP(A92,hr.个税累计数据!C:DT,122,0)-VLOOKUP(A92,hr.个税累计数据!C:DU,123,0)>0,AU92-5000*N92-VLOOKUP(A92,hr.个税累计数据!C:DT,122,0)-VLOOKUP(A92,hr.个税累计数据!C:DU,123,0),0) -> 0 | AW92: =VLOOKUP(BW92,hr.个税累计数据!C:DV,124,0) -> 0 | AY92: =IF(ROUND(MAX(AV92*{0.03,0.1,0.2,0.25,0.3,0.35,0.45}-{0,210,1410,2660,4410,7160,15160}*12)-AW92,2)<=0,0,ROUND(MAX(AV92*{0.03,0.1,0.2,0.25,0.3,0.35,0.45}-{0,210,1410,2660,4410,7160,15160}*12)-AW92,2)) -> 0 | AZ92: =-S92 -> 0 | BB92: =AC92-AM92-AY92-AX92+SUM(AZ92:BA92) -> 4100 | BD92: =AC92-AM92-AX92-AY92+SUM(AZ92:BA92) -> 4100 | BL92: =SUM(BE92:BK92) -> 0 | BS92: =SUM(V92:AB92) -> 100 | BT92: 1250 | BW92: =C92&I92 -> 弈工分健康高玉玲 | BX92: 无社公 | BY92: 保洁 | CA92: =VLOOKUP(A92,hr.个税累计数据!C:C,1,0) -> 弈工分健康高玉玲 | CB92: 弈工分健康高玉玲 | CC92: 有-意外险 | CD92: =H92=I92 -> TRUE
A93: =C93&I93 -> 弈工分健康丁成英 | B93: 物业保洁部 | C93: 弈工分健康 | D93: 正常计税 | E93: 物业保洁部 | F93: 宣国英 | G93: 保洁 | H93: 丁成英 | I93: 丁成英 | J93: 全日制 | K93: =AC93+BL93 -> 4000 | L93: =AC93-AM93-AX93-AY93+SUM(AZ93:BA93) -> 4000 | N93: 6 | O93: 4000 | Q93: =VLOOKUP(I93,考勤调整记录!I:W,15,0) -> 0 | U93: =SUM(O93:T93) -> 4000 | AC93: =SUM(O93:T93)+SUM(V93:AB93) -> 4000 | AE93: 202606 | AS93: =AC93-AM93-SUM(AN93:AR93) -> 4000 | AU93: =VLOOKUP(BW93,hr.个税累计数据!C:DS,121,0) -> 24646.16 | AV93: =IF(AU93-5000*N93-VLOOKUP(A93,hr.个税累计数据!C:DT,122,0)-VLOOKUP(A93,hr.个税累计数据!C:DU,123,0)>0,AU93-5000*N93-VLOOKUP(A93,hr.个税累计数据!C:DT,122,0)-VLOOKUP(A93,hr.个税累计数据!C:DU,123,0),0) -> 0 | AW93: =VLOOKUP(BW93,hr.个税累计数据!C:DV,124,0) -> 0 | AY93: =IF(ROUND(MAX(AV93*{0.03,0.1,0.2,0.25,0.3,0.35,0.45}-{0,210,1410,2660,4410,7160,15160}*12)-AW93,2)<=0,0,ROUND(MAX(AV93*{0.03,0.1,0.2,0.25,0.3,0.35,0.45}-{0,210,1410,2660,4410,7160,15160}*12)-AW93,2)) -> 0 | AZ93: =-S93 -> 0 | BB93: =AC93-AM93-AY93-AX93+SUM(AZ93:BA93) -> 4000 | BD93: =AC93-AM93-AX93-AY93+SUM(AZ93:BA93) -> 4000 | BL93: =SUM(BE93:BK93) -> 0 | BS93: =SUM(V93:AB93) -> 0 | BT93: 1250 | BW93: =C93&I93 -> 弈工分健康丁成英 | BX93: 无社公 | BY93: 保洁 | CA93: =VLOOKUP(A93,hr.个税累计数据!C:C,1,0) -> 弈工分健康丁成英 | CB93: 弈工分健康丁成英 | CC93: 有-意外险 | CD93: =H93=I93 -> TRUE
A94: =C94&I94 -> 弈工分健康孙建芳 | B94: 物业保洁部 | C94: 弈工分健康 | D94: 正常计税 | E94: 物业保洁部 | F94: 宣国英 | G94: 保洁 | H94: 孙建芳 | I94: 孙建芳 | J94: 全日制 | K94: =AC94+BL94 -> 4507.69 | L94: =AC94-AM94-AX94-AY94+SUM(AZ94:BA94) -> 4507.69 | N94: 6 | O94: 4000 | Q94: =VLOOKUP(I94,考勤调整记录!I:W,15,0) -> 507.69 | U94: =SUM(O94:T94) -> 4507.69 | AC94: =SUM(O94:T94)+SUM(V94:AB94) -> 4507.69 | AE94: 202606 | AS94: =AC94-AM94-SUM(AN94:AR94) -> 4507.69 | AU94: =VLOOKUP(BW94,hr.个税累计数据!C:DS,121,0) -> 23876.92 | AV94: =IF(AU94-5000*N94-VLOOKUP(A94,hr.个税累计数据!C:DT,122,0)-VLOOKUP(A94,hr.个税累计数据!C:DU,123,0)>0,AU94-5000*N94-VLOOKUP(A94,hr.个税累计数据!C:DT,122,0)-VLOOKUP(A94,hr.个税累计数据!C:DU,123,0),0) -> 0 | AW94: =VLOOKUP(BW94,hr.个税累计数据!C:DV,124,0) -> 0 | AY94: =IF(ROUND(MAX(AV94*{0.03,0.1,0.2,0.25,0.3,0.35,0.45}-{0,210,1410,2660,4410,7160,15160}*12)-AW94,2)<=0,0,ROUND(MAX(AV94*{0.03,0.1,0.2,0.25,0.3,0.35,0.45}-{0,210,1410,2660,4410,7160,15160}*12)-AW94,2)) -> 0 | AZ94: =-S94 -> 0 | BB94: =AC94-AM94-AY94-AX94+SUM(AZ94:BA94) -> 4507.69 | BD94: =AC94-AM94-AX94-AY94+SUM(AZ94:BA94) -> 4507.69 | BL94: =SUM(BE94:BK94) -> 0 | BS94: =SUM(V94:AB94) -> 0 | BT94: 1250 | BW94: =C94&I94 -> 弈工分健康孙建芳 | BX94: 无社公 | BY94: 保洁 | CA94: =VLOOKUP(A94,hr.个税累计数据!C:C,1,0) -> 弈工分健康孙建芳 | CB94: 弈工分健康孙建芳 | CC94: 有-意外险 | CD94: =H94=I94 -> TRUE
A95: =C95&I95 -> 弈工分健康黄连兵 | B95: 物业保安部 | C95: 弈工分健康 | D95: 正常计税 | E95: 物业保安部 | F95: 贾飞龙 | G95: 园区保安 | H95: 黄连兵 | I95: 黄连兵 | J95: 全日制 | K95: =AC95+BL95 -> 9250.55 | L95: =AC95-AM95-AX95-AY95+SUM(AZ95:BA95) -> 6382.02 | N95: 6 | O95: 3200 | Q95: =VLOOKUP(I95,考勤调整记录!I:W,15,0) -> 433.33 | R95: 3300 | U95: =SUM(O95:T95) -> 6933.33 | Y95: 300 | AA95: 100 | AC95: =SUM(O95:T95)+SUM(V95:AB95) -> 7333.33 | AE95: 202606 | AF95: =VLOOKUP(BW95,'HR|社保明细'!C:F,4,0) -> 7460 | AG95: =VLOOKUP($BW95,'HR|社保明细'!$C:G,5,0) -> 0 | AH95: =VLOOKUP($BW95,'HR|社保明细'!$C:H,6,0) -> 596.8 | AI95: =VLOOKUP($BW95,'HR|社保明细'!$C:I,7,0) -> 149.2 | AJ95: =VLOOKUP($BW95,'HR|社保明细'!$C:J,8,0) -> 37.3 | AK95: =VLOOKUP($BW95,'HR|社保明细'!$C:K,9,0) -> 0 | AL95: =VLOOKUP($BW95,'HR|社保明细'!$C:L,10,0) -> 0 | AM95: =SUM(AH95:AL95) -> 783.3 | AS95: =AC95-AM95-SUM(AN95:AR95) -> 6550.03 | AU95: =VLOOKUP(BW95,hr.个税累计数据!C:DS,121,0) -> 43433.33 | AV95: =IF(AU95-5000*N95-VLOOKUP(A95,hr.个税累计数据!C:DT,122,0)-VLOOKUP(A95,hr.个税累计数据!C:DU,123,0)>0,AU95-5000*N95-VLOOKUP(A95,hr.个税累计数据!C:DT,122,0)-VLOOKUP(A95,hr.个税累计数据!C:DU,123,0),0) -> 8733.53 | AW95: =VLOOKUP(BW95,hr.个税累计数据!C:DV,124,0) -> 94 | AY95: =IF(ROUND(MAX(AV95*{0.03,0.1,0.2,0.25,0.3,0.35,0.45}-{0,210,1410,2660,4410,7160,15160}*12)-AW95,2)<=0,0,ROUND(MAX(AV95*{0.03,0.1,0.2,0.25,0.3,0.35,0.45}-{0,210,1410,2660,4410,7160,15160}*12)-AW95,2)) -> 168.01 | AZ95: =-S95 -> 0 | BB95: =AC95-AM95-AY95-AX95+SUM(AZ95:BA95) -> 6382.02 | BD95: =AC95-AM95-AX95-AY95+SUM(AZ95:BA95) -> 6382.02 | BE95: =VLOOKUP($BW95,'HR|社保明细'!C:T,11,0) -> 1193.6 | BF95: =VLOOKUP($BW95,'HR|社保明细'!$C:U,12,0) -> 596.8 | BG95: =VLOOKUP($BW95,'HR|社保明细'!$C:V,13,0) -> 37.3 | BH95: =VLOOKUP($BW95,'HR|社保明细'!$C:W,14,0) -> 14.92 | BI95: =VLOOKUP($BW95,'HR|社保明细'!$C:X,15,0) -> 74.6 | BJ95: =VLOOKUP($BW95,'HR|社保明细'!$C:Y,16,0) -> 0 | BK95: =VLOOKUP($BW95,'HR|社保明细'!$C:Z,17,0) -> 0 | BL95: =SUM(BE95:BK95) -> 1917.22 | BS95: =SUM(V95:AB95) -> 400 | BT95: 1250 | BW95: =C95&I95 -> 弈工分健康黄连兵 | BX95: 无社公 | BY95: 保安 | CA95: =VLOOKUP(A95,hr.个税累计数据!C:C,1,0) -> 弈工分健康黄连兵 | CB95: 弈工分健康黄连兵 | CD95: =H95=I95 -> TRUE
A96: =C96&I96 -> 弈工分健康庄艳林 | B96: 物业保安部 | C96: 弈工分健康 | D96: 正常计税 | E96: 物业保安部 | F96: 贾飞龙 | G96: 园区保安 | H96: 庄艳林 | I96: 庄艳林 | J96: 全日制 | K96: =AC96+BL96 -> 9350.55 | L96: =AC96-AM96-AX96-AY96+SUM(AZ96:BA96) -> 6600.53 | N96: 6 | O96: 3200 | Q96: =VLOOKUP(I96,考勤调整记录!I:W,15,0) -> 433.33 | R96: 3300 | U96: =SUM(O96:T96) -> 6933.33 | Y96: 300 | AA96: 200 | AC96: =SUM(O96:T96)+SUM(V96:AB96) -> 7433.33 | AE96: 202606 | AF96: =VLOOKUP(BW96,'HR|社保明细'!C:F,4,0) -> 7460 | AG96: =VLOOKUP($BW96,'HR|社保明细'!$C:G,5,0) -> 0 | AH96: =VLOOKUP($BW96,'HR|社保明细'!$C:H,6,0) -> 596.8 | AI96: =VLOOKUP($BW96,'HR|社保明细'!$C:I,7,0) -> 149.2 | AJ96: =VLOOKUP($BW96,'HR|社保明细'!$C:J,8,0) -> 37.3 | AK96: =VLOOKUP($BW96,'HR|社保明细'!$C:K,9,0) -> 0 | AL96: =VLOOKUP($BW96,'HR|社保明细'!$C:L,10,0) -> 0 | AM96: =SUM(AH96:AL96) -> 783.3 | AS96: =AC96-AM96-SUM(AN96:AR96) -> 6650.03 | AU96: =VLOOKUP(BW96,hr.个税累计数据!C:DS,121,0) -> 43633.33 | AV96: =IF(AU96-5000*N96-VLOOKUP(A96,hr.个税累计数据!C:DT,122,0)-VLOOKUP(A96,hr.个税累计数据!C:DU,123,0)>0,AU96-5000*N96-VLOOKUP(A96,hr.个税累计数据!C:DT,122,0)-VLOOKUP(A96,hr.个税累计数据!C:DU,123,0),0) -> 8933.53 | AW96: =VLOOKUP(BW96,hr.个税累计数据!C:DV,124,0) -> 218.51 | AY96: =IF(ROUND(MAX(AV96*{0.03,0.1,0.2,0.25,0.3,0.35,0.45}-{0,210,1410,2660,4410,7160,15160}*12)-AW96,2)<=0,0,ROUND(MAX(AV96*{0.03,0.1,0.2,0.25,0.3,0.35,0.45}-{0,210,1410,2660,4410,7160,15160}*12)-AW96,2)) -> 49.5 | AZ96: =-S96 -> 0 | BB96: =AC96-AM96-AY96-AX96+SUM(AZ96:BA96) -> 6600.53 | BD96: =AC96-AM96-AX96-AY96+SUM(AZ96:BA96) -> 6600.53 | BE96: =VLOOKUP($BW96,'HR|社保明细'!C:T,11,0) -> 1193.6 | BF96: =VLOOKUP($BW96,'HR|社保明细'!$C:U,12,0) -> 596.8 | BG96: =VLOOKUP($BW96,'HR|社保明细'!$C:V,13,0) -> 37.3 | BH96: =VLOOKUP($BW96,'HR|社保明细'!$C:W,14,0) -> 14.92 | BI96: =VLOOKUP($BW96,'HR|社保明细'!$C:X,15,0) -> 74.6 | BJ96: =VLOOKUP($BW96,'HR|社保明细'!$C:Y,16,0) -> 0 | BK96: =VLOOKUP($BW96,'HR|社保明细'!$C:Z,17,0) -> 0 | BL96: =SUM(BE96:BK96) -> 1917.22 | BS96: =SUM(V96:AB96) -> 500 | BT96: 1250 | BW96: =C96&I96 -> 弈工分健康庄艳林 | BX96: 无社公 | BY96: 保安 | CA96: =VLOOKUP(A96,hr.个税累计数据!C:C,1,0) -> 弈工分健康庄艳林 | CB96: 弈工分健康庄艳林 | CD96: =H96=I96 -> TRUE
A97: =C97&I97 -> 弈工分健康谢小强 | B97: 物业保安部 | C97: 弈工分健康 | D97: 正常计税 | E97: 物业保安部 | F97: 贾飞龙 | G97: 园区保安 | H97: 谢小强 | I97: 谢小强 | J97: 全日制 | K97: =AC97+BL97 -> 9350.55 | L97: =AC97-AM97-AX97-AY97+SUM(AZ97:BA97) -> 6600.52 | N97: 6 | O97: 3200 | Q97: =VLOOKUP(I97,考勤调整记录!I:W,15,0) -> 433.33 | R97: 3300 | U97: =SUM(O97:T97) -> 6933.33 | Y97: 300 | AA97: 200 | AC97: =SUM(O97:T97)+SUM(V97:AB97) -> 7433.33 | AE97: 202606 | AF97: =VLOOKUP(BW97,'HR|社保明细'!C:F,4,0) -> 7460 | AG97: =VLOOKUP($BW97,'HR|社保明细'!$C:G,5,0) -> 0 | AH97: =VLOOKUP($BW97,'HR|社保明细'!$C:H,6,0) -> 596.8 | AI97: =VLOOKUP($BW97,'HR|社保明细'!$C:I,7,0) -> 149.2 | AJ97: =VLOOKUP($BW97,'HR|社保明细'!$C:J,8,0) -> 37.3 | AK97: =VLOOKUP($BW97,'HR|社保明细'!$C:K,9,0) -> 0 | AL97: =VLOOKUP($BW97,'HR|社保明细'!$C:L,10,0) -> 0 | AM97: =SUM(AH97:AL97) -> 783.3 | AS97: =AC97-AM97-SUM(AN97:AR97) -> 6650.03 | AU97: =VLOOKUP(BW97,hr.个税累计数据!C:DS,121,0) -> 39851.66 | AV97: =IF(AU97-5000*N97-VLOOKUP(A97,hr.个税累计数据!C:DT,122,0)-VLOOKUP(A97,hr.个税累计数据!C:DU,123,0)>0,AU97-5000*N97-VLOOKUP(A97,hr.个税累计数据!C:DT,122,0)-VLOOKUP(A97,hr.个税累计数据!C:DU,123,0),0) -> 5151.86 | AW97: =VLOOKUP(BW97,hr.个税累计数据!C:DV,124,0) -> 105.05 | AY97: =IF(ROUND(MAX(AV97*{0.03,0.1,0.2,0.25,0.3,0.35,0.45}-{0,210,1410,2660,4410,7160,15160}*12)-AW97,2)<=0,0,ROUND(MAX(AV97*{0.03,0.1,0.2,0.25,0.3,0.35,0.45}-{0,210,1410,2660,4410,7160,15160}*12)-AW97,2)) -> 49.51 | AZ97: =-S97 -> 0 | BB97: =AC97-AM97-AY97-AX97+SUM(AZ97:BA97) -> 6600.52 | BD97: =AC97-AM97-AX97-AY97+SUM(AZ97:BA97) -> 6600.52 | BE97: =VLOOKUP($BW97,'HR|社保明细'!C:T,11,0) -> 1193.6 | BF97: =VLOOKUP($BW97,'HR|社保明细'!$C:U,12,0) -> 596.8 | BG97: =VLOOKUP($BW97,'HR|社保明细'!$C:V,13,0) -> 37.3 | BH97: =VLOOKUP($BW97,'HR|社保明细'!$C:W,14,0) -> 14.92 | BI97: =VLOOKUP($BW97,'HR|社保明细'!$C:X,15,0) -> 74.6 | BJ97: =VLOOKUP($BW97,'HR|社保明细'!$C:Y,16,0) -> 0 | BK97: =VLOOKUP($BW97,'HR|社保明细'!$C:Z,17,0) -> 0 | BL97: =SUM(BE97:BK97) -> 1917.22 | BS97: =SUM(V97:AB97) -> 500 | BT97: 1250 | BW97: =C97&I97 -> 弈工分健康谢小强 | BX97: 无社公 | BY97: 保安 | CA97: =VLOOKUP(A97,hr.个税累计数据!C:C,1,0) -> 弈工分健康谢小强 | CB97: 弈工分健康谢小强 | CD97: =H97=I97 -> TRUE
A98: =C98&I98 -> 弈工分健康史文奎 | B98: 物业保安部 | C98: 弈工分健康 | D98: 正常计税 | E98: 物业保安部 | F98: 贾飞龙 | G98: 园区保安 | H98: 史文奎 | I98: 史文奎 | J98: 全日制 | K98: =AC98+BL98 -> 9093.02 | L98: =AC98-AM98-AX98-AY98+SUM(AZ98:BA98) -> 6236.7 | N98: 6 | O98: 3000 | Q98: =VLOOKUP(I98,考勤调整记录!I:W,15,0) -> 420 | R98: 3300 | S98: 155.8 | U98: =SUM(O98:T98) -> 6875.8 | Y98: 300 | AC98: =SUM(O98:T98)+SUM(V98:AB98) -> 7175.8 | AE98: 202606 | AF98: =VLOOKUP(BW98,'HR|社保明细'!C:F,4,0) -> 7460 | AG98: =VLOOKUP($BW98,'HR|社保明细'!$C:G,5,0) -> 0 | AH98: =VLOOKUP($BW98,'HR|社保明细'!$C:H,6,0) -> 596.8 | AI98: =VLOOKUP($BW98,'HR|社保明细'!$C:I,7,0) -> 149.2 | AJ98: =VLOOKUP($BW98,'HR|社保明细'!$C:J,8,0) -> 37.3 | AK98: =VLOOKUP($BW98,'HR|社保明细'!$C:K,9,0) -> 0 | AL98: =VLOOKUP($BW98,'HR|社保明细'!$C:L,10,0) -> 0 | AM98: =SUM(AH98:AL98) -> 783.3 | AS98: =AC98-AM98-SUM(AN98:AR98) -> 6392.5 | AU98: =VLOOKUP(BW98,hr.个税累计数据!C:DS,121,0) -> 21977.4 | AV98: =IF(AU98-5000*N98-VLOOKUP(A98,hr.个税累计数据!C:DT,122,0)-VLOOKUP(A98,hr.个税累计数据!C:DU,123,0)>0,AU98-5000*N98-VLOOKUP(A98,hr.个税累计数据!C:DT,122,0)-VLOOKUP(A98,hr.个税累计数据!C:DU,123,0),0) -> 0 | AW98: =VLOOKUP(BW98,hr.个税累计数据!C:DV,124,0) -> 0 | AY98: =IF(ROUND(MAX(AV98*{0.03,0.1,0.2,0.25,0.3,0.35,0.45}-{0,210,1410,2660,4410,7160,15160}*12)-AW98,2)<=0,0,ROUND(MAX(AV98*{0.03,0.1,0.2,0.25,0.3,0.35,0.45}-{0,210,1410,2660,4410,7160,15160}*12)-AW98,2)) -> 0 | AZ98: =-S98 -> -155.8 | BB98: =AC98-AM98-AY98-AX98+SUM(AZ98:BA98) -> 6236.7 | BD98: =AC98-AM98-AX98-AY98+SUM(AZ98:BA98) -> 6236.7 | BE98: =VLOOKUP($BW98,'HR|社保明细'!C:T,11,0) -> 1193.6 | BF98: =VLOOKUP($BW98,'HR|社保明细'!$C:U,12,0) -> 596.8 | BG98: =VLOOKUP($BW98,'HR|社保明细'!$C:V,13,0) -> 37.3 | BH98: =VLOOKUP($BW98,'HR|社保明细'!$C:W,14,0) -> 14.92 | BI98: =VLOOKUP($BW98,'HR|社保明细'!$C:X,15,0) -> 74.6 | BJ98: =VLOOKUP($BW98,'HR|社保明细'!$C:Y,16,0) -> 0 | BK98: =VLOOKUP($BW98,'HR|社保明细'!$C:Z,17,0) -> 0 | BL98: =SUM(BE98:BK98) -> 1917.22 | BS98: =SUM(V98:AB98) -> 300 | BT98: 1250 | BW98: =C98&I98 -> 弈工分健康史文奎 | BX98: 无社公 | BY98: 保安 | CA98: =VLOOKUP(A98,hr.个税累计数据!C:C,1,0) -> 弈工分健康史文奎 | CB98: 弈工分健康张子俊 | CD98: =H98=I98 -> TRUE
A99: =C99&I99 -> 弈工分健康胡程林 | B99: 物业外包保安 | C99: 弈工分健康 | D99: 劳务计税 | E99: 物业外包保安 | F99: 贾飞龙 | G99: 园区保安 | H99: 胡程林 | I99: 胡程林 | J99: 全日制 | K99: =AC99+BL99 -> 200 | L99: =AC99-AM99-AX99-AY99+SUM(AZ99:BA99) -> 200 | N99: 1 | U99: =SUM(O99:T99) -> 0 | AA99: 200 | AC99: =SUM(O99:T99)+SUM(V99:AB99) -> 200 | AE99: 202606 | AM99: =SUM(AH99:AL99) -> 0 | AY99: =IF(ROUND(MAX(AV99*{0.03,0.1,0.2,0.25,0.3,0.35,0.45}-{0,210,1410,2660,4410,7160,15160}*12)-AW99,2)<=0,0,ROUND(MAX(AV99*{0.03,0.1,0.2,0.25,0.3,0.35,0.45}-{0,210,1410,2660,4410,7160,15160}*12)-AW99,2)) -> 0 | AZ99: =-S99 -> 0 | BB99: =AC99-AM99-AY99-AX99+SUM(AZ99:BA99) -> 200 | BD99: =AC99-AM99-AX99-AY99+SUM(AZ99:BA99) -> 200 | BL99: =SUM(BE99:BK99) -> 0 | BS99: =SUM(V99:AB99) -> 200 | BW99: =C99&I99 -> 弈工分健康胡程林 | BX99: 无社公 | BY99: 保安 | CA99: =VLOOKUP(A99,hr.个税累计数据!C:C,1,0) -> #N/A | CB99: 弈工分健康张子俊 | CD99: =H99=I99 -> TRUE
A100: =C100&I100 -> 弈工分健康孔令波 | B100: 物业外包保安 | C100: 弈工分健康 | D100: 劳务计税 | E100: 物业外包保安 | F100: 贾飞龙 | G100: 园区保安 | H100: 孔令波 | I100: 孔令波 | J100: 全日制 | K100: =AC100+BL100 -> 100 | L100: =AC100-AM100-AX100-AY100+SUM(AZ100:BA100) -> 100 | N100: 1 | U100: =SUM(O100:T100) -> 0 | AA100: 100 | AC100: =SUM(O100:T100)+SUM(V100:AB100) -> 100 | AE100: 202606 | AM100: =SUM(AH100:AL100) -> 0 | AY100: =IF(ROUND(MAX(AV100*{0.03,0.1,0.2,0.25,0.3,0.35,0.45}-{0,210,1410,2660,4410,7160,15160}*12)-AW100,2)<=0,0,ROUND(MAX(AV100*{0.03,0.1,0.2,0.25,0.3,0.35,0.45}-{0,210,1410,2660,4410,7160,15160}*12)-AW100,2)) -> 0 | AZ100: =-S100 -> 0 | BB100: =AC100-AM100-AY100-AX100+SUM(AZ100:BA100) -> 100 | BD100: =AC100-AM100-AX100-AY100+SUM(AZ100:BA100) -> 100 | BL100: =SUM(BE100:BK100) -> 0 | BS100: =SUM(V100:AB100) -> 100 | BW100: =C100&I100 -> 弈工分健康孔令波 | BX100: 无社公 | BY100: 保安 | CA100: =VLOOKUP(A100,hr.个税累计数据!C:C,1,0) -> #N/A | CB100: 弈工分健康张子俊 | CD100: =H100=I100 -> TRUE
A101: =C101&I101 -> 弈工分健康姚伟 | B101: 物业外包保安 | C101: 弈工分健康 | D101: 劳务计税 | E101: 物业外包保安 | F101: 贾飞龙 | G101: 园区保安 | H101: 姚伟 | I101: 姚伟 | J101: 全日制 | K101: =AC101+BL101 -> 200 | L101: =AC101-AM101-AX101-AY101+SUM(AZ101:BA101) -> 200 | N101: 1 | U101: =SUM(O101:T101) -> 0 | AA101: 200 | AC101: =SUM(O101:T101)+SUM(V101:AB101) -> 200 | AE101: 202606 | AM101: =SUM(AH101:AL101) -> 0 | AY101: =IF(ROUND(MAX(AV101*{0.03,0.1,0.2,0.25,0.3,0.35,0.45}-{0,210,1410,2660,4410,7160,15160}*12)-AW101,2)<=0,0,ROUND(MAX(AV101*{0.03,0.1,0.2,0.25,0.3,0.35,0.45}-{0,210,1410,2660,4410,7160,15160}*12)-AW101,2)) -> 0 | AZ101: =-S101 -> 0 | BB101: =AC101-AM101-AY101-AX101+SUM(AZ101:BA101) -> 200 | BD101: =AC101-AM101-AX101-AY101+SUM(AZ101:BA101) -> 200 | BL101: =SUM(BE101:BK101) -> 0 | BS101: =SUM(V101:AB101) -> 200 | BW101: =C101&I101 -> 弈工分健康姚伟 | BX101: 无社公 | BY101: 保安 | CA101: =VLOOKUP(A101,hr.个税累计数据!C:C,1,0) -> #N/A | CB101: 弈工分健康张子俊 | CD101: =H101=I101 -> TRUE
...

Sheet Sheet3
E1: 税
A2: 开弈投资 | B2: 戴琼琪 | C2: 开弈投资戴琼琪 | E2: 351
A3: 弈工分健康 | B3: 金学忠 | C3: 弈工分健康金学忠 | E3: 237
A4: 开弈信息 | B4: 杨晓璐 | C4: 开弈信息杨晓璐 | E4: 10.62
A5: 开弈信息 | B5: 王力 | C5: 开弈信息王力 | E5: 180
A6: 弈工分信息 | B6: 姚娟 | C6: 弈工分信息姚娟 | E6: 7543.96
A7: 开弈人才 | B7: 罗国秋 | C7: 开弈人才罗国秋 | E7: -24
A8: 天津英才 | B8: 陈一卓 | C8: 天津英才陈一卓 | E8: 0.01
A9: 开弈投资 | B9: 黄欢欢 | C9: 开弈投资黄欢欢 | E9: -24.98
A10: 弈工分信息 | B10: 方有保 | C10: 弈工分信息方有保 | E10: 350.54
A11: 开弈信息 | B11: 贺知奕 | C11: =A11&B11 -> 开弈信息贺知奕 | E11: 19.5
A14: 开弈信息贺知奕 | C14: 1125 | D14: 1962.8 | E14: 250 | F14: 250
A15: 开弈人才戚珏琳 | C15: 819.5 | D15: 1645.2 | E15: -48 | F15: -48
A16: 开弈人才朱馨怡 | C16: 905.5 | D16: 1731.2 | E16: 86 | F16: 86
A17: 开弈人才舒雯 | C17: 905.5 | D17: 1731.2 | E17: 86 | F17: 86

Sheet HR|社保明细
A1: 公司 | B1: 姓名 | C1: key | D1: 社保key | E1: 标志 | F1: 社保基数 | G1: 公积金基数 | H1: 个人部分 | M1: 企业部分 | U1: 比例
H2: 养老 | I2: 医疗 | J2: 失业 | K2: 公积金 | L2: 补充公积金 | M2: 养老 | N2: 医疗 | O2: 失业 | P2: 工伤 | Q2: 生育 | R2: 公积金 | S2: 补充公积金 | T2: 商业保险 | U2: 养老 | V2: 失业 | W2: 工伤 | X2: 生育 | Y2: 医疗 | Z2: 正常部份(7%)-公司 | AA2: 养老保险 | AB2: 医疗保险 | AC2: 附加 | AD2: 失业保险 | AE2: 正常部份(7%)-个人 | AF2: 补充公积金比例 | AG2: 个人福利合计 | AH2: 企业福利合计 | AI2: 合计 | AJ2: 失业基数 | AK2: 医疗+剩余基数 | AL2: 外地 | AM2: 有社保 | AN2: 有公积金
A3: 北京点才 | B3: 孟庆芳 | C3: =A3&B3 -> 北京点才孟庆芳 | D3: 暂无 | F3: 0 | G3: 0 | H3: =IF(OR($D3={"开弈信息","开弈投资","开弈人才","开弈营销","开弈人力资源","弈工分企业外包","开弈企业服务外包"}),ROUNDUP(TRUNC($F3*AA3,2),1),ROUND($F3*AA3,2)) -> 0 | I3: =IF(OR($D3={"开弈信息","开弈投资","开弈人才","开弈营销","开弈人力资源","弈工分企业外包","开弈企业服务外包"}),ROUNDUP(TRUNC($F3*AB3,2),1)+AC3,ROUND($F3*AB3,2)+AC3) -> 0 | J3: =IF(OR($D3={"开弈信息","开弈投资","开弈人才","开弈营销","开弈人力资源","弈工分企业外包","开弈企业服务外包"}),ROUNDUP(TRUNC($F3*AD3,2),1),ROUND($F3*AD3,2)) -> 0 | K3: =IF(D3="深圳",ROUND(G3*AE3,1),ROUND(G3*AE3,0)) -> 0 | L3: =ROUND(G3*AF3,0) -> 0 | M3: =IF(OR($D3={"开弈信息","开弈投资","开弈人才","开弈营销","开弈人力资源","弈工分企业外包","开弈企业服务外包"}),ROUNDUP(TRUNC($F3*U3,2),1),ROUND($F3*U3,2)) -> 0 | N3: =IF(OR($D3={"开弈信息","开弈投资","开弈人才","开弈营销","开弈人力资源","弈工分企业外包","开弈企业服务外包"}),ROUNDUP(TRUNC($F3*Y3,2),1),ROUND($F3*Y3,2)) -> 0 | O3: =IF(OR($D3={"开弈信息","开弈投资","开弈人才","开弈营销","开弈人力资源","弈工分企业外包","开弈企业服务外包"}),ROUNDUP(TRUNC($F3*V3,2),1),ROUND($F3*V3,2)) -> 0 | P3: =IF(OR($D3={"开弈信息","开弈投资","开弈人才","开弈营销","开弈人力资源","弈工分企业外包","开弈企业服务外包"}),ROUNDUP(TRUNC($F3*W3,2),1),ROUND($F3*W3,2)) -> 0 | Q3: =IF(OR($D3={"开弈信息","开弈投资","开弈人才","开弈营销","开弈人力资源","弈工分企业外包","开弈企业服务外包"}),ROUNDUP(TRUNC($F3*X3,2),1),ROUND($F3*X3,2)) -> 0 | R3: =K3 -> 0 | S3: =L3 -> 0 | U3: =VLOOKUP($D3,'HR|社保政策'!$A:P,6,0) -> 0 | V3: =VLOOKUP($D3,'HR|社保政策'!$A:Q,7,0) -> 0 | W3: =VLOOKUP($D3,'HR|社保政策'!$A:R,8,0) -> 0 | X3: =VLOOKUP($D3,'HR|社保政策'!$A:S,9,0) -> 0 | Y3: =VLOOKUP($D3,'HR|社保政策'!$A:T,10,0) -> 0 | Z3: =VLOOKUP($D3,'HR|社保政策'!$A:U,11,0) -> 0 | AA3: =VLOOKUP($D3,'HR|社保政策'!$A:V,12,0) -> 0 | AB3: =VLOOKUP($D3,'HR|社保政策'!$A:W,13,0) -> 0 | AC3: =VLOOKUP($D3,'HR|社保政策'!$A:X,14,0) -> 0 | AD3: =VLOOKUP($D3,'HR|社保政策'!$A:Y,15,0) -> 0 | AE3: =VLOOKUP($D3,'HR|社保政策'!$A:Z,16,0) -> 0 | AG3: =H3+I3+J3+K3+L3 -> 0 | AH3: =M3+N3+O3+P3+Q3+R3+S3 -> 0 | AI3: =AG3+AH3 -> 0 | AL3: =A3 -> 北京点才 | AO3: =VLOOKUP(B3,薪酬明细!I:I,1,0) -> 孟庆芳 | AP3: =VLOOKUP(C3,薪酬明细!A:A,1,0) -> 北京点才孟庆芳 | AQ3: =A3&B3 -> 北京点才孟庆芳 | AW3: =VLOOKUP(C3,薪酬明细!A:A,2,0) -> #REF! | AX3: =A3=D3 -> FALSE | AY3: =AQ3=C3 -> TRUE
A4: 北京点才 | B4: 尚庆军 | C4: =A4&B4 -> 北京点才尚庆军 | D4: 点才残疾人 | E4: 残疾人 | F4: 7162 | G4: 2540 | H4: =IF(OR($D4={"开弈信息","开弈投资","开弈人才","开弈营销","开弈人力资源","弈工分企业外包","开弈企业服务外包"}),ROUNDUP(TRUNC($F4*AA4,2),1),ROUND($F4*AA4,2)) -> 572.96 | I4: 146.24 | J4: =IF(OR($D4={"开弈信息","开弈投资","开弈人才","开弈营销","开弈人力资源","弈工分企业外包","开弈企业服务外包"}),ROUNDUP(TRUNC($F4*AD4,2),1),ROUND($F4*AD4,2)) -> 35.81 | K4: 0 | L4: =ROUND(G4*AF4,0) -> 0 | M4: =IF(OR($D4={"开弈信息","开弈投资","开弈人才","开弈营销","开弈人力资源","弈工分企业外包","开弈企业服务外包"}),ROUNDUP(TRUNC($F4*U4,2),1),ROUND($F4*U4,2)) -> 1145.92 | N4: 644.58 | O4: =IF(OR($D4={"开弈信息","开弈投资","开弈人才","开弈营销","开弈人力资源","弈工分企业外包","开弈企业服务外包"}),ROUNDUP(TRUNC($F4*V4,2),1),ROUND($F4*V4,2)) -> 35.81 | P4: 28.65 | Q4: 57.3 | R4: =ROUND(G4*0.12,0) -> 305 | S4: =L4 -> 0 | U4: =VLOOKUP($D4,'HR|社保政策'!$A:P,6,0) -> 0.16 | V4: =VLOOKUP($D4,'HR|社保政策'!$A:Q,7,0) -> 0.005 | W4: =VLOOKUP($D4,'HR|社保政策'!$A:R,8,0) -> 0.002 | X4: =VLOOKUP($D4,'HR|社保政策'!$A:S,9,0) -> 0.008 | Y4: =VLOOKUP($D4,'HR|社保政策'!$A:T,10,0) -> 0.09 | Z4: =VLOOKUP($D4,'HR|社保政策'!$A:U,11,0) -> 0.12 | AA4: =VLOOKUP($D4,'HR|社保政策'!$A:V,12,0) -> 0.08 | AB4: =VLOOKUP($D4,'HR|社保政策'!$A:W,13,0) -> 0.02 | AC4: =VLOOKUP($D4,'HR|社保政策'!$A:X,14,0) -> 3 | AD4: =VLOOKUP($D4,'HR|社保政策'!$A:Y,15,0) -> 0.005 | AE4: =VLOOKUP($D4,'HR|社保政策'!$A:Z,16,0) -> 0.12 | AG4: =H4+I4+J4+K4+L4 -> 755.01 | AH4: =M4+N4+O4+P4+Q4+R4+S4 -> 2217.26 | AI4: =AG4+AH4 -> 2972.27 | AJ4: 4713 | AK4: 5360 | AL4: =A4 -> 北京点才 | AM4: 有 | AN4: 有 | AO4: =VLOOKUP(B4,薪酬明细!I:I,1,0) -> 尚庆军 | AP4: =VLOOKUP(C4,薪酬明细!A:A,1,0) -> 北京点才尚庆军 | AQ4: =A4&B4 -> 北京点才尚庆军 | AW4: =VLOOKUP(C4,薪酬明细!A:A,2,0) -> #REF! | AX4: =A4=D4 -> FALSE | AY4: =AQ4=C4 -> TRUE
A5: 北京点才 | B5: 杨崴 | C5: =A5&B5 -> 北京点才杨崴 | D5: 点才 | F5: 7162 | G5: 7000 | H5: =IF(OR($D5={"开弈信息","开弈投资","开弈人才","开弈营销","开弈人力资源","弈工分企业外包","开弈企业服务外包"}),ROUNDUP(TRUNC($F5*AA5,2),1),ROUND($F5*AA5,2)) -> 572.96 | I5: 146.24 | J5: =IF(OR($D5={"开弈信息","开弈投资","开弈人才","开弈营销","开弈人力资源","弈工分企业外包","开弈企业服务外包"}),ROUNDUP(TRUNC($F5*AD5,2),1),ROUND($F5*AD5,2)) -> 35.81 | K5: =IF(D5="深圳",ROUND(G5*AE5,1),ROUND(G5*AE5,0)) -> 840 | L5: =ROUND(G5*AF5,0) -> 0 | M5: =IF(OR($D5={"开弈信息","开弈投资","开弈人才","开弈营销","开弈人力资源","弈工分企业外包","开弈企业服务外包"}),ROUNDUP(TRUNC($F5*U5,2),1),ROUND($F5*U5,2)) -> 1145.92 | N5: 644.58 | O5: =IF(OR($D5={"开弈信息","开弈投资","开弈人才","开弈营销","开弈人力资源","弈工分企业外包","开弈企业服务外包"}),ROUNDUP(TRUNC($F5*V5,2),1),ROUND($F5*V5,2)) -> 35.81 | P5: 28.65 | Q5: 57.3 | R5: =K5 -> 840 | S5: =L5 -> 0 | U5: =VLOOKUP($D5,'HR|社保政策'!$A:P,6,0) -> 0.16 | V5: =VLOOKUP($D5,'HR|社保政策'!$A:Q,7,0) -> 0.005 | W5: =VLOOKUP($D5,'HR|社保政策'!$A:R,8,0) -> 0.002 | X5: =VLOOKUP($D5,'HR|社保政策'!$A:S,9,0) -> 0.008 | Y5: =VLOOKUP($D5,'HR|社保政策'!$A:T,10,0) -> 0.09 | Z5: =VLOOKUP($D5,'HR|社保政策'!$A:U,11,0) -> 0.12 | AA5: =VLOOKUP($D5,'HR|社保政策'!$A:V,12,0) -> 0.08 | AB5: =VLOOKUP($D5,'HR|社保政策'!$A:W,13,0) -> 0.02 | AC5: =VLOOKUP($D5,'HR|社保政策'!$A:X,14,0) -> 3 | AD5: =VLOOKUP($D5,'HR|社保政策'!$A:Y,15,0) -> 0.005 | AE5: =VLOOKUP($D5,'HR|社保政策'!$A:Z,16,0) -> 0.12 | AG5: =H5+I5+J5+K5+L5 -> 1595.01 | AH5: =M5+N5+O5+P5+Q5+R5+S5 -> 2752.26 | AI5: =AG5+AH5 -> 4347.27 | AJ5: 6500 | AK5: 6500 | AL5: =A5 -> 北京点才 | AM5: 有 | AN5: 有 | AO5: =VLOOKUP(B5,薪酬明细!I:I,1,0) -> 杨崴 | AP5: =VLOOKUP(C5,薪酬明细!A:A,1,0) -> 北京点才杨崴 | AQ5: =A5&B5 -> 北京点才杨崴 | AW5: =VLOOKUP(C5,薪酬明细!A:A,2,0) -> #REF! | AX5: =A5=D5 -> FALSE | AY5: =AQ5=C5 -> TRUE
A6: 北京点才 | B6: 王倩 | C6: =A6&B6 -> 北京点才王倩 | D6: 暂无 | F6: 0 | G6: 0 | H6: =IF(OR($D6={"开弈信息","开弈投资","开弈人才","开弈营销","开弈人力资源","弈工分企业外包","开弈企业服务外包","智名"}),ROUNDUP(TRUNC($F6*AA6,2),1),ROUND($F6*AA6,2)) -> 0 | I6: =IF(OR($D6={"开弈信息","开弈投资","开弈人才","开弈营销","开弈人力资源","弈工分企业外包","开弈企业服务外包"}),ROUNDUP(TRUNC($F6*AB6,2),1)+AC6,ROUND($F6*AB6,2)+AC6) -> 0 | J6: =IF(OR($D6={"开弈信息","开弈投资","开弈人才","开弈营销","开弈人力资源","弈工分企业外包","开弈企业服务外包"}),ROUNDUP(TRUNC($F6*AD6,2),1),ROUND($F6*AD6,2)) -> 0 | K6: =IF(D6="深圳",ROUND(G6*AE6,1),ROUND(G6*AE6,0)) -> 0 | L6: =ROUND(G6*AF6,0) -> 0 | M6: =IF(OR($D6={"开弈信息","开弈投资","开弈人才","开弈营销","开弈人力资源","弈工分企业外包","开弈企业服务外包"}),ROUNDUP(TRUNC($F6*U6,2),1),ROUND($F6*U6,2)) -> 0 | N6: =IF(OR($D6={"开弈信息","开弈投资","开弈人才","开弈营销","开弈人力资源","弈工分企业外包","开弈企业服务外包"}),ROUNDUP(TRUNC($F6*Y6,2),1),ROUND($F6*Y6,2)) -> 0 | O6: =IF(OR($D6={"开弈信息","开弈投资","开弈人才","开弈营销","开弈人力资源","弈工分企业外包","开弈企业服务外包"}),ROUNDUP(TRUNC($F6*V6,2),1),ROUND($F6*V6,2)) -> 0 | P6: =IF(OR($D6={"开弈信息","开弈投资","开弈人才","开弈营销","开弈人力资源","弈工分企业外包","开弈企业服务外包"}),ROUNDUP(TRUNC($F6*W6,2),1),ROUND($F6*W6,2)) -> 0 | Q6: =IF(OR($D6={"开弈信息","开弈投资","开弈人才","开弈营销","开弈人力资源","弈工分企业外包","开弈企业服务外包"}),ROUNDUP(TRUNC($F6*X6,2),1),ROUND($F6*X6,2)) -> 0 | R6: =K6 -> 0 | S6: =L6 -> 0 | U6: =VLOOKUP($D6,'HR|社保政策'!$A:P,6,0) -> 0 | V6: =VLOOKUP($D6,'HR|社保政策'!$A:Q,7,0) -> 0 | W6: =VLOOKUP($D6,'HR|社保政策'!$A:R,8,0) -> 0 | X6: =VLOOKUP($D6,'HR|社保政策'!$A:S,9,0) -> 0 | Y6: =VLOOKUP($D6,'HR|社保政策'!$A:T,10,0) -> 0 | Z6: =VLOOKUP($D6,'HR|社保政策'!$A:U,11,0) -> 0 | AA6: =VLOOKUP($D6,'HR|社保政策'!$A:V,12,0) -> 0 | AB6: =VLOOKUP($D6,'HR|社保政策'!$A:W,13,0) -> 0 | AC6: =VLOOKUP($D6,'HR|社保政策'!$A:X,14,0) -> 0 | AD6: =VLOOKUP($D6,'HR|社保政策'!$A:Y,15,0) -> 0 | AE6: =VLOOKUP($D6,'HR|社保政策'!$A:Z,16,0) -> 0 | AG6: =H6+I6+J6+K6+L6 -> 0 | AH6: =M6+N6+O6+P6+Q6+R6+S6 -> 0 | AI6: =AG6+AH6 -> 0 | AL6: =A6 -> 北京点才 | AO6: =VLOOKUP(B6,薪酬明细!I:I,1,0) -> 王倩 | AP6: =VLOOKUP(C6,薪酬明细!A:A,1,0) -> 北京点才王倩 | AQ6: =A6&B6 -> 北京点才王倩 | AW6: =VLOOKUP(C6,薪酬明细!A:A,2,0) -> #REF! | AX6: =A6=D6 -> FALSE | AY6: =AQ6=C6 -> TRUE
A7: 开博人才 | B7: 王倩 | C7: =A7&B7 -> 开博人才王倩 | D7: 开博人才 | F7: 0 | G7: 0 | H7: =ROUND($F7*AA7,2) -> 0 | I7: =ROUND($F7*AB7,2) -> 0 | J7: =ROUND($F7*AD7,2) -> 0 | K7: =IF(D7="深圳",ROUND(G7*AE7,1),ROUND(G7*AE7,0)) -> 0 | L7: =ROUND(G7*AF7,0) -> 0 | M7: =ROUND($F7*U7,2) -> 0 | N7: =ROUND($F7*Y7,2) -> 0 | O7: =ROUND($F7*V7,2) -> 0 | P7: =ROUND($F7*W7,2) -> 0 | Q7: =ROUND($F7*X7,2) -> 0 | R7: =K7 -> 0 | S7: =L7 -> 0 | U7: =VLOOKUP($D7,'HR|社保政策'!$A:P,6,0) -> 0.16 | V7: =VLOOKUP($D7,'HR|社保政策'!$A:Q,7,0) -> 0.005 | W7: =VLOOKUP($D7,'HR|社保政策'!$A:R,8,0) -> 0.0016 | X7: =VLOOKUP($D7,'HR|社保政策'!$A:S,9,0) -> 0.01 | Y7: 0.08 | Z7: =VLOOKUP($D7,'HR|社保政策'!$A:U,11,0) -> 0.07 | AA7: =VLOOKUP($D7,'HR|社保政策'!$A:V,12,0) -> 0.08 | AB7: =VLOOKUP($D7,'HR|社保政策'!$A:W,13,0) -> 0.02 | AC7: =VLOOKUP($D7,'HR|社保政策'!$A:X,14,0) -> 0 | AD7: =VLOOKUP($D7,'HR|社保政策'!$A:Y,15,0) -> 0.005 | AE7: =VLOOKUP($D7,'HR|社保政策'!$A:Z,16,0) -> 0.07 | AG7: =H7+I7+J7+K7+L7 -> 0 | AH7: =M7+N7+O7+P7+Q7+R7+S7 -> 0 | AI7: =AG7+AH7 -> 0 | AO7: =VLOOKUP(B7,薪酬明细!I:I,1,0) -> 王倩 | AP7: =VLOOKUP(C7,薪酬明细!A:A,1,0) -> 开博人才王倩 | AQ7: =A7&B7 -> 开博人才王倩 | AR7: 0 | AS7: =H7+I7+J7+K7+L7 -> 0 | AT7: =AR7-AS7 -> 0 | AU7: 0 | AV7: =AU7-M7-N7-O7-P7-Q7-R7-S7 -> 0 | AW7: =VLOOKUP(C7,薪酬明细!A:A,2,0) -> #REF! | AX7: =A7=D7 -> TRUE | AY7: =AQ7=C7 -> TRUE
A8: 开弈人力资源 | B8: 葛豪平 | C8: =A8&B8 -> 开弈人力资源葛豪平 | D8: 开弈人力资源 | F8: 10000 | G8: 10000 | H8: =ROUND($F8*AA8,2) -> 800 | I8: =ROUND($F8*AB8,2) -> 200 | J8: =ROUND($F8*AD8,2) -> 50 | K8: =IF(D8="深圳",ROUND(G8*AE8,1),ROUND(G8*AE8,0)) -> 700 | L8: =ROUND(G8*AF8,0) -> 500 | M8: =ROUND($F8*U8,2) -> 1600 | N8: =ROUND($F8*Y8,2) -> 800 | O8: =ROUND($F8*V8,2) -> 50 | P8: =ROUND($F8*W8,2) -> 32 | Q8: =ROUND($F8*X8,2) -> 100 | R8: =K8 -> 700 | S8: =L8 -> 500 | U8: =VLOOKUP($D8,'HR|社保政策'!$A:P,6,0) -> 0.16 | V8: =VLOOKUP($D8,'HR|社保政策'!$A:Q,7,0) -> 0.005 | W8: =VLOOKUP($D8,'HR|社保政策'!$A:R,8,0) -> 0.0032 | X8: =VLOOKUP($D8,'HR|社保政策'!$A:S,9,0) -> 0.01 | Y8: 0.08 | Z8: =VLOOKUP($D8,'HR|社保政策'!$A:U,11,0) -> 0.07 | AA8: =VLOOKUP($D8,'HR|社保政策'!$A:V,12,0) -> 0.08 | AB8: =VLOOKUP($D8,'HR|社保政策'!$A:W,13,0) -> 0.02 | AC8: =VLOOKUP($D8,'HR|社保政策'!$A:X,14,0) -> 0 | AD8: =VLOOKUP($D8,'HR|社保政策'!$A:Y,15,0) -> 0.005 | AE8: =VLOOKUP($D8,'HR|社保政策'!$A:Z,16,0) -> 0.07 | AF8: 0.05 | AG8: =H8+I8+J8+K8+L8 -> 2250 | AH8: =M8+N8+O8+P8+Q8+R8+S8 -> 3782 | AI8: =AG8+AH8 -> 6032 | AM8: 有 | AN8: 有 | AO8: =VLOOKUP(B8,薪酬明细!I:I,1,0) -> 葛豪平 | AP8: =VLOOKUP(C8,薪酬明细!A:A,1,0) -> 开弈人力资源葛豪平 | AQ8: =A8&B8 -> 开弈人力资源葛豪平 | AR8: 2250 | AS8: =H8+I8+J8+K8+L8 -> 2250 | AT8: =AR8-AS8 -> 0 | AU8: 3866 | AV8: =AU8-M8-N8-O8-P8-Q8-R8-S8 -> 84 | AW8: =VLOOKUP(C8,薪酬明细!A:A,2,0) -> #REF! | AX8: =A8=D8 -> TRUE | AY8: =AQ8=C8 -> TRUE
A9: 开弈人力资源 | B9: 闫秀文 | C9: =A9&B9 -> 开弈人力资源闫秀文 | D9: 开弈人力资源 | E9: 残疾人 | F9: 7460 | H9: =ROUND($F9*AA9,2) -> 596.8 | I9: =ROUND($F9*AB9,2) -> 149.2 | J9: =ROUND($F9*AD9,2) -> 37.3 | K9: =IF(D9="深圳",ROUND(G9*AE9,1),ROUND(G9*AE9,0)) -> 0 | L9: =ROUND(G9*AF9,0) -> 0 | M9: =ROUND($F9*U9,2) -> 1193.6 | N9: =ROUND($F9*Y9,2) -> 596.8 | O9: =ROUND($F9*V9,2) -> 37.3 | P9: =ROUND($F9*W9,2) -> 23.87 | Q9: =ROUND($F9*X9,2) -> 74.6 | R9: =K9 -> 0 | S9: =L9 -> 0 | U9: =VLOOKUP($D9,'HR|社保政策'!$A:P,6,0) -> 0.16 | V9: =VLOOKUP($D9,'HR|社保政策'!$A:Q,7,0) -> 0.005 | W9: =VLOOKUP($D9,'HR|社保政策'!$A:R,8,0) -> 0.0032 | X9: =VLOOKUP($D9,'HR|社保政策'!$A:S,9,0) -> 0.01 | Y9: 0.08 | Z9: =VLOOKUP($D9,'HR|社保政策'!$A:U,11,0) -> 0.07 | AA9: =VLOOKUP($D9,'HR|社保政策'!$A:V,12,0) -> 0.08 | AB9: =VLOOKUP($D9,'HR|社保政策'!$A:W,13,0) -> 0.02 | AC9: =VLOOKUP($D9,'HR|社保政策'!$A:X,14,0) -> 0 | AD9: =VLOOKUP($D9,'HR|社保政策'!$A:Y,15,0) -> 0.005 | AE9: =VLOOKUP($D9,'HR|社保政策'!$A:Z,16,0) -> 0.07 | AG9: =H9+I9+J9+K9+L9 -> 783.3 | AH9: =M9+N9+O9+P9+Q9+R9+S9 -> 1926.17 | AI9: =AG9+AH9 -> 2709.47 | AM9: 有 | AO9: =VLOOKUP(B9,薪酬明细!I:I,1,0) -> 闫秀文 | AP9: =VLOOKUP(C9,薪酬明细!A:A,1,0) -> 开弈人力资源闫秀文 | AQ9: =A9&B9 -> 开弈人力资源闫秀文 | AR9: 684.6 | AS9: =H9+I9+J9+K9+L9 -> 783.3 | AT9: =AR9-AS9 -> -98.7 | AU9: 1744.5 | AV9: =AU9-M9-N9-O9-P9-Q9-R9-S9 -> -181.67 | AW9: =VLOOKUP(C9,薪酬明细!A:A,2,0) -> #REF! | AX9: =A9=D9 -> TRUE | AY9: =AQ9=C9 -> TRUE
A10: 开弈人力资源 | B10: 姜启志 | C10: =A10&B10 -> 开弈人力资源姜启志 | D10: 开弈人力资源 | E10: 残疾人 | F10: 7460 | H10: =ROUND($F10*AA10,2) -> 596.8 | I10: =ROUND($F10*AB10,2) -> 149.2 | J10: =ROUND($F10*AD10,2) -> 37.3 | K10: =IF(D10="深圳",ROUND(G10*AE10,1),ROUND(G10*AE10,0)) -> 0 | L10: =ROUND(G10*AF10,0) -> 0 | M10: =ROUND($F10*U10,2) -> 1193.6 | N10: =ROUND($F10*Y10,2) -> 596.8 | O10: =ROUND($F10*V10,2) -> 37.3 | P10: =ROUND($F10*W10,2) -> 23.87 | Q10: =ROUND($F10*X10,2) -> 74.6 | R10: =K10 -> 0 | S10: =L10 -> 0 | U10: =VLOOKUP($D10,'HR|社保政策'!$A:P,6,0) -> 0.16 | V10: =VLOOKUP($D10,'HR|社保政策'!$A:Q,7,0) -> 0.005 | W10: =VLOOKUP($D10,'HR|社保政策'!$A:R,8,0) -> 0.0032 | X10: =VLOOKUP($D10,'HR|社保政策'!$A:S,9,0) -> 0.01 | Y10: 0.08 | Z10: =VLOOKUP($D10,'HR|社保政策'!$A:U,11,0) -> 0.07 | AA10: =VLOOKUP($D10,'HR|社保政策'!$A:V,12,0) -> 0.08 | AB10: =VLOOKUP($D10,'HR|社保政策'!$A:W,13,0) -> 0.02 | AC10: =VLOOKUP($D10,'HR|社保政策'!$A:X,14,0) -> 0 | AD10: =VLOOKUP($D10,'HR|社保政策'!$A:Y,15,0) -> 0.005 | AE10: =VLOOKUP($D10,'HR|社保政策'!$A:Z,16,0) -> 0.07 | AG10: =H10+I10+J10+K10+L10 -> 783.3 | AH10: =M10+N10+O10+P10+Q10+R10+S10 -> 1926.17 | AI10: =AG10+AH10 -> 2709.47 | AM10: 有 | AO10: =VLOOKUP(B10,薪酬明细!I:I,1,0) -> 姜启志 | AP10: =VLOOKUP(C10,薪酬明细!A:A,1,0) -> 开弈人力资源姜启志 | AQ10: =A10&B10 -> 开弈人力资源姜启志 | AR10: 684.6 | AS10: =H10+I10+J10+K10+L10 -> 783.3 | AT10: =AR10-AS10 -> -98.7 | AU10: 1744.5 | AV10: =AU10-M10-N10-O10-P10-Q10-R10-S10 -> -181.67 | AW10: =VLOOKUP(C10,薪酬明细!A:A,2,0) -> #REF! | AX10: =A10=D10 -> TRUE | AY10: =AQ10=C10 -> TRUE
